Workbook
Name ActNos: '[1]Actual Numbers'!$A$1:$M$53
Name asd: [2]WorkingPivot!$T:$Z
Name BasePoint: [3]WorkingPivots!$O$5
Name BrCodeBrName: [3]WorkingPivots!$AM$4:$AP$2503
Name DivisorBln: [3]WorkingPivots!$E$1
Name DivisorMn: [3]WorkingPivots!$D$1
Name DivisorThou: [4]WorkingPivots!$C$1
Name Down: '[5]Region wise'!$T$4
Name Equal: '[5]Region wise'!$S$4
Name gh: '[6]Snap-Shot'!$G$3
Name LastDay: [3]WorkingPivots!$M$5
Name LastMonth: [3]WorkingPivots!$N$5
Name LastWeekTrend: [3]WorkingPivots!$A$5:$H$24
Name LastWeekTrendInput: [3]Dashboard!$D$14
Name LastWeekTrendList: [3]WorkingPivots!$A$5:$A$24
Name LiabOD: '[1]Total Liab & OD'!$A$2:$Q$52
Name Link_AreaWise: [7]!Table_CategoriesMaker.accdb2[#All]
Name Link_BrWise: [7]!Table_CategoriesMaker.accdb[#Data]
Name LoV_Regions: [8]LoV!$B$1:$B$36
Name MIS_Date: '[5]Branch wise'!$B$3
Name MIS_Dt: '[9]Snap-Shot'!$G$3
Name MISDate: [4]Dashboard!$B$3
Name MTDC_BestWorst: [3]WorkingPivots!$X$4:$AC$33
Name MTDC_Input: [3]Dashboard!$D$35
Name NewBase: '[5]2015 Final Working'!$M$1:$P$1729
Name ODC_BestWorst: [3]WorkingPivots!$Q$4:$V$35
Name ODC_Dashboard: [3]Dashboard!$A$1
Name ODC_Input: [3]Dashboard!$D$23
Name Range_AreaWise: [5]WorkingPivot!$K:$Q
Name Range_FTM: [5]WorkingPivot!$B$8:$C$1638
Name Range_PWMTD: [10]br.Issuance!#REF!
Name Range_PWMTD: [10]br.Issuance!#REF!
Name Range_PWMTD: [10]br.Issuance!#REF!
Name Range_PWMTD: [10]br.Issuance!#REF!
Name Range_PWRED: [10]br.Issuance!#REF!
Name Range_PWRED: [10]br.Issuance!#REF!
Name Range_PWRED: [10]br.Issuance!#REF!
Name Range_PWRED: [10]br.Issuance!#REF!
Name Range_PWYTD: [10]br.Issuance!#REF!
Name Range_PWYTD: [10]br.Issuance!#REF!
Name Range_PWYTD: [10]br.Issuance!#REF!
Name Range_PWYTD: [10]br.Issuance!#REF!
Name Range_QTR: [5]WorkingPivot!$E$8:$F$1638
Name Range_Region: [5]WorkingPivot!$T:$Z
Name Range_YTD: [5]WorkingPivot!$H$8:$I$1638
Name RangeBMAllowance: [7]!Table_CategoriesMaker.accdb6[[#All],[Area Name]:[Eligibility]]
Name RegionInput: '[11]Main One Pager'!$D$4
Name RegionReportingLines: [12]RegionReporting!$A$1:$B$22
Name SPLM: [3]WorkingPivots!$A$39
Name SPLM_Text: [3]WorkingPivots!$A$40
Name SPLY: [3]WorkingPivots!$B$39
Name SPLY_Text: [3]WorkingPivots!$B$40
Name Static: [3]Dashboard!$X$5
Name Targets: [13]Target!$B$3:$CM$32
Name Term: [3]Dashboard!#REF!
Name Term: [3]Dashboard!#REF!
Name Term: [3]Dashboard!#REF!
Name Term: [3]Dashboard!#REF!
Name TodayStatus: [3]WorkingPivots!$L$5
Name TrendChecker: [3]WorkingPivots!$I$24

Sheet FP 2026
B3: Anum Vista
B4: Summary Sheet / Funds Position - 2026
F6: 46023 | J6: 46054 | O6: 46054 | S6: 46082
B8: Cash in Hand - Opening Balance | H8: 6442017 | L8: =+H38 -> 6352776 | Q8: =+H38 -> 6352776 | U8: =Q38 -> 6378113
B10: Inflow
C11: Maintenance | F11: =+'Recpt 2026'!D58 -> 262500 | J11: =+'Recpt 2026'!H58 -> 0 | O11: =+'Recpt 2026'!G58 -> 241500 | S11: =+'Recpt 2026'!J58 -> 171500
C12: Maintenance Shop A | F12: =+'Recpt 2026'!D61 -> 0 | J12: =+'Recpt 2026'!H61 -> 0 | O12: 0 | S12: 0
C13: Rent Community Hall | F13: =+'Recpt 2026'!D62 -> 0 | J13: =+'Recpt 2026'!H62 -> 0 | O13: 0 | S13: 0
C14: Advertisment | F14: =+'Recpt 2026'!D63+'Recpt 2026'!D64+'Recpt 2026'!D65 -> 500000 | J14: =+'Recpt 2026'!H63+'Recpt 2026'!H64+'Recpt 2026'!H65 -> 0 | O14: =+'Recpt 2026'!G63+'Recpt 2026'!G64+'Recpt 2026'!G65 -> 700000 | S14: =+'Recpt 2026'!J63+'Recpt 2026'!J64+'Recpt 2026'!J65 -> 1200000
C15: Advertisement Utility Bill Collection | F15: =+'Recpt 2026'!D67 -> 50000 | J15: =+'Recpt 2026'!H67 -> 0 | O15: 0 | S15: 0
C16: Scrap Sale | F16: =+'Recpt 2026'!D66 -> 27500 | J16: =+'Recpt 2026'!H66 -> 0 | O16: 0 | S16: 0
F17: =SUM(F11:F16) -> 840000 | J17: =SUM(J11:J16) -> 0 | O17: =SUM(O11:O16) -> 941500 | S17: =SUM(S11:S16) -> 1371500
B18: Outflow
C19: Water Tanker | F19: =+'Exp 2026'!D10 -> 0 | J19: =+'Exp 2026'!M10 -> 0 | O19: =+'Exp 2026'!F10 -> 15000 | S19: =+'Exp 2026'!H10 -> 0
C20: Salaries + Security Gurads | F20: =+'Exp 2026'!D19+'Exp 2026'!D22 -> 265000 | J20: =+'Exp 2026'!L19+'Exp 2026'!L22 -> 2 | O20: =+'Exp 2026'!F19+'Exp 2026'!F22 -> 225800 | S20: =+'Exp 2026'!H19+'Exp 2026'!H22 -> 276000
C21: Lift Work + Monthly Maintenance | F21: =+'Exp 2026'!D30 -> 21300 | J21: =+'Exp 2026'!L30 -> 0 | O21: =+'Exp 2026'!F30 -> 16500 | S21: =+'Exp 2026'!H30 -> 33000
C22: Petty Cash Expenses | F22: =+'Exp 2026'!D33 -> 15740 | J22: =+'Exp 2026'!L33 -> 0 | O22: =+'Exp 2026'!F33 -> 12560 | S22: =+'Exp 2026'!H33 -> 18170
C23: Utilities - Kelectric | F23: =+'Exp 2026'!D36 -> 226381 | J23: =+'Exp 2026'!L36 -> 0 | O23: =+'Exp 2026'!F36 -> 242468 | S23: =+'Exp 2026'!H36 -> 224818
C24: Electrical Work Expenses | F24: =+'Exp 2026'!D43 -> 34580 | J24: =+'Exp 2026'!L43 -> 0 | O24: =+'Exp 2026'!F43 -> 3640 | S24: =+'Exp 2026'!H43 -> 50110
C25: Generator & Diesel Exp | F25: =+'Exp 2026'!D49 -> 11500 | J25: =+'Exp 2026'!L49 -> 0 | O25: =+'Exp 2026'!F49 -> 53600 | S25: =+'Exp 2026'!H49 -> 92270
C26: Building Colour | F26: =+'Exp 2026'!D52 -> 0 | J26: =+'Exp 2026'!L52 -> 0 | O26: =+'Exp 2026'!F52 -> 169450 | S26: =+'Exp 2026'!H52 -> 0
C27: Building Maintenance - Others | F27: =+'Exp 2026'!D58 -> 18500 | J27: =+'Exp 2026'!L58 -> 0 | O27: =+'Exp 2026'!F58 -> 6600 | S27: =+'Exp 2026'!H58 -> 6970
C28: Play Area Expense | F28: =+'Exp 2026'!D62 -> 0 | J28: =+'Exp 2026'!L62 -> 0 | O28: =+'Exp 2026'!F62 -> 0 | S28: =+'Exp 2026'!H62 -> 15000
C29: Entertaiment Expense | F29: =+'Exp 2026'!D66 -> 0 | J29: =+'Exp 2026'!L66 -> 0 | O29: 0 | S29: =+'Exp 2026'!H66 -> 0
C30: Water - Machine and Plumbering Work | F30: =+'Exp 2026'!D78 -> 273740 | J30: =+'Exp 2026'!L78 -> 0 | O30: =+'Exp 2026'!F78 -> 83600 | S30: =+'Exp 2026'!H78 -> 5990
C31: Qurbani Expenses | F31: =+'Exp 2026'!D84 -> 0 | J31: =+'Exp 2026'!L84 -> 0 | O31: 0 | S31: =+'Exp 2026'!H84 -> 0
C32: Mosque/Ramzan Expenses | F32: =+'Exp 2026'!D91 -> 0 | J32: =+'Exp 2026'!L91 -> 0 | O32: =+'Exp 2026'!F91 -> 58445 | S32: =+'Exp 2026'!H91 -> 200230
C33: Gym Expense | F33: =+'Exp 2026'!D96 -> 0 | J33: =+'Exp 2026'!L96 -> 0 | O33: 0 | S33: =+'Exp 2026'!H96 -> 0
C34: Building Assets | F34: =+'Exp 2026'!D101 -> 50000 | J34: =+'Exp 2026'!L101 -> 0 | O34: =+'Exp 2026'!F101 -> 16000 | S34: =+'Exp 2026'!H101 -> 41000
C35: Camera, Intercom and Internet Expenses | F35: =+'Exp 2026'!D105 -> 12500 | J35: =+'Exp 2026'!L105 -> 0 | O35: =+'Exp 2026'!F105 -> 12500 | S35: =+'Exp 2026'!H105 -> 12500
F37: =SUM(F19:F36) -> 929241 | J37: =SUM(J19:J36) -> 2 | O37: =SUM(O19:O36) -> 916163 | S37: =SUM(S19:S36) -> 976058
B38: Cash in Hand - Closing Balance | H38: =H8+F17-F37 -> 6352776 | L38: =L8+J17-J37 -> 6352774 | Q38: =Q8+O17-O37 -> 6378113 | U38: =U8+S17-S37 -> 6773555
B40: Funds in Hand
C41: Danish | H41: =+'Funds Breakup'!C636 -> 2923241 | L41: =+'Funds Breakup'!G663 -> 0 | Q41: =+'Funds Breakup'!C663 -> 2923241 | U41: =+'Funds Breakup'!C690 -> 2923241
C42: Ali | H42: =+'Funds Breakup'!O636 -> 930000 | L42: =+'Funds Breakup'!S663 -> 0 | Q42: =+'Funds Breakup'!O663 -> 930000 | U42: =+'Funds Breakup'!O690 -> 930000
C43: Dilshad | H43: =+'Funds Breakup'!I636 -> 857518 | L43: =+'Funds Breakup'!M663 -> 0 | Q43: =+'Funds Breakup'!I663 -> 883823 | U43: =+'Funds Breakup'!I690 -> 1332583
C44: Asif | H44: =+'Funds Breakup'!L636 -> 1381000 | L44: =+'Funds Breakup'!P663 -> 0 | Q44: =+'Funds Breakup'!L663 -> 1381000 | U44: =+'Funds Breakup'!L690 -> 1381000
C45: Naveed | H45: =+'Funds Breakup'!F636 -> 261017 | L45: =+'Funds Breakup'!J663 -> 0 | Q45: =+'Funds Breakup'!F663 -> 260049 | U45: =+'Funds Breakup'!F690 -> 206731
H46: =SUM(H41:H45) -> 6352776 | L46: =SUM(L41:L45) -> 0 | Q46: =SUM(Q41:Q45) -> 6378113 | U46: =SUM(U41:U45) -> 6773555
H49: =H46-H38 -> 0 | L49: =L46-L38 -> -6352774 | Q49: =Q46-Q38 -> 0 | U49: =U46-U38 -> 0

Sheet Recpt 2026
B3: Anum Vista | Q3: Anum Vista
B4: Residents - Receipts - 2026 | Q4: Residents - Consolidated Oustanding Maintenance Position as of Jan 31, 2026
B5: Particulars | D5: 46023 | G5: 46054 | J5: 46082 | M5: 46113 | Q5: Appartment No. | R5: Name of Resident | S5: Monthly Maintenance | T5: Dues till Dec 31, 2025 | U5: Maintenance amunt till Mar 2026 | V5: Maintenance Recived during the Year 2026 | W5: Dues till Mar, 2026
B6: Residents Name | C6: Appartment No. | D6: Amount | E6: Receipt No. | F6: Date | G6: Amount | H6: Receipt No. | I6: Date | J6: Amount | K6: Receipt No. | L6: Date | M6: Amount | N6: Receipt No. | O6: Date
B8: Mr. Rehan | C8: 101 | D8: 28500 | E8: 229 | F8: 46028 | Q8: 101 | R8: Mr. Rehan | S8: =9500*12 -> 114000 | T8: 28500 | U8: =9500*3 -> 28500 | V8: =D8+G8+J8 -> 28500 | W8: =T8+U8-V8 -> 28500
B9: Mr. Faisal A. Khan | C9: 102 | D9: 14000 | E9: 239 | F9: 46030 | G9: 7000 | H9: 263 | I9: 46058 | J9: 7000 | K9: 287 | L9: 46085 | Q9: 102 | R9: Mr. Faisal A. Khan | S9: =7000*12 -> 84000 | T9: 28000 | U9: =7000*3 -> 21000 | V9: =D9+G9+J9 -> 28000 | W9: =T9+U9-V9 -> 21000
B10: Mrs. Rashid | C10: 103 | G10: 5000 | H10: 265 | I10: 46059 | Q10: 103 | R10: Mrs. Rashid | S10: =2500*12 -> 30000 | T10: 0 | U10: =2500*3 -> 7500 | V10: =D10+G10+J10 -> 5000 | W10: =T10+U10-V10 -> 2500
B11: Mr. Dilshad | C11: 104 | D11: 7000 | E11: 237 | F11: 46029 | G11: 7000 | H11: 254 | I11: 46055 | J11: 7000 | K11: 285 | L11: 46083 | Q11: 104 | R11: Mr. Dilshad | S11: =7000*12 -> 84000 | T11: 0 | U11: =7000*3 -> 21000 | V11: =D11+G11+J11 -> 21000 | W11: =T11+U11-V11 -> 0
B13: Mr. Ammar | C13: 201 | D13: 5500 | E13: 235 | F13: 46028 | G13: 5500 | H13: 255 | I13: 46055 | J13: 5500 | K13: 284 | L13: 46082 | M13: 5500 | N13: 308 | O13: 46114 | Q13: 201 | R13: Mr. Ammar | S13: =5500*12 -> 66000 | T13: 0 | U13: =5500*3 -> 16500 | V13: =D13+G13+J13 -> 16500 | W13: =T13+U13-V13 -> 0
B14: Mr. Faisal | C14: 202 | D14: 21000 | E14: 245 | F14: 46034 | Q14: 202 | R14: Mr. Faisal | S14: =7000*12 -> 84000 | T14: 14000 | U14: =7000+9000+9000 -> 25000 | V14: =D14+G14+J14 -> 21000 | W14: =T14+U14-V14 -> 18000
B15: Mr. Bakshish | C15: 203 | D15: 7000 | E15: 241 | F15: 46030 | Q15: 203 | R15: Mr. Bakshish | S15: =7000*12 -> 84000 | T15: 0 | U15: =7000*3 -> 21000 | V15: =D15+G15+J15 -> 7000 | W15: =T15+U15-V15 -> 14000
B16: Mr. Taimur | C16: 204 | D16: 7500 | E16: 251 | F16: 46052 | G16: 7500 | H16: 281 | I16: 46079 | J16: 7500 | K16: 302 | L16: 46101 | Q16: 204 | R16: Mr. Taimur | S16: =7500*12 -> 90000 | T16: 0 | U16: =7500*3 -> 22500 | V16: =D16+G16+J16 -> 22500 | W16: =T16+U16-V16 -> 0
B18: Mr. Zia | C18: 301 | D18: 5500 | E18: 233 | F18: 46027 | G18: 5500 | H18: 264 | I18: 46059 | J18: 5500 | K18: 294 | L18: 46088 | Q18: 301 | R18: Mr. Zia | S18: =5500*12 -> 66000 | T18: 0 | U18: =5500*3 -> 16500 | V18: =D18+G18+J18 -> 16500 | W18: =T18+U18-V18 -> 0
B19: Mr. Ashraf | C19: 302 | G19: 33000 | H19: 279 | I19: 46079 | Q19: 302 | R19: Mr. Ashraf | S19: =5500*12 -> 66000 | T19: 0 | U19: =5500*3 -> 16500 | V19: =D19+G19+J19 -> 33000 | W19: =T19+U19-V19 -> -16500
B20: Mr. Mubeen | C20: 303 | D20: 9000 | E20: 236 | F20: 46028 | G20: 9000 | H20: 269 | I20: 46062 | J20: 9000 | K20: 288 | L20: 46085 | Q20: 303 | R20: Mr. Mubeen | S20: =9000*12 -> 108000 | T20: 0 | U20: =9000*3 -> 27000 | V20: =D20+G20+J20 -> 27000 | W20: =T20+U20-V20 -> 0
B21: Mr. Farhan | C21: 304 | D21: 5500 | E21: 234 | F21: 46028 | G21: 5500 | H21: 261 | I21: 46058 | J21: 5500 | K21: 293 | L21: 46088 | Q21: 304 | R21: Mr. Farhan | S21: =5500*12 -> 66000 | T21: 0 | U21: =5500*3 -> 16500 | V21: =D21+G21+J21 -> 16500 | W21: =T21+U21-V21 -> 0
B23: Dr. Nazim | C23: 401 | D23: 9500 | E23: 230 | F23: 46026 | G23: 9500 | H23: 257 | I23: 46058 | J23: 9500 | K23: 289 | L23: 46085 | Q23: 401 | R23: Dr. Nazim | S23: =9500*12 -> 114000 | T23: 0 | U23: =9500*3 -> 28500 | V23: =D23+G23+J23 -> 28500 | W23: =T23+U23-V23 -> 0
B24: Mr. Junaid | C24: 402 | D24: 33000 | E24: 227 | F24: 46023 | Q24: 402 | R24: Mr. Junaid | S24: =5500*12 -> 66000 | T24: 0 | U24: =5500*3 -> 16500 | V24: =D24+G24+J24 -> 33000 | W24: =T24+U24-V24 -> -16500
B25: Mr. Asif Siddiqui | C25: 403 | Q25: 403 | R25: Mr. Asif Siddiqui | S25: =7000*12 -> 84000 | T25: 7000 | U25: =7000*3 -> 21000 | V25: =D25+G25+J25 -> 0 | W25: =T25+U25-V25 -> 28000
B26: Mr. Khalid Ashraf Lari | C26: 404 | Q26: 404 | R26: Mr. Khalid Ashraf Lari | S26: =7500*12 -> 90000 | T26: 22500 | U26: =5500*3 -> 16500 | V26: =D26+G26+J26 -> 0 | W26: =T26+U26-V26 -> 39000
B28: Mr. Tanveer Iqbal | C28: 501 | Q28: 501 | R28: Mr. Saad | S28: =7500*12 -> 90000 | T28: 7500 | U28: =7500*3 -> 22500 | V28: =D28+G28+J28 -> 0 | W28: =T28+U28-V28 -> 30000
B29: Mr. Naveed Ansari | C29: 502 | J29: 16500 | K29: 266 | L29: 46112 | Q29: 502 | R29: Mr. Naveed Ansari | S29: =5500*12 -> 66000 | T29: 16500 | U29: =5500*3 -> 16500 | V29: =D29+G29+J29 -> 16500 | W29: =T29+U29-V29 -> 16500
B30: Mr. Salman Khan | C30: 503 | Q30: 503 | R30: Mr. Salman Khan | S30: =7000*12 -> 84000 | T30: 0 | U30: =7000*3 -> 21000 | V30: =D30+G30+J30 -> 0 | W30: =T30+U30-V30 -> 21000
B31: Mr. Nafis | C31: 504 | D31: 5500 | E31: 228 | F31: 46027 | G31: 5500 | H31: 259 | I31: 46058 | J31: 5500 | K31: 290 | L31: 46087 | Q31: 504 | R31: Mr. Nafis | S31: =5500*12 -> 66000 | T31: 0 | U31: =5500*3 -> 16500 | V31: =D31+G31+J31 -> 16500 | W31: =T31+U31-V31 -> 0
B33: Mr. Sohail | C33: 601 | D33: 5500 | E33: 258 | F33: 46048 | G33: 5500 | H33: 280 | I33: 46080 | J33: 5500 | K33: 304 | L33: 46109 | Q33: 601 | R33: Mr. Sohail | S33: =5500*12 -> 66000 | T33: 0 | U33: =5500*3 -> 16500 | V33: =D33+G33+J33 -> 16500 | W33: =T33+U33-V33 -> 0
B34: Mr. Nasir | C34: 602 | D34: 5500 | E34: 243 | F34: 46037 | G34: 5500 | H34: 273 | I34: 46060 | J34: 5500 | K34: 298 | L34: 46092 | Q34: 602 | R34: Mr. Nasir | S34: =5500*12 -> 66000 | T34: 0 | U34: =5500*3 -> 16500 | V34: =D34+G34+J34 -> 16500 | W34: =T34+U34-V34 -> 0
B35: Mr. Shahid | C35: 603 | G35: 18000 | H35: 267 | I35: 46061 | Q35: 603 | R35: Mr. Shahid | S35: =9000*12 -> 108000 | T35: 27000 | U35: =9000*3 -> 27000 | V35: =D35+G35+J35 -> 18000 | W35: =T35+U35-V35 -> 36000
B36: Mr. Ashfaque Sb | C36: 604 | D36: 5500 | E36: 260 | F36: 46051 | G36: 5500 | H36: 292 | I36: 46081 | Q36: 604 | R36: Mr. Ashfaque Sb | S36: =5500*12 -> 66000 | T36: 0 | U36: =5500*3 -> 16500 | V36: =D36+G36+J36 -> 11000 | W36: =T36+U36-V36 -> 5500
B38: Mr. Owais | C38: 701 | D38: 5500 | E38: 244 | F38: 46033 | J38: 11000 | K38: 286 | L38: 46085 | Q38: 701 | R38: Mr. Owais | S38: =5500*12 -> 66000 | T38: 0 | U38: =5500*3 -> 16500 | V38: =D38+G38+J38 -> 16500 | W38: =T38+U38-V38 -> 0
B39: Mrs. Younus | C39: 702 | G39: 21500 | H39: 268 | I39: 46061 | J39: 5500 | K39: 303 | L39: 46097 | Q39: 702 | R39: Mrs. Younus | S39: =5500*12 -> 66000 | T39: 12000 | U39: =4000+5500+5500 -> 15000 | V39: =D39+G39+J39 -> 27000 | W39: =T39+U39-V39 -> 0
B40: Mr. Yousuf | C40: 703 | D40: 11000 | E40: 247 | F40: 46035 | G40: 11000 | H40: 271 | I40: 46065 | J40: 11000 | K40: 295 | L40: 46089 | Q40: 703 | R40: Mr. Yousuf | S40: =11000*12 -> 132000 | T40: 0 | U40: =11000*3 -> 33000 | V40: =D40+G40+J40 -> 33000 | W40: =T40+U40-V40 -> 0
B41: Mr. Taj | C41: 704 | D41: =7500+5500 -> 13000 | E41: 248/242 | F41: 12/13 Jan | G41: 5500 | H41: 275 | I41: 46069 | J41: 5500 | K41: 299 | L41: 46096 | Q41: 704 | R41: Mr. Taj | S41: =5500*12 -> 66000 | T41: 15000 | U41: =5500*3 -> 16500 | V41: =D41+G41+J41 -> 24000 | W41: =T41+U41-V41 -> 7500
B43: Mr. Kashif Patel | C43: 801 | G43: 11000 | H43: 274 | I43: 46068 | J43: 5500 | K43: 296 | L43: 46088 | Q43: 801 | R43: Mr. Kashif Patel | S43: =5500*12 -> 66000 | T43: 0 | U43: =5500*3 -> 16500 | V43: =D43+G43+J43 -> 16500 | W43: =T43+U43-V43 -> 0
B44: Mr. Munaf | C44: 802 | D44: 7500 | E44: 232 | F44: 46026 | G44: 7500 | H44: 270 | I44: 46065 | J44: 5500 | K44: 305 | L44: 46111 | Q44: 802 | R44: Mr. Munaf | S44: =7500*12 -> 90000 | T44: 0 | U44: =7500+7500+5500 -> 20500 | V44: =D44+G44+J44 -> 20500 | W44: =T44+U44-V44 -> 0
B45: Mr. Shamim | C45: 803 | D45: 7000 | E45: 231 | F45: 46026 | G45: 7000 | H45: 256 | I45: 46057 | J45: 7000 | K45: 301 | L45: 46098 | Q45: 803 | R45: Mr. Shamim | S45: =7000*12 -> 84000 | T45: 0 | U45: =7000*3 -> 21000 | V45: =D45+G45+J45 -> 21000 | W45: =T45+U45-V45 -> 0
B46: Mr. Aziz | C46: 804 | D46: 5500 | E46: 224 | F46: 46023 | G46: 5500 | H46: 252 | I46: 46054 | J46: 5500 | K46: 283 | L46: 46082 | M46: 5500 | N46: 307 | O46: 46113 | Q46: 804 | R46: Mr. Aziz | S46: =5500*12 -> 66000 | T46: 0 | U46: =5500*3 -> 16500 | V46: =D46+G46+J46 -> 16500 | W46: =T46+U46-V46 -> 0
B48: Mr. Fahad Qureshi | C48: 901 | Q48: 901 | R48: Mr. Fahad Qureshi | S48: =4000*12 -> 48000 | T48: 0 | U48: =4000*3 -> 12000 | V48: =D48+G48+J48 -> 0 | W48: =T48+U48-V48 -> 12000
B49: Mr. Arif 2 | C49: 902 | D49: 5500 | E49: 250 | F49: 46039 | G49: 5500 | H49: 278 | I49: 46079 | Q49: 902 | R49: Mr. Arif 2 | S49: =5500*12 -> 66000 | T49: 0 | U49: =5500*3 -> 16500 | V49: =D49+G49+J49 -> 11000 | W49: =T49+U49-V49 -> 5500
B50: Mr. Muhammad Arif | C50: 903 | D50: 7000 | E50: 249 | F50: 46039 | G50: 7000 | H50: 277 | I50: 46079 | Q50: 903 | R50: Mr. Muhammad Arif | S50: =7000*12 -> 84000 | T50: 0 | U50: =7000*3 -> 21000 | V50: =D50+G50+J50 -> 14000 | W50: =T50+U50-V50 -> 7000
B51: Mr. Hafeez | C51: 904 | D51: 5500 | E51: 246 | F51: 46034 | G51: 5500 | H51: 276 | I51: 46070 | J51: 5500 | K51: 300 | L51: 46096 | Q51: 904 | R51: Mr. Hafeez | S51: =5500*12 -> 66000 | T51: 0 | U51: =5500*3 -> 16500 | V51: =D51+G51+J51 -> 16500 | W51: =T51+U51-V51 -> 0
B53: Mr. Danish | C53: 1001 | M53: 12000 | N53: 309 | O53: 46116 | Q53: 1001 | R53: Mr. Danish | S53: =4000*12 -> 48000 | T53: 12000 | U53: =4000*3 -> 12000 | V53: =D53+G53+J53 -> 0 | W53: =T53+U53-V53 -> 24000
B54: Dr. Mansoor | C54: 1002 | D54: 5500 | E54: 223 | F54: 46023 | G54: 5500 | H54: 253 | I54: 46054 | J54: 5500 | K54: 282 | L54: 46082 | M54: 5500 | N54: 306 | O54: 46113 | Q54: 1002 | R54: Dr. Mansoor | S54: =5500*12 -> 66000 | T54: 0 | U54: =5500*3 -> 16500 | V54: =D54+G54+J54 -> 16500 | W54: =T54+U54-V54 -> 0
B55: Mr. Wajih | C55: 1003 | D55: 9000 | E55: 238 | F55: 46030 | G55: 9000 | H55: 262 | I55: 46058 | J55: 9000 | K55: 291 | L55: 46087 | Q55: 1003 | R55: Mr. Wajih | S55: =9000*12 -> 108000 | T55: 0 | U55: =9000*3 -> 27000 | V55: =D55+G55+J55 -> 27000 | W55: =T55+U55-V55 -> 0
B56: Mr. Ali | C56: 1004 | D56: 5500 | E56: 240 | F56: 46030 | G56: 5500 | H56: 272 | I56: 46065 | J56: 5500 | K56: 297 | L56: 46090 | Q56: 1004 | R56: Mr. Ali | S56: =5500*12 -> 66000 | T56: 0 | U56: =5500*3 -> 16500 | V56: =D56+G56+J56 -> 16500 | W56: =T56+U56-V56 -> 0
B58: Total | D58: =SUM(D8:D56) -> 262500 | G58: =SUM(G8:G56) -> 241500 | J58: =SUM(J8:J56) -> 171500 | M58: =SUM(M8:M56) -> 28500 | Q58: Shop Maint. (A) | S58: =7500*12 -> 90000 | T58: 22500 | U58: =7500*2 -> 15000 | V58: =D61+G61 -> 0 | W58: =T58+U58-V58 -> 37500
B60: Other Income : | Q60: Total | S60: =SUM(S8:S58) -> 3186000 | T60: =SUM(T8:T58) -> 212500 | U60: =SUM(U8:U58) -> 783500 | V60: =SUM(V8:V58) -> 675500 | W60: =SUM(W8:W58) -> 320500
B61: Shop Maintenance (A) | D61: 0 | G61: 0
B62: Rent Community Hall | D62: 0 | G62: 0
B63: Advertisement - Asif (A) | D63: 500000 | F63: 46042 | G63: 500000 | I63: 46070 | J63: 1000000 | L63: 02,16 Mar
B64: Advertisement - Raza (B) | D64: 0 | G64: 0
B65: Advertisement - Shehryar (C) | D65: 0 | G65: 200000 | I65: 46069 | J65: 200000 | L65: 46097
B66: Scrap Sale / AC | D66: 27500 | F66: 46053 | G66: 0
B67: Advertisement Utility Bill Collection | D67: 50000 | F67: 46037 | G67: 0
B68: Gross Total | D68: =D62+D63+D64+D65+D58+D61+D66+D67 -> 840000 | G68: =G62+G63+G64+G65+G58+G61+G66 -> 941500 | J68: =J62+J63+J64+J65+J58+J61+J66 -> 1371500 | M68: =M62+M63+M64+M65+M58+M61+M66 -> 28500
D70: =+D58+D62+D61 -> 262500 | G70: =+G58+G62+G61 -> 241500 | J70: =+J58+J62+J61 -> 171500 | M70: =+M58+M62+M61 -> 28500
G78: Transfer from Danish | I78: =+'Recpt 2025'!DG86 -> 206030
G79: Collection till Dec 2025 | I79: =+'Recpt 2025'!DG87 -> 1774501
G80: Collection from Jan 2026 till date | I80: =D70+G70+J70+M70 -> 704000
G81: Total Amount Received | J81: =I80+I79+I78 -> 2684531
G83: Kelectric | H83: 45901 | I83: 261172
G84: Kelectric | H84: 45931 | I84: 237312
G85: Imam Sb salary | H85: 45933 | I85: 25000
G86: Transfer to Danish | H86: 45934 | I86: 100000
G87: Cash Salaries | H87: 45931 | I87: 129000
G88: Kelectric | H88: 45964 | I88: 249928
G89: Kelectric | H89: 46025 | I89: 219111
G90: Kelectric | H90: 46055 | I90: 226381
G91: Kelectric | H91: 46087 | I91: 242468
G92: Kelectric | H92: 46114 | I92: 224818
J93: =-SUM(I83:I92) -> -1915190
G95: Colour Payment | H95: 45910 | I95: 48960
G96: Colour Payment | H96: 45971 | I96: 17900
G97: Amanat Labour | H97: 45971 | I97: 20000
G98: Amanat Labour | H98: 18/10/2025 | I98: 20000
G99: Colour Payment | H99: 20/10/2025 | I99: 29850
G100: Amanat Labour | H100: 25/10/2025 | I100: 20000
G101: Amanat Labour | H101: 27/10/2025 | I101: 30000
G102: Colour Payment | H102: 28/10/2025 | I102: 74480
G103: Colour Payment | H103: 45727 | I103: 51640
G104: Amanat Labour | H104: 45727 | I104: 30000
G105: Colour Payment | H105: 45788 | I105: 6260
G106: Colour Payment | H106: 45788 | I106: 6000
G107: Colour Payment | H107: 45880 | I107: 62570
G108: Amanat Labour | H108: 45880 | I108: 60000
G109: Amanat Labour | H109: 45972 | I109: 50000
G110: Colour Payment | H110: 23/11/2025 | I110: 6450
J111: =-SUM(I95:I110) -> -534110 | L111: =+'FP 2026'!U45 -> 206731
J112: =J81+J93+J111 -> 235231 | L112: =+M70 -> 28500 | M112: =L112+L111 -> 235231
H114: Account balance as of | J114: 151141
H115: Cash n Hand | J115: =130000+45000+54500+20000 -> 249500
J116: =J112-J114-J115 -> -165410
H118: Shahid Bhai | J118: 7000
H119: Albert | J119: 5000
J120: =J116-J118-J119 -> -177410

Sheet Exp 2026
B2: Anum Vista
B3: Expenses - Till Jul 2025
B4: Particulars | D4: 46023 | F4: 46054 | H4: 46054 | L4: Others - Petty Expenses
B5: Discription | C5: Name | L5: S. No. | M5: Particulors | N5: Date | O5: Amount
B6: Water Tanker | F6: 15000 | G6: 46068 | L6: 1 | M6: Garbage Collection | N6: 46051 | O6: 3000
L7: 2 | M7: Clearing Material - Albert | N7: 46035 | O7: 2800
L8: 3 | M8: Water - Aqua for Staff | N8: 46040 | O8: 5940
L9: 4 | M9: Air freshner | N9: 46035 | O9: 4000
D10: =SUM(D6:D9) -> 0 | F10: =SUM(F6:F9) -> 15000 | H10: =SUM(H6:H9) -> 0 | L10: 46023 | O10: =SUM(O6:O9) -> 15740
B11: Salaries and Wages | C11: Nadeem | D11: 40000 | E11: 46023 | F11: 40000 | G11: 46055 | H11: 50000 | I11: 46082
C12: Imam Sb | D12: 28000 | E12: 46023 | F12: 28000 | G12: 46055 | H12: 28000 | I12: 46082 | L12: S. No. | M12: Particulors | N12: Date | O12: Amount
C13: Adnan | D13: 26000 | E13: 46023 | F13: 15000 | G13: 46055 | H13: 31000 | I13: 46082 | L13: 1 | M13: Garbage Collection | N13: 46058 | O13: 3000
C14: Sajid | D14: 26000 | E14: 46023 | F14: 25000 | G14: 46055 | H14: 31000 | I14: 46082 | L14: 2 | M14: Clearing Material - Albert | N14: 3,19 Feb | O14: =7740+800 -> 8540
C15: Ali | D15: 13000 | E15: 46023 | F15: 0 | L15: 3 | M15: Water - Aqua for Staff | N15: Nil | O15: Nil
C16: Albert | D16: 37000 | E16: 46023 | F16: 37000 | G16: 46055 | H16: 42000 | I16: 46082 | L16: 4 | M16: Stationary | N16: 46056 | O16: 520
C17: Sunny/Matloob+Zara | D17: 30000 | E17: 46023 | F17: 9800 | G17: 46055 | H17: 14000 | I17: 46082 | L17: 5 | M17: Key Making | N17: 46067 | O17: 500
C18: Ahmed | F18: 6000 | G18: 46055 | H18: 10000 | I18: 46082 | L18: 46054 | O18: =SUM(O13:O17) -> 12560
D19: =SUM(D11:D18) -> 200000 | F19: =SUM(F11:F18) -> 160800 | H19: =SUM(H11:H18) -> 206000
B20: Murtaza Security | C20: Guard 1 | D20: 32500 | E20: 46031 | F20: 32500 | G20: 46055 | H20: 35000 | I20: 46086 | L20: S. No. | M20: Particulors | N20: Date | O20: Amount
C21: Guard 2 | D21: 32500 | E21: 46031 | F21: 32500 | G21: 46055 | H21: 35000 | I21: 46086 | L21: 1 | M21: Garbage Collection | N21: 46090 | O21: 3000
D22: =SUM(D20:D21) -> 65000 | F22: =SUM(F20:F21) -> 65000 | H22: =SUM(H20:H21) -> 70000 | L22: 2 | M22: Clearing Material - Albert | N22: 46092 | O22: 6930
B23: Lift Work + Monthly Maintenance | C23: Monthly Maintenance | D23: 12000 | E23: 46026 | F23: 12000 | G23: 46055 | H23: 12000 | I23: 46083 | L23: 3 | M23: Water - Aqua for Staff | N23: 46083 | O23: 3740
C24: Circuit Relay | D24: 3800 | E24: 46026 | L24: 4 | M24: Reception Chair repair | N24: 46098 | O24: 4500
C25: Lift Card repair | D25: 5500 | E25: 46048
C26: Button/Lift weight/Safety Switch | F26: 4500 | G26: 46055 | H26: 21000 | I26: 46097 | L26: 46082 | O26: =SUM(O21:O25) -> 18170
C27: Brake Shoes, Door repair, Oil
C28: Display Card / Invertor
C29: Mirror - Lift
D30: =SUM(D23:D29) -> 21300 | F30: =SUM(F23:F29) -> 16500 | H30: =SUM(H23:H29) -> 33000
B31: Others - Petty Expenses | D31: =+O10 -> 15740 | E31: Various | F31: =+O18 -> 12560 | G31: Various | H31: =+O26 -> 18170 | I31: Various
D33: =SUM(D31:D32) -> 15740 | F33: =SUM(F31:F32) -> 12560 | H33: =SUM(H31:H32) -> 18170
B34: Utilities | C34: KESC | D34: 226381 | E34: 46053 | F34: 242468 | G34: 46081 | H34: 224818 | I34: 46112
D36: =SUM(D34:D35) -> 226381 | F36: =SUM(F34:F35) -> 242468 | H36: =SUM(H34:H35) -> 224818
B37: Electrical work Expenses | C37: Other Electrical Material Purchases
C38: Lights - Purchases | D38: 33080 | E38: 46051 | F38: 3640 | G38: 46068 | H38: =3250+44860 -> 48110 | I38: 12,26 - Mar
C39: Labour | D39: 1500 | E39: 46035
C40: Gate Lock + Door Closer / Time Switch
C41: Fan Winding/Wire | H41: 2000 | I41: 46089
D43: =SUM(D37:D42) -> 34580 | F43: =SUM(F37:F42) -> 3640 | H43: =SUM(H37:H42) -> 50110
B44: Generator & Diesel Exp | C44: Maintenance | F44: 43600 | G44: 46079
C45: Diesel + Cartage | D45: 10000 | E45: 46043 | F45: 10000 | G45: 46077 | H45: 40000 | I45: 46089
C46: Diesel + Cartage | H46: 50000 | I46: 46104
C47: Diesel + Cartage
C48: Touching Wire/Fuel Pump/Drum | D48: 1500 | E48: 46048 | H48: =570+1700 -> 2270 | I48: 17,23 Mar
D49: =SUM(D44:D48) -> 11500 | F49: =SUM(F44:F48) -> 53600 | H49: =SUM(H44:H48) -> 92270
B50: Building Colour | C50: Material Purchases | F50: =60770+58680 -> 119450 | G50: 46081
C51: Labour Paid | F51: 50000 | G51: 46081
D52: =SUM(D50:D51) -> 0 | F52: =SUM(F50:F51) -> 169450 | H52: =SUM(H50:H51) -> 0
B53: Building Maintenance - Others | C53: Plants (Indoor + Outdoor) | F53: 4500 | G53: 46058
C54: Building Mats
C55: Other Maintenance | F55: 2100 | G55: 46062
C56: Fire Cylinder Refil + Drill + Colour
C57: Tile Water Tank + Cover + Rubber Pipe + Labour | D57: 18500 | E57: 46041 | H57: 6970 | I57: 46109
D58: =SUM(D53:D57) -> 18500 | F58: =SUM(F53:F57) -> 6600 | H58: =SUM(H53:H57) -> 6970
B59: Play Area Expenses | C59: Table Tennis Rackets + Balls / Play Area
C60: Door Repairing | H60: 15000 | I60: 46097
C61: Snooker Dabbo Polish + Fusball Service + Material
D62: =SUM(D59:D61) -> 0 | F62: =SUM(F59:F61) -> 0 | H62: =SUM(H59:H61) -> 15000
B63: Entertaiment Expense | C63: Annual Function - Dinner + Decoration etc
C64: Fireworks and Cakes on New Year
C65: Farm house + Food
D66: =SUM(D63:D65) -> 0 | F66: =SUM(F63:F65) -> 0 | H66: =SUM(H63:H65) -> 0
B67: Water - Machine and Plumbering Work | C67: Material | D67: 11500 | E67: 46023 | H67: 5990 | I67: 46097 | L67: Kashif Motor overhead tank
C68: Labour | D68: 7000 | E68: 46023 | L68: Material, Rooftop sewerage line work
C69: Motor - Purchase | D69: 52000 | E69: 46023 | L69: Boring Machine
C70: Motor - Repair | F70: 31780 | G70: 46079 | L70: Kashif Labour - Boring
C71: Material - Water Tank new lines installation | D71: =12245+122050+16600 -> 150895 | E71: 46039 | F71: =51820-4000 -> 47820 | G71: 46072 | L71: Motor Repairing with Labour
C72: Labour - Kashif | D72: 46500 | E72: 46039 | F72: 4000 | G72: 46072 | L72: Belt - Motor
C73: Suction pump | D73: 5845 | E73: 46048 | L73: Summer pump - New Motor + Labour
L74: Kashif - Labour / Roof work / Valve
L75: Electrical work tank + Labour
L76: Kashif - Material + Labour/Tile Work
L77: Water Mater Outside/Tank cleaning/Parking Area Seweage line
D78: =SUM(D67:D77) -> 273740 | F78: =SUM(F67:F77) -> 83600 | H78: =SUM(H67:H77) -> 5990
B79: Qurbani Expenses | C79: Chapra + Loading Bamboos + lifting
C80: Watch Man
C81: Eid Material - Plastic etc
C82: Lights Outside purchase
C83: Outside cleaning and garbage lifting
D84: =SUM(D79:D83) -> 0 | F84: =SUM(F79:F83) -> 0 | H84: =SUM(H79:H83) -> 0
B85: Mosque/Ramzan Expenses : | C85: Ramazan - Sehri + Iftar items for building | F85: 57395 | G85: 46072
C86: Janamaz/Fragnance | F86: 1050 | G86: 46077
C87: Suits for Staff - On Eid | H87: 19220 | I87: 46089
C88: Khatam-e-Quran - Sweet | H88: 26520 | I88: 46097
C89: Khatam-e-Quran ( Taraweah Imam Sb) | H89: 40000 | I89: 46097
C90: Khatam-e-Quran ( Taraweah ) Dinner + Decoration | H90: =13000+3750+94400+3340 -> 114490 | I90: 46097
D91: =SUM(D85:D90) -> 0 | F91: =SUM(F85:F90) -> 58445 | H91: =SUM(H85:H90) -> 200230
B92: Gym Expenses : | C92: Gym Maintenance + Treadmill new belt change + Dumbel
C93: Trade Mill
D96: =SUM(D92:D95) -> 0 | F96: =SUM(F92:F95) -> 0 | H96: =SUM(H92:H95) -> 0
B97: Building Assets | C97: Electrical Appliances - Air Conditioners
C98: New Cameras Installation/Purchases | D98: 50000 | E98: 46193
C99: UPS and Hard drive purchase
C100: Trolly + Bailcha + Blower + Dust bins | F100: =9000+7000 -> 16000 | G100: 1,5 Feb | H100: 41000 | I100: 46106
D101: =SUM(D97:D100) -> 50000 | F101: =SUM(F97:F100) -> 16000 | H101: =SUM(H97:H100) -> 41000
B102: Camera, Intercom and Internet Expenses | C102: Intercom - Monthly Maintenance | D102: =2500 -> 2500 | E102: 46041 | F102: 2500 | G102: 46062 | H102: 2500 | I102: 46097
C103: Monthy Camera | D103: 10000 | E103: 46041 | F103: 10000 | G103: 46062 | H103: 10000 | I103: 46097
D105: =SUM(D102:D103) -> 12500 | F105: =SUM(F102:F103) -> 12500 | H105: =SUM(H102:H103) -> 12500
B107: Total | D107: =D10+D19+D22+D30+D33+D36+D43+D49+D52+D58+D62+D66+D78+D84+D91+D96+D101+D105 -> 929241 | F107: =F10+F19+F22+F30+F33+F36+F43+F49+F52+F58+F62+F66+F78+F84+F91+F96+F101+F105 -> 916163 | H107: =H10+H19+H22+H30+H33+H36+H43+H49+H52+H58+H62+H66+H78+H84+H91+H96+H101+H105 -> 976058
D109: 0 | F109: 0 | H109: 0
...

Sheet Funds Breakup
B2: Danish | E2: Danish
B3: Particulars | C3: Amount | E3: Particulars | F3: Amount | G3: Remarks
B5: Opening Jan 01, 2024 | C5: 4082138
B7: Maintenance amount received by Danish | C7: =+'Recpt 2025'!AP58 -> 477000
B8: Maintenance Shop A | C8: =+'Recpt 2025'!AP61 -> 15000
B9: Community Hall Rent | C9: =+'Recpt 2025'!AP62 -> 0
B10: Advertisement - Asif (A) | C10: =+'Recpt 2025'!AP63 -> 1706250
B11: Advertisement - Raza (B) | C11: =+'Recpt 2025'!AP64 -> 0
B12: Advertisement - Khizer (C) | C12: =+'Recpt 2025'!AP65 -> 300000
B13: Salaries + Security Gurads | C13: =-Exp!AB23-Exp!AB26 -> -198500
B14: Water tanker | C14: =-Exp!AB14 -> -220000
B15: Petty Cash Expenses | C15: =-Exp!AB35 -> -14850
B16: Water - Machine and Plumbering Work | C16: =-Exp!AB85 -> -29960
B17: Generator & Diesel Exp | C17: =-Exp!AB57 -> -25000
B18: Lift Work + Monthly Maintenance | C18: =-Exp!AB34 -> -24500
B19: Electrical Work Expenses | C19: =-Exp!AB47 -> 0
B20: Kelectric - Jan 2024 | C20: =-Exp!AB40 -> -199495
B21: Gym Expenses | C21: =-Exp!AB102 -> 0
B22: Entertaiment Expense | C22: =-Exp!AB73 -> 0
B23: Building Colour Expenses | C23: =-Exp!AB62 -> 0
B24: Plants for building | C24: =-Exp!AB65 -> 0
B26: 45292 | C26: =SUM(C7:C25) -> 1785945
B28: Maintenance amount received by Danish | C28: =+'Recpt 2025'!AS58 -> 185500
B29: Maintenance Shop A | C29: =+'Recpt 2025'!AS61 -> 15000
B30: Community Hall Rent | C30: =+'Recpt 2025'!AS62 -> 0
B31: Advertisement - Asif (A) | C31: =+'Recpt 2025'!AS63 -> 0
B32: Advertisement - Raza (B) | C32: =+'Recpt 2025'!AS64 -> 0
B33: Advertisement - Khizer (C) | C33: =+'Recpt 2025'!AS65 -> 0
B34: Salaries + Security Gurads | C34: =-Exp!AD23-Exp!AD26 -> -200000
B35: Water tanker | C35: =-Exp!AD14 -> -210000
B36: Petty Cash Expenses | C36: =-Exp!AD37 -> -15100
B37: Water - Machine and Plumbering Work | C37: =-Exp!AD85 -> 0
B38: Generator & Diesel Exp | C38: =-Exp!AD57 -> -5000
B39: Lift Work + Monthly Maintenance | C39: =-Exp!AD34 -> -9500
B40: Electrical Work Expenses | C40: =-Exp!AD47 -> 0
B41: Kelectric - Feb 2024 | C41: =-Exp!AD40 -> -182471
B42: Gym Expenses | C42: =-Exp!AD102 -> 0
B43: Entertaiment Expense | C43: =-Exp!AD73 -> 0
B44: Building Colour Expenses | C44: =-Exp!AD62 -> 0
B45: Plants for building | C45: =-Exp!AD65 -> -44000
B47: 45323 | C47: =SUM(C28:C46) -> -465571
B49: Maintenance amount received by Danish | C49: =+'Recpt 2025'!AV58 -> 213000
B50: Maintenance Shop A | C50: =+'Recpt 2025'!AV61 -> 0
B51: Community Hall Rent | C51: =+'Recpt 2025'!AV62 -> 0
B52: Advertisement - Asif (A) | C52: =+'Recpt 2025'!AV63 -> 0
B53: Advertisement - Raza (B) | C53: =+'Recpt 2025'!AV64 -> 0
B54: Advertisement - Khizer (C) | C54: =+'Recpt 2025'!AV65 -> 0
B55: Salaries + Security Gurads | C55: =-Exp!AF23-Exp!AF26 -> -209000
B56: Water tanker | C56: =-Exp!AF14 -> -110000
B57: Petty Cash Expenses | C57: =-Exp!AF37 -> -17500
B58: Water - Machine and Plumbering Work | C58: =-Exp!AF85 -> -37790
B59: Generator & Diesel Exp | C59: =-Exp!AF57 -> -10000
B60: Lift Work + Monthly Maintenance | C60: =-Exp!AF34 -> -9500
B61: Electrical Work Expenses | C61: =-Exp!AF47 -> -21900
B62: Kelectric - Mar 2024 | C62: =-Exp!AF40 -> -182901
B63: Gym Expenses | C63: =-Exp!AF102 -> 0
B64: Entertaiment Expense | C64: =-Exp!AF73 -> -17000
B65: Building Colour Expenses | C65: =-Exp!AF62 -> 0
B66: Mosque/Ramazan Expenses | C66: =-Exp!AF98 -> -70150
B67: Plants for building | C67: =-Exp!AF63 -> 0
B68: Play Area Expenses | C68: =-Exp!AF68 -> -7000
B69: Vacume Cleaner | C69: =-Exp!AF64 -> -15900
B71: 45352 | C71: =SUM(C49:C69) -> -495641
B73: Maintenance amount received by Danish | C73: =+'Recpt 2025'!AY58 -> 376500
B74: Maintenance Shop A | C74: =+'Recpt 2025'!AY61 -> 0
B75: Community Hall Rent | C75: =+'Recpt 2025'!AY62 -> 0
B76: Advertisement - Asif (A) | C76: =+'Recpt 2025'!AY63 -> 1791562.5
B77: Advertisement - Raza (B) | C77: =+'Recpt 2025'!AY64 -> 0
B78: Advertisement - Khizer (C) | C78: =+'Recpt 2025'!AY65 -> 300000
B79: Salaries + Security Gurads | C79: =-'Exp 2024'!J22-'Exp 2024'!J25 -> -211000
B80: Water tanker | C80: =-'Exp 2024'!J14 -> -11500
B81: Petty Cash Expenses | C81: =-'Exp 2024'!J36 -> -19300
B82: Water - Machine and Plumbering Work | C82: =-'Exp 2024'!J86 -> -22080
B83: Generator & Diesel Exp | C83: =-'Exp 2024'!J56 -> 0
B84: Lift Work + Monthly Maintenance | C84: =-'Exp 2024'!J33 -> -16000
B85: Electrical Work Expenses | C85: =-'Exp 2024'!J46 -> -1000
B86: Kelectric - Apr 2024 | C86: =-'Exp 2024'!J39 -> -253462
B87: Gym Expenses | C87: =-'Exp 2024'!J103 -> -3500
B88: Entertaiment Expense | C88: =-'Exp 2024'!J74 -> 0
B89: Building Colour Expenses | C89: =-'Exp 2024'!J61 -> 0
B90: Mosque/Ramazan Expenses | C90: =-'Exp 2024'!J99 -> -120460
B91: Plants for building | C91: =-'Exp 2024'!J62 -> 0
B92: Play Area Expenses | C92: =-'Exp 2024'!J69 -> -8500
B93: Vacume Cleaner | C93: =-Exp!AF88 -> 0
B95: 45383 | C95: =SUM(C73:C93) -> 1801260.5
B97: Maintenance amount received by Danish | C97: =+'Recpt 2025'!BB58 -> 161000
B98: Maintenance Shop A | C98: 0
B99: Community Hall Rent | C99: 0
B100: Advertisement - Asif (A) | C100: 0
B101: Advertisement - Raza (B) | C101: 0
B102: Advertisement - Khizer (C) | C102: 0
B103: Salaries + Security Gurads | C103: =-'Exp 2024'!L22-'Exp 2024'!L25 -> -210000
B104: Water tanker | C104: 0
B105: Petty Cash Expenses | C105: =-'Exp 2024'!L36 -> -10200
B106: Water - Machine and Plumbering Work | C106: =-'Exp 2024'!L86 -> 0
B107: Generator & Diesel Exp | C107: =-'Exp 2024'!L56 -> -10000
B108: Lift Work + Monthly Maintenance | C108: =-'Exp 2024'!L33 -> -25100
B109: Electrical Work Expenses | C109: =-'Exp 2024'!L46 -> -7500
B110: Kelectric - May 2024 | C110: =-'Exp 2024'!L39 -> -271300
B111: Gym Expenses | C111: =-'Exp 2024'!L103 -> 0
...

Sheet Advertisment
B3: Advertisement
B4: Adv Payment Duration | C4: Name | D4: Collection From Avertising | E4: Received Payments | F4: Payments Due | G4: Received Date
B5: 6 Month | C5: KHYZER | D5: 750000 | E5: Apr to sep-21 | F5: 44470
B6: 3 Month | C6: KHYZER | D6: 375000 | E6: Apr -May - Jun-21 | F6: 44378
B7: 3 Month | C7: Asif - Side A | D7: 825000 | E7: MAR-APR-MAY-2021 | F7: 44348
B8: 6 Month | C8: Raza - Side -B | D8: 400000 | E8: MAY to OCT-2021 | F8: 44499
B9: 3 Month | C9: Asif | D9: 990000 | E9: Jun-Jul-Aug-2021 | F9: 44440
D10: =SUM(D5:D9) -> 3340000
B11: 3 Months | C11: Asif - Side A | D11: =450000+457500 -> 907500 | E11: Sep-Oct-Nov-2021 | F11: 44440 | G11: 24 Sep, 15 Oct 2021
B12: 3 Months | C12: Asif - Side A | D12: 907500 | E12: Dec-Jan-Feb - 2022 | F12: 44531 | G12: 44563
B14: 3 Months | C14: Asif - Side A | D14: 812500 | E14: Mar - May 2022 | F14: 44621 | G14: 44635 | L14: =6500000 -> 6500000 | M14: =L14/4 -> 1625000 | N14: =M14/2 -> 812500 | Q14: =1625000*4 -> 6500000
B15: 3 Months | C15: Asif - Side A | D15: 812500 | E15: Mar - May 2022 | F15: 44621 | G15: 44651 | Q15: 800000
B16: 3 Months | C16: Asif - Side A | D16: =6500000/4 -> 1625000 | E16: Jun - Aug 2022 | F16: 44734 | G16: 44742 | Q16: 1200000
B17: 3 Months | C17: Asif - Side A | D17: =6500000/4 -> 1625000 | E17: Sep - Nov 2022 | F17: 44826 | G17: Rec in Oct, Nov & Dec 2022 | Q17: =SUM(Q14:Q16) -> 8500000
B18: 3 Months | C18: Asif - Side A | D18: =6500000/4 -> 1625000 | E18: Dec 2022 - Feb 2023 | F18: 44896 | G18: Rec in Jan, Feb and Mar 2023
B19: 3 Months | C19: Asif - Side A | D19: =+O19 -> 1706250 | E19: Mar 2023 - May 2023 | F19: 44986 | H19: Rec in Apr | L19: 6500000 | M19: =L19*5% -> 325000 | N19: =L19+M19 -> 6825000 | O19: =N19/4 -> 1706250
B20: 3 Months | C20: Asif - Side A | D20: =+O20 -> 1706250 | E20: Jun 2023 - Aug 2023 | F20: 45100 | H20: Rec in Jul | O20: 1706250
B21: 3 Months | C21: Asif - Side A | D21: =+O21 -> 1706250 | E21: Sep 2023 - Nov 2023 | F21: 45192 | H21: Rec in Oct | O21: 1706250
B22: 3 Months | C22: Asif - Side A | D22: =+O22 -> 1706250 | E22: Dec 2023 - Feb 2024 | F22: 45283 | H22: Rec in Jan 24 | O22: 1706250
B23: 3 Months | C23: Asif - Side A | D23: =+O23 -> 1791562.5 | E23: Mar 2024 - May 2024 | F23: 45352 | H23: Rec in Apr 24 | L23: =+N19 -> 6825000 | M23: =L23*5% -> 341250 | N23: =L23+M23 -> 7166250 | O23: =N23/4 -> 1791562.5
B24: 3 Months | C24: Asif - Side A | D24: =+O24 -> 1791563 | E24: Jun 2024 - Aug 2024 | F24: 45444 | H24: Rec in Jul 24 | O24: 1791563
B25: 3 Months | C25: Asif - Side A | D25: =+O25 -> 1791563 | E25: Sep 2024 - Nov 2024 | F25: 45536 | H25: Rec in Oct 24 | O25: 1791563
B26: 3 Months | C26: Asif - Side A | D26: =+O26 -> 1791563 | E26: Dec 2024 - Feb 2025 | F26: 45627 | H26: Rec in Jan 25 | O26: 1791563
B27: 3 Months | C27: Asif - Side A | D27: =+O27 -> 1881140.6 | E27: Mar 2025 - May 2025 | F27: 45717 | H27: Rec in May 25 | L27: =+N23 -> 7166250 | M27: =L27*5% -> 358312.5 | N27: =L27+M27 -> 7524562.5 | O27: =N27/4 -> 1881140.6 | AF27: Asif - Advertisement Payment
C28: Pending Mar - May | D28: =D26-D27 -> -89577.625 | E28: Mar 2025 - May 2025 | F28: 45717 | G28: Balance | O28: =+O27 -> 1881140.6
B29: 3 Months | C29: Asif - Side A | D29: =+O28 -> 1881140.6 | E29: Jun 2025 - Aug 2025 | F29: 45809 | H29: Rec in Aug 25, 1,100,000 Rec by Danish, 781,000 Rec by Asif | J29: =1881141 -> 1881141 | O29: =+O28 -> 1881140.6 | AF29: Jun to Aug 2025 | AH29: =D29 -> 1881140.6
B30: 3 Months | C30: Asif - Side A | D30: =600000+500000+600000+270000 -> 1970000 | E30: Sep 2025 - Nov 2025 | F30: 45901 | H30: 600k received By Asif, 500K 21/10/25, 600K 20/11/25, 270K 01/12/25 Remaining Rec by Dilshad | J30: 1700000 | O30: =+O29 -> 1881140.6
C31: Difference | D31: =D29-D30 -> -88859.375 | J31: =J29-J30 -> 181141 | L31: =+N27 -> 7524562.5 | M31: =L31*5% -> 376228.12 | N31: =L31+M31 -> 7900790.6 | O31: =N31/4 -> 1975197.7
C32: Received Pending Mar - May | D32: =-D28 -> 89577.625 | E32: =D31+D32 -> 718.25 | J32: =J31+D32 -> 270718.62 | R32: 500000 | S32: Rec. Dilshad | T32: 46010 | AF32: Paid to Danish Bhai | AH32: 1100000
B33: 3 Months | C33: Asif - Side A | D33: =500000+500000+500000 -> 1500000 | E33: Dec 2025 - Feb 2026 | F33: 45992 | H33: Received by Dilshad 500k 19/12/2025, 500k 20/01/2026, 500k 17/02/2026
D34: =D27-D33 -> 381140.62 | E34: Dec 2025 - Feb 2026 | F34: Mar Adjust | G34: =D34+D35 -> 1000000 | H34: Received by Dilshad 500k 02/03/2026, 500k 16/03/2026 | J34: =1881141 -> 1881141
D35: =500000+500000-D34 -> 618859.38 | E35: Mar 2026 - May 2026 | F35: Mar
D36: 2000000
D37: =D36-D35 -> 1381140.6
J39: =89578 -> 89578
B40: 6 Months | C40: Raza - Side -B | D40: 400000 | E40: Nov 2021 to Apr 2022 | F40: 44521 | G40: Rec Nov 02, 2021 | J40: =J34+J39 -> 1970719 | AF40: Remaining to be transferred to Muhammad Asif | AH40: =AH29-AH32 -> 781140.62
B41: 6 Months | C41: Raza - Side -B | D41: 400000 | E41: May 2022 to Oct 2022 | F41: 44682 | G41: Rec in May 2022
B42: 6 Months | C42: Raza - Side -B | D42: 400000 | E42: Nov 2022 to Apr 2023 | F42: 44866 | G42: Rec in Jan 2023
B43: 6 Months | C43: Raza - Side -B | D43: 400000 | E43: May 2023 to Oct 2023 | F43: 45047 | H43: Rec in May
B44: 6 Months | C44: Raza - Side -B | D44: 400000 | E44: Nov 2023 to Apr 2024 | F44: 45231 | H44: Rec in Oct
B45: 6 Months | C45: Raza - Side -B | D45: 400000 | E45: May 2024 to Oct 2024 | F45: 45413 | H45: Discontinue - Informed in May by Danish in union meeting
B46: Adhoc Payments for 2 ads | D46: 100000
B47: 6 Months | C47: Raza - Side -B | D47: 300000 | E47: Jul 2025 to Dec 2025 | F47: 45901 | H47: Received by Danish
B51: 1 Year - Quarterly Payment | C51: Top C | D51: 300000 | E51: Jan to Mar 2023 | F51: 44949 | G51: Rec in Jan 2023
B52: 1 Year - Quarterly Payment | C52: Top C | D52: 300000 | E52: Apr to Jun 2023 | F52: 45039 | H52: Rec in Apr
B53: 1 Year - Quarterly Payment | C53: Top C | D53: 300000 | E53: Jul to Sep 2023 | F53: 45130 | H53: Rec in Jul
B54: 1 Year - Quarterly Payment | C54: Top C | D54: 300000 | E54: Oct to Dec 2023 | F54: 45222 | H54: Rec in Oct
B55: 1 Year - Quarterly Payment | C55: Top C | D55: 300000 | E55: Jan to Mar 2024 | F55: 45314 | H55: Rec in Jan 24 | L55: 1200000 | M55: =L55*5% -> 60000 | N55: =L55+M55 -> 1260000 | O55: =N55/4 -> 315000
B56: 1 Year - Quarterly Payment | C56: Top C | D56: 300000 | E56: Apr to Jun 2024 | F56: 45405 | H56: Rec in Apr 24 | O56: 315000
B57: 1 Year - Quarterly Payment | C57: Top C | D57: 300000 | E57: Jul to Sep 2024 | F57: 45496 | H57: Rec in Jul 24 | O57: 315000
B58: 1 Year - Quarterly Payment | C58: Top C | D58: 300000 | E58: Oct to Dec 2024 | F58: 45588 | H58: Rec in Oct 24 | O58: 315000
B59: 1 Year - Quarterly Payment | C59: Top C | D59: 300000 | E59: Jan to Mar 2025 | F59: 45680 | H59: Rec in Jan 25 | I59: =300000*5% -> 15000
B60: 1 Year - Quarterly Payment | C60: Top C | D60: 300000 | E60: Apr to Jun 2025 | F60: 45770 | H60: Rec in Apr 25
B61: 1 Year - Quarterly Payment | C61: Top C | D61: 300000 | E61: Jul to Sep 2025 | F61: 45861 | H61: Received in Aug and Sep 2025
B62: 1 Year - Quarterly Payment | C62: Top C | D62: 300000 | E62: Oct to Dec 2025 | F62: 45953 | H62: Received in Nov and Dec 2025
B64: 1 Year - Quarterly Payment | C64: Top C | D64: 400000 | E64: Jan to Mar 2026 | F64: 45680 | H64: Received in Feb and Mar - 2026
B65: 1 Year - Quarterly Payment | C65: Top C | D65: 400000 | E65: Apr to Jun 2026 | F65: 45770
B66: 1 Year - Quarterly Payment | C66: Top C | D66: 400000 | E66: Jul to Sep 2026 | F66: 45861
B67: 1 Year - Quarterly Payment | C67: Top C | D67: 400000 | E67: Oct to Dec 2026 | F67: 45953
B69: Advance - Building Colour, Fire Safety, seepage of overhead tank+Parking and lobby colour+Flooring of 4th floor Parking
B70: Advance | C70: Date | D70: Amount
C71: 44470 | D71: 600000
C72: 44501 | D72: 1400000
C73: 44531 | D73: 500000
C74: 44562 | D74: 400000
B75: Full and Final | C75: 44742 | D75: 272000
D76: =SUM(D71:D75) -> 3172000 | E76: =SUM(D71:D74) -> 2900000 | F76: 272000 | G76: =E76+F76 -> 3172000 | H76: Full and final
G77: =+D88 -> 3136000 | H77: Adjusted
B78: Adv. Adj | G78: =G76-G77 -> 36000 | H78: Balance
B79: Advance Adjusted : Building Colour (Front and Back) | D79: 1235000
B80: Advance Adjusted : Water Proofing - Overhead Tank - Automatic switch & Control work | D80: 550000
B81: Advance Adjusted : Fire Extinguishing Work | D81: 687000
B82: Advance Adjusted : Grill for Top - Roof + Colour | D82: 22000
B83: Advance Adjusted : Glass Work for ground lobby + Mosque + Spot light | D83: 49500
B84: Advance Adjusted : Tiles for Ground floor lobby + entrance gate + Albert day work | D84: 22500
B85: Advance Adjusted : Colour for Building all floor lobies + Parking Area | D85: 420000
B86: Advance Adjusted : 4th floor Parking - Ground work + Sarfaraz 5000 | D86: 150000
B88: Total Adv. Adj | D88: =SUM(D79:D87) -> 3136000
B90: Balance for Adv Adjustment | D90: =D76-D88 -> 36000 | E90: Adjusted in Sep 30 - Added in Danish cashflow
B91: Advance to Ali bhai for miscellaneous expenses | D91: 31800 | E91: Adjusted in Sep 30 - Added in Danish cashflow
D92: =SUM(D90:D91) -> 67800

Sheet Sheet2
B2: Maintenance | N2: SALARIES | P2: Paid in Cash
B3: Received in Cash | H3: 801 | I3: Adnan | J3: 110 | K3: 4000 | L3: Aug
H4: 1001 | I4: Danish | J4: 109 | K4: 5500 | L4: Aug
B5: 502 | C5: Naveed | D5: 108 | E5: 5500 | F5: Aug | N5: Nadeem | O5: HO To Nadeem | P5: 35000
B6: 103 | C6: Mrs. Rashid | D6: 111 | E6: 2500 | F6: Aug | H6: 100000 | I6: Transfer to Danish Oct 04, 2025 | N6: Ali | O6: HO To Nadeem | P6: =22000-11000 -> 11000
N7: Adnan | O7: HO To Nadeem | P7: 23000
B8: 603 | C8: Shahid | D8: 101 | E8: 65000 | F8: Jan to Aug | G8: 72000 | N8: Albert | O8: HO To Nadeem | P8: 37000 | Q8: 20000 | R8: Advance paid to Dilshad
B9: 102 | C9: Faisal | D9: 114 | E9: 42000 | F9: Mar to Aug | H9: Trf to FBL account from Cash on Dec 25, 2025 = Total 60k from Shehroz | N9: Abrar | O9: HO To Nadeem | P9: 23000
B10: 302 | C10: Ashraf | D10: 115 | E10: 33000 | F10: Jul to Dec | H10: Trf to FBL account from Cash on Dec 25, 2025 = Total 49.5k from HBL | N10: Imam Sb | P10: 25000 | Q10: Transferred through FBL account
B11: 702 | C11: Mrs. Younus | D11: 131 | E11: 5500 | F11: Sep
B12: 1004 | C12: Ali | D12: 132 | E12: 5500 | F12: Sep | N12: Zaheer - Electrician | P12: 15000 | Q12: Transfer
B13: 504 | C13: Nafis | D13: 133 | E13: 5500 | F13: Sep
B14: 902 | C14: Taj | D14: 134 | E14: 5500 | F14: Sep
B15: 602 | C15: Nasir | D15: 135 | E15: 5500 | F15: Sep
B16: 601 | C16: Sohail | D16: 136 | E16: 5500 | F16: Sep | N16: Cash Receipt | P16: =E8+E11+E12+E13+E14+E15+E16+E17+E21+E22 -> 127500
B17: 603 | C17: Shahid | D17: 139 | E17: 9000 | F17: Sep | N17: Slaries Paid from Cash | P17: =SUM(P5:P9) -> 129000
B18: 502 | C18: Naveed | D18: 144 | E18: 5500 | F18: Sep
B19: 1001 | C19: Danish | D19: 146 | E19: 4000 | H19: Trf to FBL account from Cash on Dec 25, 2025 = Total 60k from Shehroz
B20: 103 | C20: Mrs. Rashid | D20: 147 | E20: 2500 | F20: Sep
B21: 701 | C21: Anis | D21: 150 | E21: 15000 | F21: Sep and Oct
B22: 504 | C22: Nafees | D22: 151 | E22: 5500 | F22: Oct
B23: 503 | C23: Salman | D23: 152 | E23: 14000 | F23: Sep and Oct | H23: Trf to FBL account from Cash on Dec 25, 2025 = Total 60k from Shehroz
B24: 901 | C24: Fahad | D24: 162 | E24: 16000 | F24: Sep to Dec | G24: 45942
B25: 1004 | C25: Ali | D25: 163 | E25: 5500 | F25: Oct'25 | G25: 45938
B26: 602 | C26: Nasir | D26: 164 | E26: 5500 | F26: Oct'25 | G26: 45941
B27: 902 | C27: Taj | D27: 165 | E27: 5500 | F27: Oct'25 | G27: 45942
B28: 601 | C28: Sohail | D28: 166 | E28: 5500 | F28: Oct'25 | G28: 45948
B29: 501 | C29: Tanveer | D29: 169 | E29: 16500 | F29: Feb+Mar+Apr | G29: 45956 | H29: Trf to FBL account from Cash on Dec 25, 2025 = Total 49.5k from HBL
B31: 1004 | C31: Ali | D31: 171 | E31: 4000 | F31: Com-Hall | G31: 45957
B32: 604 | C32: Ashfaq | D32: 172 | E32: 5500 | F32: Oct'25 | G32: 45961
B33: 201 | C33: Kashif | D33: 173 | E33: 5500 | F33: Nov'25 | G33: 45962 | H33: Deposited in Account by Asif against BC, Paid 10k cash to Noor | I33: 1000
B34: 504 | C34: Nafees | D34: 177 | E34: 5500 | F34: Nov'25 | G34: 45964 | H34: Deposited in Account by Asif against BC, Paid 10k cash to Noor
B35: 103 | C35: Mrs. Rashid | D35: 179 | E35: 2500 | F35: Oct'25 | G35: 45961
B36: 602 | C36: Nasir | D36: 192 | E36: 5500 | F36: Nov'25 | G36: 45977
B37: 902 | C37: Taj | D37: 193 | E37: 5500 | F37: Nov'25 | G37: 45977
B38: 601 | C38: Sohail | D38: 197 | E38: 5500 | F38: Nov'25 | G38: 45986
B39: 504 | C39: Nafees | D39: 214 | E39: 5500 | F39: Dec'25 | G39: 45995
B40: 602 | C40: Nasir | D40: 215 | E40: 5500 | F40: Dec'25 | G40: 46000
B41: 703 | C41: Junaid | D41: 216 | E41: 11000 | F41: Dec'25 | G41: 46009
B42: 103 | C42: Mrs. Rashid | D42: 222 | E42: 5000 | F42: Nov, Dec 2025 | G42: 46022 | I42: 325000 | M42: 325000 | O42: 460500 | Q42: 200000
B43: 503 | C43: Salman | D43: 221 | E43: 14000 | F43: Nov, Dec 2025 | G43: 46021 | I43: -31000 | J43: Mysha fees | M43: -49500 | O43: 200500 | Q43: 265000
I44: -28000 | J44: Noor | M44: =M42+M43 -> 275500 | O44: =O42-O43 -> 260000
B45: 402 | C45: Junaid | D45: 227 | E45: 33000 | F45: Jan to Jun 2026 | G45: 46023 | I45: -16000 | J45: Masi | O45: 200000
B46: 101 | C46: Rehan | D46: 229 | E46: 28500 | F46: Oct+Nov+Dec'25 | G46: 46028 | I46: -5000 | J46: Qari
B47: 504 | C47: Nafees | D47: 228 | E47: 5500 | F47: Jan'25 | G47: 46027 | I47: -7000 | J47: Zakat
B48: 704 | C48: Taj | D48: 242 | E48: 5500 | F48: Jan'26 | G48: 46034 | I48: -5500 | J48: Iqba
B49: 602 | C49: Nasir | D49: 243 | E49: 5500 | F49: Jan'26 | G49: 46037 | I49: -5000 | J49: Car cleaning
I50: -15000 | J50: BC
I53: =SUM(I42:I51) -> 212500
E56: 44000
E57: 5000 | I57: 465000
E58: 11000 | I58: 200000
E59: 34000 | I59: 220000
E60: 14000
E61: 27500

Sheet Naveed
E3: Balance | J3: 7946
E5: Received | F5: Naveed - 502 | G5: Nov & Dec 2022 | H5: 11000
F6: Mohsin - 501 | G6: Oct & Nov 2022 | H6: 15000
F7: Rashid - 103 | G7: Nov & Dec 2022 | H7: 5000
H8: =SUM(H5:H7) -> 31000
E9: Expense | F9: Lights | G9: 44866 | H9: -21300
F10: Mats | G10: 44866 | H10: -8000
H11: =SUM(H8:H10) -> 1700 | J11: 1700
E13: Received | F13: Fahad - 901 | G13: Sep, Oct, Nov & Dec 2022 | H13: 16000
F14: Mohsin - 501 | G14: 44896 | H14: 7500
H15: =SUM(H13:H14) -> 23500
E16: Expense | F16: Cakes | G16: 44896 | H16: -23750
H17: =SUM(H15:H16) -> -250 | J17: -250
E19: Received | F19: Naveed - 502 | G19: Jan & Feb 2023 | H19: 11000
F20: Rashid - 103 | G20: Jan & Feb 2023 | H20: 5000
H21: =SUM(H19:H20) -> 16000
E22: Expense | F22: Lights - Bulb + Shade roll | G22: 44927 | H22: -16230
H23: =SUM(H21:H22) -> -230 | J23: -230
E25: Received | F25: Asif - 403 | G25: Maintenance | H25: 20600 | L25: Oct + Nov 14000, Mar & Apr 14000 + 4000 Community Hall - 11400 lights
F26: Shahid - 603 | G26: Dec 2022, Jan, Feb, Mar 2023 | H26: 34000 | L26: Dec 9000, Jan to Mar 8000 + including 1000 balance
F27: Naveed - 502 | G27: 44986 | H27: 5500
F28: Rashid - 103 | G28: 44986 | H28: 2500
H29: =SUM(H25:H28) -> 62600
E30: Expense | F30: Mosque Mic | H30: -3000
F31: Faraz for lights, cutain fittings | H31: -3000
F32: Carpet | H32: -11000
F33: Fabric for Staff | H33: -19300
F34: Mineral Water 19 litre | G34: 2 bottles | H34: =-290-290 -> -580
F35: Green Tea for Imam Sb. during Taraweah | H35: -180
F36: Material for building - Air Freshnors + Cells | H36: -3346
F37: Cold drink + Vaitor | H37: -2500
F38: Sweets - Khatam-e-Quran | H38: =-15401-3001 -> -18402
H39: =SUM(H29:H38) -> 1292 | J39: =+H39 -> 1292
F40: Apr & May
F41: Naveed - 502 | G41: Apr & May 2023 | H41: 11000
F42: Rashid - 103 | G42: Apr & May 2023 | H42: 5000
F43: Received from Danish | G43: 45112 | H43: 50000
F44: Colour Material | G44: 45112 | H44: -37150
F45: Wood and Carpentor Labour for duct | G45: 45112 | H45: -15000
F46: Received from Danish | G46: 45204 | H46: 50000
F47: Colour Material | G47: 45204 | H47: -25000
F48: Colour Material | G48: 45235 | H48: -18650
F49: Received from Danish | G49: 13/5/2023 | H49: 70000 | N49: Labour
F50: Colour Material | G50: 13/5/2023 | H50: -48300 | M50: 45112 | N50: 25000 | P50: 45112 | Q50: 37150
F51: Colour Labour Paid | G51: 13/5/2023 | H51: -20000 | M51: 13/5/2023 | N51: 20000 | P51: 45204 | Q51: 25000
F52: Received from Danish | G52: 16/5/2023 | H52: 50000 | K52: 2000 | M52: 16/5/2023 | N52: 20000 | P52: 45235 | Q52: 18650
F53: Colour Labour Paid | G53: 16/5/2023 | H53: -20000 | K53: 5000 | M53: 21/5/2023 | N53: 35000 | P53: 13/5/2023 | Q53: 48300
F54: Colour Material | G54: 16/5/2023 | H54: -30300 | M54: 24/5/2023 | N54: 5000 | P54: 16/5/2023 | Q54: 30300
F55: Received from Danish | G55: 21/5/2023 | H55: 50000 | M55: 25/5/2023 | N55: 15000 | P55: 21/5/2023 | Q55: 22120
F56: Colour Material | G56: 21/5/2023 | H56: -22120 | K56: 1100 | M56: 30/5/2023 | N56: 20000 | P56: 28/5/2023 | Q56: 5000
F57: Colour Labour Paid | G57: 21/5/2023 | H57: -35000 | K57: 10000 | M57: 30/5/2023 | N57: 30000 | P57: 28/5/2023 | Q57: 9450
F58: Colour Labour Paid | G58: 24/5/2023 | H58: -5000 | P58: 28/5/2023 | Q58: 7430
F59: Received from Danish | G59: 25/5/2023 | H59: 50000 | P59: 30/5/2023 | Q59: 15400
F60: Colour Labour Paid | G60: 25/5/2023 | H60: -15000 | K60: 10000 | P60: 31/5/2023 | Q60: 15520
F61: Colour Material + rent | G61: 28/5/2023 | H61: =-3000-2000 -> -5000 | P61: 45022 | Q61: 2490
F62: Colour Material | G62: 28/5/2023 | H62: -9450
F63: Colour Material | G63: 28/5/2023 | H63: -7430 | P63: Carpenter | Q63: 15000
F64: Labour Charges - light change | G64: 28/5/2023 | H64: -500 | P64: Others | Q64: =500 -> 500
F65: Colour Labour Paid | G65: 30/5/2023 | H65: -20000 | M65: Total Paid | N65: =SUM(N50:N64) -> 170000 | Q65: =SUM(Q50:Q64) -> 252310 | T65: =N65+Q65 -> 422310
F66: Received from Danish | G66: 30/5/2023 | H66: 50000 | T66: =345000+50000 -> 395000
F67: Colour Material | G67: 30/5/2023 | H67: -15400 | T67: 16000
F68: Colour Material | G68: 31/5/2023 | H68: -15520 | T68: =T66+T67-T65 -> -11310
F69: Colour Material | G69: 45022 | H69: -2490
F70: Colour Labour Paid | G70: 30/5/2023 | H70: =-25000-5000-5000 -> -35000
H73: =SUM(H41:H72) -> -16310 | J73: =+H73 -> -16310
F75: 45078
F76: Received from Danish for Grill Works | G76: 45022 | H76: 90000
F77: Paid to Zahid - Grill works | G77: 45022 | H77: -40000 | R77: Funds/Expense Record - Naveed Ansari
F78: Paid to Shahid bhai for Mistri | G78: 45205 | H78: -30000 | R78: GL - Record 1 | W78: GL - Record 2 - 2023 | AB78: GL - Record 2 - 2023 | AF78: GL - Record 3 - 2023 | AJ78: GL - Record 4 - 2024 | AN78: GL - Record 5 - 2024 | AR78: GL - Record 6 - 2024 | AV78: GL - Record 1 - 2025
F79: Colour Material - Khurram | G79: 45266 | H79: -34020
F80: Received from Danish | G80: 45266 | H80: 100000 | R80: Directly Paid by Danish to Amanat for labour charges | S80: 45112 | T80: 25000 | W80: Received from Danish for Grill Works | X80: 45022 | Y80: 90000 | AB80: Received from Danish | AC80: 20/08/2023 | AD80: 75000 | AF80: Received from Danish | AJ80: Received from Danish | AN80: Received from Danish | AR80: Received from Danish | AS80: 18/12/2024 | AT80: 80000 | AV80: Received from Danish
F81: Colour Material - Khurram | G81: 13/6/2023 | H81: -33090 | R81: Received from Danish | S81: 45112 | T81: 50000 | W81: Received from Danish | X81: 45266 | Y81: 100000 | AB81: Received from Danish | AC81: 21/08/2023 | AD81: 5000 | AR81: Received from Danish | AS81: 29/12/2024 | AT81: 20000 | AV81: Received from Danish
F82: Colour Labour Paid | G82: 14/6/2023 | H82: -20000 | R82: Received from Danish | S82: 45204 | T82: 50000 | W82: Received from Danish (Cash) | X82: 16/06/2023 | Y82: 100000 | AB82: Received from Danish | AC82: 27/09/2023 | AD82: 50000
F83: Paid to Zahid - Grill works | G83: 14/6/2023 | H83: -20000 | R83: Received from Danish | S83: 13/5/2023 | T83: 70000 | W83: Received from Danish | X83: 19/6/2023 | Y83: 75000
F84: Received from Danish (Cash) | G84: 16/06/2023 | H84: 100000 | R84: Received from Danish | S84: 16/5/2023 | T84: 50000 | W84: Received from Danish | X84: 21/6/2023 | Y84: 100000
F85: Colour Material - Taha | G85: 17/06/2023 | H85: -27800 | R85: Received from Danish | S85: 21/5/2023 | T85: 50000 | W85: Received from Danish | X85: 23/6/2023 | Y85: 100000
F86: Colour Material - Khurram | G86: 17/06/2023 | H86: -25000 | R86: Received from Danish | S86: 25/5/2023 | T86: 50000 | W86: Directly Paid to Chapra - Aameen Ullah | X86: 17/6/2023 | Y86: 57000
F87: Paid to Zahid - Grill works | G87: 17/06/2023 | H87: -20000 | R87: Received from Danish | S87: 30/5/2023 | T87: 50000
F88: Mystri block + Labour (Final Payment) | G88: 17/06/2023 | H88: -3000
F89: Air Freshnor | G89: 16/06/2023 | H89: -2600 | R89: Total Cash Received | T89: =SUM(T80:T87) -> 395000 | W89: Total Cash Received | Y89: =SUM(Y80:Y86) -> 622000 | AB89: Total Cash Received | AD89: =SUM(AD80:AD88) -> 130000 | AF89: Total Cash Received | AH89: =SUM(AH80:AH88) -> 0 | AJ89: Total Cash Received | AL89: =SUM(AL80:AL88) -> 0 | AN89: Total Cash Received | AP89: =SUM(AP80:AP88) -> 0 | AR89: Total Cash Received | AT89: =SUM(AT80:AT88) -> 100000 | AV89: Total Cash Received | AX89: =SUM(AX80:AX88) -> 0
F90: Plant Pont + Fixing + Labour | G90: 18/6/2023 | H90: -6500
F91: Received from Danish | G91: 19/6/2023 | H91: 75000
F92: Colour Material - Khurram | G92: 19/6/2023 | H92: -37400 | M92: 40000 | R92: Colour Material | S92: 45112 | T92: -37150 | W92: Colour Material - Khurram | X92: 45266 | Y92: -34020 | AB92: Colour Material - Taha | AC92: 19/08/2023 | AD92: -34380 | AR92: Colour Material - Khurram | AS92: 18/12/2024 | AT92: -46870
F93: Colour Labour Paid | G93: 21/6/2023 | H93: -35000 | M93: 33000 | R93: Colour Material | S93: 45204 | T93: -25000 | W93: Colour Material - Khurram | X93: 13/6/2023 | Y93: -33090 | AB93: Colour Material - Taha | AC93: 23/08/2023 | AD93: -19400 | AR93: Colour Material - Khurram | AS93: 23/12/2024 | AT93: -30670
F94: Received from Danish | G94: 21/6/2023 | H94: 100000 | M94: =M92+M93 -> 73000 | R94: Colour Material | S94: 45235 | T94: -18650 | W94: Colour Material - Taha | X94: 17/06/2023 | Y94: -27800 | AB94: Tape | AC94: 21/08/2023 | AD94: -5000
F95: Bhalo Mitti | G95: 21/6/2023 | H95: -2000 | R95: Colour Material | S95: 13/5/2023 | T95: -48300 | W95: Colour Material - Khurram | X95: 17/06/2023 | Y95: -25000 | AB95: Colour Material - Khurram | AC95: 18/09/2023 | AD95: -27270
F96: Lights - Paid to Faraz | G96: 22/6/2023 | H96: -15000 | R96: Colour Material | S96: 16/5/2023 | T96: -30300 | W96: Colour Material - Khurram | X96: 19/6/2023 | Y96: -37400 | AB96: Colour Material - Khurram | AC96: 23/09/2023 | AD96: -18100
F97: Colour Material - Khurram | G97: 22/6/2023 | H97: -49000 | R97: Colour Material | S97: 21/5/2023 | T97: -22120 | W97: Colour Material - Khurram | X97: 22/6/2023 | Y97: -49000
F98: Received from Danish | G98: 23/6/2023 | H98: 100000 | M98: =M94-J141 -> -12208 | R98: Colour Material + rent + Misc. Expense | S98: 28/5/2023 | T98: =-3000-2000 -> -5000 | W98: Colour Material - Taha | X98: 24/6/2023 | Y98: -20200
F99: Colour Material - Taha | G99: 24/6/2023 | H99: -20200 | R99: Colour Material | S99: 28/5/2023 | T99: -9450 | W99: Colour Material - Taha | X99: 24/6/2023 | Y99: -10160
F100: Colour Material - Taha | G100: 24/6/2023 | H100: -10160 | R100: Colour Material | S100: 28/5/2023 | T100: -7430 | W100: Colour Material - Khurram | X100: 24/6/2023 | Y100: -52870
F101: Colour Material - Khurram | G101: 24/6/2023 | H101: -52870 | R101: Colour Material | S101: 30/5/2023 | T101: -15400 | W101: Colour Material - Taha | X101: 25/6/2023 | Y101: -13200
F102: Colour Labour Paid | G102: 25/6/2023 | H102: -45000 | R102: Colour Material | S102: 31/5/2023 | T102: -15520 | W102: Colour Material - Khurram | X102: 45114 | Y102: -12200
F103: Colour Material - Taha | G103: 25/6/2023 | H103: -13200 | R103: Colour Material | S103: 45022 | T103: -2490
F104: Colour Material - Khurram | G104: 45114 | H104: -12200
R105: Total Colour Material | T105: =SUM(T92:T103) -> -236810 | W105: Total Colour Material | Y105: =SUM(Y92:Y103) -> -314940 | AB105: Total Colour Material | AD105: =SUM(AD92:AD103) -> -104150 | AF105: Total Colour Material | AH105: =SUM(AH92:AH103) -> 0 | AJ105: Total Colour Material | AL105: =SUM(AL92:AL103) -> 0 | AN105: Total Colour Material | AP105: =SUM(AP92:AP103) -> 0 | AR105: Total Colour Material | AT105: =SUM(AT92:AT103) -> -77540 | AV105: Total Colour Material | AX105: =SUM(AX92:AX103) -> 0
H107: =SUM(H76:H105) -> 10960 | J107: =+H107 -> 10960 | R107: Colour Labour Paid by Danish | S107: 45112 | T107: -25000 | W107: Colour Labour Paid | X107: 14/6/2023 | Y107: -20000 | AB107: Colour Labour Paid | AD107: -16000 | AR107: Colour Labour Paid | AS107: 20/12/2024 | AT107: -11000
R108: Colour Labour Paid | S108: 13/5/2023 | T108: -20000 | W108: Colour Labour Paid | X108: 21/6/2023 | Y108: -35000 | AB108: Colour Labour Paid | AD108: -7000 | AR108: Colour Labour Paid | AS108: 26/12/2024 | AT108: -25000
R109: Colour Labour Paid | S109: 16/5/2023 | T109: -20000 | W109: Colour Labour Paid | X109: 25/6/2023 | Y109: -45000 | AB109: Colour Labour Paid | AD109: -3500 | AR109: Colour Labour Paid | AS109: 29/12/2024 | AT109: -15000
R110: Colour Labour Paid | S110: 21/5/2023 | T110: -35000 | AB110: Colour Labour Paid | AD110: -30000
...

Sheet FP 2025
B3: Anum Vista
B4: Summary Sheet / Funds Position - 2025
F6: 45292 | J6: 45323 | N6: 45352 | R6: 45383 | V6: 45413 | Z6: 45444 | AD6: 45474 | AH6: 45505 | AL6: 45536 | AP6: 45566 | AT6: 45597 | AX6: 45627 | BB6: 45658 | BF6: 45689 | BJ6: 45717 | BN6: 45748 | BR6: 45778 | BV6: 45809 | BZ6: 45839 | CD6: 45870 | CH6: 45901 | CL6: 45931 | CP6: 45962 | CT6: 45992 | CX6: Total
B8: Cash in Hand - Opening Balance | H8: 4082138 | L8: =+H52 -> 5868083 | P8: =+L52 -> 5402512 | T8: =+P52 -> 4906871 | X8: =+T52 -> 6708131.5 | AB8: =+X52 -> 6335031.5 | AF8: =+AB52 -> 5916397.5 | AJ8: =+AF52 -> 7296569.5 | AN8: =+AJ52 -> 6644905.5 | AR8: =+AN52 -> 6393275.5 | AV8: =+AR52 -> 8088340.5 | AZ8: =+AV52 -> 7578686.5 | BD8: =+AZ52 -> 7140404.5 | BH8: =+BD52 -> 8934190.5 | BL8: =+BH52 -> 8376862.5 | BP8: =+BL52 -> 7269104.5 | BT8: =+BP52 -> 6903791.5 | BX8: =+BT52 -> 8155264.1 | CB8: =+BX52 -> 7555206.1 | CF8: =+CB52 -> 3819671.1 | CJ8: =+CF52 -> 6119099.1 | CN8: =+CJ52 -> 6605867.1 | CR8: =+CN52 -> 6121029.1 | CV8: =+CR52 -> 6154187.1
B10: Inflow
C11: Maintenance | F11: =+'Recpt 2025'!AP58 -> 477000 | J11: =+'Recpt 2025'!AS58 -> 185500 | N11: =+'Recpt 2025'!AV58 -> 213000 | R11: =+'Recpt 2025'!AY58 -> 376500 | V11: =+'Recpt 2025'!BB58 -> 161000 | Z11: =+'Recpt 2025'!BE58 -> 249500 | AD11: =+'Recpt 2025'!BH58 -> 173500 | AH11: =+'Recpt 2025'!BK58 -> 179000 | AL11: =+'Recpt 2025'!BN58 -> 290500 | AP11: =+'Recpt 2025'!BQ58 -> 254500 | AT11: =+'Recpt 2025'!BT58 -> 206500 | AX11: =+'Recpt 2025'!BW58 -> 406000 | BB11: =+'Recpt 2025'!CA58 -> 264500 | BF11: =+'Recpt 2025'!CD58 -> 161000 | BJ11: =+'Recpt 2025'!CG58 -> 257000 | BN11: =+'Recpt 2025'!CJ58 -> 120500 | BR11: =+'Recpt 2025'!CM58 -> 157500 | BV11: =+'Recpt 2025'!CP58 -> 215500 | BZ11: =+'Recpt 2025'!CS58 -> 370500 | CD11: =+'Recpt 2025'!CV58 -> 912000 | CH11: =+'Recpt 2025'!CY58 -> 300500 | CL11: =+'Recpt 2025'!DB58 -> 232500 | CP11: =+'Recpt 2025'!DE58 -> 200000 | CT11: =+'Recpt 2025'!DH58 -> 163001 | CX11: =+BB11+BF11+BJ11+BN11+BR11+BV11+BZ11+CD11 -> 2458500
C12: Maintenance Shop A | F12: =+'Recpt 2025'!AP61 -> 15000 | J12: =+'Recpt 2025'!AS61 -> 15000 | N12: 0 | R12: =+'Recpt 2025'!AY61 -> 0 | V12: 0 | Z12: =+'Recpt 2025'!BE61 -> 30000 | AD12: =+'Recpt 2025'!BH61 -> 0 | AH12: =+'Recpt 2025'!BL61 -> 0 | AL12: =+'Recpt 2025'!BN61 -> 0 | AP12: =+'Recpt 2025'!BQ61 -> 0 | AT12: =+'Recpt 2025'!BT61 -> 15000 | AX12: =+'Recpt 2025'!BW61 -> 0 | BB12: =+'Recpt 2025'!CA61 -> 0 | BF12: =+'Recpt 2025'!CD61 -> 0 | BJ12: =+'Recpt 2025'!CG61 -> 0 | BN12: =+'Recpt 2025'!CJ61 -> 0 | BR12: =+'Recpt 2025'!CM61 -> 0 | BV12: =+'Recpt 2025'!CP61 -> 0 | BZ12: =+'Recpt 2025'!CS61 -> 0 | CD12: =+'Recpt 2025'!CV61 -> 90000 | CH12: =+'Recpt 2025'!CY61 -> 0 | CL12: =+'Recpt 2025'!DB61 -> 0 | CP12: =+'Recpt 2025'!DE61 -> 7500 | CT12: =+'Recpt 2025'!DH61 -> 0 | CX12: =+BB12+BF12+BJ12+BN12+BR12+BV12+BZ12+CD12 -> 90000
C13: Rent Community Hall | F13: =+'Recpt 2025'!AP62 -> 0 | J13: =+'Recpt 2025'!AS62 -> 0 | N13: 0 | R13: =+'Recpt 2025'!AY62 -> 0 | V13: 0 | Z13: 0 | AD13: =+'Recpt 2025'!BH62 -> 0 | AH13: =+'Recpt 2025'!BL62 -> 0 | AL13: =+'Recpt 2025'!BN62 -> 0 | AP13: =+'Recpt 2025'!BQ62 -> 0 | AT13: =+'Recpt 2025'!BT62 -> 0 | AX13: =+'Recpt 2025'!BW62 -> 8000 | BB13: =+'Recpt 2025'!CA62 -> 0 | BF13: =+'Recpt 2025'!CD62 -> 0 | BJ13: =+'Recpt 2025'!CG62 -> 0 | BN13: =+'Recpt 2025'!CJ62 -> 0 | BR13: =+'Recpt 2025'!CM62 -> 8000 | BV13: =+'Recpt 2025'!CP62 -> 4000 | BZ13: =+'Recpt 2025'!CS62 -> 8000 | CD13: 0 | CH13: =+'Recpt 2025'!CY62 -> 0 | CL13: =+'Recpt 2025'!DB62 -> 4000 | CP13: =+'Recpt 2025'!DE62 -> 0 | CT13: =+'Recpt 2025'!DH62 -> 8000 | CX13: =+BB13+BF13+BJ13+BN13+BR13+BV13+BZ13+CD13 -> 20000
C14: Advertisment | F14: =+'Recpt 2025'!AP63+'Recpt 2025'!AP64+'Recpt 2025'!AP65 -> 2006250 | J14: =+'Recpt 2025'!AS63+'Recpt 2025'!AS64+'Recpt 2025'!AS65 -> 0 | N14: 0 | R14: =+'Recpt 2025'!AY63+'Recpt 2025'!AY64+'Recpt 2025'!AY65 -> 2091562.5 | V14: 0 | Z14: 0 | AD14: =+'Recpt 2025'!BH63+'Recpt 2025'!AY65 -> 2091563 | AH14: =+'Recpt 2025'!BL63+'Recpt 2025'!BC65 -> 0 | AL14: =+'Recpt 2025'!BN63+'Recpt 2025'!BN64+'Recpt 2025'!BN65 -> 0 | AP14: =+'Recpt 2025'!BQ63+'Recpt 2025'!BQ64+'Recpt 2025'!BQ65 -> 2091563 | AT14: =+'Recpt 2025'!BT63+'Recpt 2025'!BT64+'Recpt 2025'!BT65 -> 0 | AX14: =+'Recpt 2025'!BW63+'Recpt 2025'!BW64+'Recpt 2025'!BW65 -> 0 | BB14: =+'Recpt 2025'!CA63+'Recpt 2025'!CA64+'Recpt 2025'!CA65 -> 2091563 | BF14: =+'Recpt 2025'!CD63+'Recpt 2025'!CD64+'Recpt 2025'!CD65 -> 0 | BJ14: =+'Recpt 2025'!CG63+'Recpt 2025'!CG64+'Recpt 2025'!CG65 -> 100000 | BN14: =+'Recpt 2025'!CJ63+'Recpt 2025'!CJ64+'Recpt 2025'!CJ65 -> 300000 | BR14: =+'Recpt 2025'!CM63+'Recpt 2025'!CM64+'Recpt 2025'!CM65 -> 1791562.6 | BV14: =+'Recpt 2025'!CP63+'Recpt 2025'!CP64+'Recpt 2025'!CP65 -> 0 | BZ14: =+'Recpt 2025'!CS63+'Recpt 2025'!CS64+'Recpt 2025'!CS65 -> 0 | CD14: =+'Recpt 2025'!CV63+'Recpt 2025'!CV65 -> 2081000 | CH14: =+'Recpt 2025'!CY63+'Recpt 2025'!CY64+'Recpt 2025'!CY65 -> 1000000 | CL14: =+'Recpt 2025'!DB63 -> 500000 | CP14: =+'Recpt 2025'!DE63+'Recpt 2025'!DE64+'Recpt 2025'!DE65 -> 1020000 | CT14: =+'Recpt 2025'!DH63+'Recpt 2025'!DH65 -> 650000 | CX14: =+BB14+BF14+BJ14+BN14+BR14+BV14+BZ14+CD14 -> 6364125.6
C15: Scrap Sale | F15: 0 | J15: 0 | N15: 0 | R15: 0 | V15: 0 | Z15: 0 | AD15: 0 | AH15: 0 | AL15: 0 | AP15: 0 | AT15: 0 | AX15: 0 | BB15: =+'Recpt 2025'!CA66 -> 10000 | BF15: =+'Recpt 2025'!CD66 -> 60000 | BJ15: =+'Recpt 2025'!CG66 -> 0 | BN15: =+'Recpt 2025'!CJ66 -> 0 | BR15: 0 | BV15: =+'Recpt 2025'!CP66 -> 0 | BZ15: =+'Recpt 2025'!CS66 -> 0 | CD15: =+'Recpt 2025'!CV66 -> 0 | CH15: =+'Recpt 2025'!DB66 -> 0 | CT15: =+'Recpt 2025'!DH66 -> 50000 | CX15: =+BB15+BF15+BJ15+BN15+BR15+BV15+BZ15+CD15 -> 70000
F16: =SUM(F11:F15) -> 2498250 | J16: =SUM(J11:J15) -> 200500 | N16: =SUM(N11:N15) -> 213000 | R16: =SUM(R11:R15) -> 2468062.5 | V16: =SUM(V11:V15) -> 161000 | Z16: =SUM(Z11:Z15) -> 279500 | AD16: =SUM(AD11:AD15) -> 2265063 | AH16: =SUM(AH11:AH15) -> 179000 | AL16: =SUM(AL11:AL15) -> 290500 | AP16: =SUM(AP11:AP15) -> 2346063 | AT16: =SUM(AT11:AT15) -> 221500 | AX16: =SUM(AX11:AX15) -> 414000 | BB16: =SUM(BB11:BB15) -> 2366063 | BF16: =SUM(BF11:BF15) -> 221000 | BJ16: =SUM(BJ11:BJ15) -> 357000 | BN16: =SUM(BN11:BN15) -> 420500 | BR16: =SUM(BR11:BR15) -> 1957062.6 | BV16: =SUM(BV11:BV15) -> 219500 | BZ16: =SUM(BZ11:BZ15) -> 378500 | CD16: =SUM(CD11:CD15) -> 3083000 | CH16: =SUM(CH11:CH15) -> 1300500 | CL16: =SUM(CL11:CL15) -> 736500 | CP16: =SUM(CP11:CP15) -> 1227500 | CT16: =SUM(CT11:CT15) -> 871001 | CX16: =SUM(CX11:CX15) -> 9002625.6
B18: Outflow
C19: Water Tanker | F19: =+Exp!AB14 -> 220000 | J19: =+Exp!AD14 -> 210000 | N19: =+Exp!AF14 -> 110000 | R19: =+'Exp 2024'!J14 -> 11500 | V19: =+'Exp 2024'!L14 -> 0 | Z19: =+'Exp 2024'!P14 -> 0 | AD19: =+'Exp 2024'!P14 -> 0 | AH19: =+'Exp 2024'!R14 -> 0 | AL19: =+'Exp 2024'!T14 -> 0 | AP19: =+'Exp 2024'!V14 -> 0 | AT19: =+'Exp 2024'!X14 -> 26000 | AX19: =+'Exp 2024'!Z14 -> 52000 | BB19: =+'Exp 2025'!AC14 -> 0 | BF19: =+'Exp 2025'!AE14 -> 13000 | BJ19: =+'Exp 2025'!AG14 -> 13000 | BN19: =+'Exp 2025'!AI14 -> 0 | BR19: =+'Exp 2025'!AK7 -> 18000 | BV19: =+'Exp 2025'!AM14 -> 18000 | BZ19: =+'Exp 2025'!AO14 -> 30000 | CD19: =+'Exp 2025'!AQ14 -> 0 | CH19: =+'Exp 2025'!AS14 -> 60000 | CL19: =+'Exp 2025'!AU14 -> 132000 | CP19: =+'Exp 2025'!AW14 -> 129000 | CT19: =+'Exp 2025'!AY14 -> 15000 | CX19: =+BB19+BF19+BJ19+BN19+BR19+BV19+BZ19 -> 92000
C20: Utilities | F20: =+Exp!AB40 -> 199495 | J20: =+Exp!AD40 -> 182471 | N20: =+Exp!AF40 -> 182901 | R20: =+'Exp 2024'!J39 -> 253462 | V20: =+'Exp 2024'!L39 -> 271300 | Z20: =+'Exp 2024'!N39 -> 245427 | AD20: =+'Exp 2024'!P39 -> 283531 | AH20: =+'Exp 2024'!R39 -> 281334 | AL20: =+'Exp 2024'!T39 -> 236550 | AP20: =+'Exp 2024'!V39 -> 260098 | AT20: =+'Exp 2024'!X39 -> 267330 | AX20: =+'Exp 2024'!Z39 -> 255800 | BB20: =+'Exp 2025'!AC40 -> 204057 | BF20: =+'Exp 2025'!AE40 -> 192348 | BJ20: =+'Exp 2025'!AG40 -> 216757 | BN20: =+'Exp 2025'!AI40 -> 245053 | BR20: =+'Exp 2025'!AK40 -> 245240 | BV20: =+'Exp 2025'!AM40 -> 249608 | BZ20: =+'Exp 2025'!AO40 -> 235050 | CD20: =+'Exp 2025'!AQ40 -> 261172 | CH20: =+'Exp 2025'!AS40 -> 237312 | CL20: =+'Exp 2025'!AU40 -> 249928 | CP20: =+'Exp 2025'!AW40 -> 240498 | CT20: =+'Exp 2025'!AY40 -> 219111 | CX20: =+BB20+BF20+BJ20+BN20+BR20+BV20+BZ20 -> 1588113
C21: Salaries and Wages | F21: =+Exp!AB23 -> 148500 | J21: =+Exp!AD23 -> 150000 | N21: =+Exp!AF23 -> 159000 | R21: =+'Exp 2024'!J22 -> 161000 | V21: =+'Exp 2024'!L22 -> 160000 | Z21: =+'Exp 2024'!N22 -> 181000 | AD21: =+'Exp 2024'!P22 -> 161000 | AH21: =+'Exp 2024'!R22 -> 165000 | AL21: =+'Exp 2024'!T22 -> 168000 | AP21: =+'Exp 2024'!V22 -> 168000 | AT21: =+'Exp 2024'!X22 -> 152854 | AX21: =+'Exp 2024'!Z22 -> 152532 | BB21: =+'Exp 2025'!AC23 -> 166000 | BF21: =+'Exp 2025'!AE23 -> 166000 | BJ21: =+'Exp 2025'!AG23 -> 171600 | BN21: =+'Exp 2025'!AI23 -> 165000 | BR21: =+'Exp 2025'!AK23 -> 164000 | BV21: =+'Exp 2025'!AM23 -> 170100 | BZ21: =+'Exp 2025'!AO23 -> 160000 | CD21: =+'Exp 2025'!AQ23 -> 180000 | CH21: =+'Exp 2025'!AS23 -> 171500 | CL21: =+'Exp 2025'!AU23 -> 154000 | CP21: =+'Exp 2025'!AW23 -> 169200 | CT21: =+'Exp 2025'!AY23 -> 189600 | CX21: =+BB21+BF21+BJ21+BN21+BR21+BV21+BZ21 -> 1162700
C22: Security Guards | F22: =+Exp!AB26 -> 50000 | J22: =+Exp!AD26 -> 50000 | N22: =+Exp!AF26 -> 50000 | R22: =+'Exp 2024'!J25 -> 50000 | V22: =+'Exp 2024'!L25 -> 50000 | Z22: =+'Exp 2024'!N25 -> 50000 | AD22: =+'Exp 2024'!P25 -> 50000 | AH22: =+'Exp 2024'!R25 -> 50000 | AL22: =+'Exp 2024'!V25 -> 50000 | AP22: =+'Exp 2024'!V25 -> 50000 | AT22: =+'Exp 2024'!X25 -> 50000 | AX22: =+'Exp 2024'!Z25 -> 50000 | BB22: =+'Exp 2025'!AC26 -> 50000 | BF22: =+'Exp 2025'!AE26 -> 50000 | BJ22: =+'Exp 2025'!AG26 -> 50000 | BN22: =+'Exp 2025'!AI26 -> 50000 | BR22: =+'Exp 2025'!AK26 -> 50000 | BV22: =+'Exp 2025'!AM26 -> 65000 | BZ22: =+'Exp 2025'!AO26 -> 65000 | CD22: =+'Exp 2025'!AQ26 -> 65000 | CH22: =+'Exp 2025'!AS26 -> 65000 | CL22: =+'Exp 2025'!AU26 -> 65000 | CP22: =+'Exp 2025'!AW26 -> 65000 | CT22: =+'Exp 2025'!AY26 -> 65000 | CX22: =+BB22+BF22+BJ22+BN22+BR22+BV22+BZ22 -> 380000
C23: Lift Work + Monthly Maintenance | F23: =+Exp!AB34 -> 24500 | J23: =+Exp!AD34 -> 9500 | N23: =+Exp!AF34 -> 9500 | R23: =+'Exp 2024'!J33 -> 16000 | V23: =+'Exp 2024'!L33 -> 25100 | Z23: =+'Exp 2024'!N33 -> 5300 | AD23: =+'Exp 2024'!P33 -> 14300 | AH23: =+'Exp 2024'!R33 -> 12000 | AL23: =+'Exp 2024'!T33 -> 27550 | AP23: =+'Exp 2024'!V33 -> 17200 | AT23: =+'Exp 2024'!X33 -> 9500 | AX23: =+'Exp 2024'!Z33 -> 112300 | BB23: =+'Exp 2025'!AC34 -> 22000 | BF23: =+'Exp 2025'!AE34 -> 13200 | BJ23: =+'Exp 2025'!AG34 -> 10900 | BN23: =+'Exp 2025'!AI34 -> 98400 | BR23: =+'Exp 2025'!AK34 -> 11100 | BV23: =+'Exp 2025'!AM34 -> 12500 | BZ23: =+'Exp 2025'!AO34 -> 13900 | CD23: =+'Exp 2025'!AQ34 -> 19100 | CH23: =+'Exp 2025'!AS34 -> 18200 | CL23: =+'Exp 2025'!AU34 -> 16300 | CP23: =+'Exp 2025'!AW34 -> 10500 | CT23: =+'Exp 2025'!AY34 -> 9500 | CX23: =+BB23+BF23+BJ23+BN23+BR23+BV23+BZ23 -> 182000
C24: Others - Petty Expenses | F24: =+Exp!AB37 -> 14850 | J24: =+Exp!AD37 -> 15100 | N24: =+Exp!AF37 -> 17500 | R24: =+'Exp 2024'!J36 -> 19300 | V24: =+'Exp 2024'!L36 -> 10200 | Z24: =+'Exp 2024'!N36 -> 19257 | AD24: =+'Exp 2024'!P36 -> 24890 | AH24: =+'Exp 2024'!R36 -> 41230 | AL24: =+'Exp 2024'!T36 -> 24530 | AP24: =+'Exp 2024'!V36 -> 21500 | AT24: =+'Exp 2024'!X36 -> 15600 | AX24: =+'Exp 2024'!Z36 -> 20610 | BB24: =+'Exp 2025'!AC37 -> 29300 | BF24: =+'Exp 2025'!AE37 -> 35300 | BJ24: =+'Exp 2025'!AG37 -> 24690 | BN24: =+'Exp 2025'!AI37 -> 24000 | BR24: =+'Exp 2025'!AK37 -> 12750 | BV24: =+'Exp 2025'!AM37 -> 25100 | BZ24: =+'Exp 2025'!AO37 -> 30000 | CD24: =+'Exp 2025'!AQ37 -> 31500 | CH24: =+'Exp 2025'!AS37 -> 50840 | CL24: =+'Exp 2025'!AU37 -> 29800 | CP24: =+'Exp 2025'!AW37 -> 21150 | CT24: =+'Exp 2025'!AY37 -> 29910 | CX24: =+BB24+BF24+BJ24+BN24+BR24+BV24+BZ24 -> 181140
C25: Generator & Diesel Exp | F25: =+Exp!AB57 -> 25000 | J25: =+Exp!AD57 -> 5000 | N25: =+Exp!AF57 -> 10000 | R25: =+'Exp 2024'!J56 -> 0 | V25: =+'Exp 2024'!L56 -> 10000 | Z25: =+'Exp 2024'!N56 -> 45000 | AD25: =+'Exp 2024'!P56 -> 20000 | AH25: =+'Exp 2024'!R56 -> 30000 | AL25: =+'Exp 2024'!T56 -> 19500 | AP25: =+'Exp 2024'!V56 -> 25000 | AT25: =+'Exp 2024'!X56 -> 5000 | AX25: =+'Exp 2024'!Z56 -> 0 | BB25: =+'Exp 2025'!AC57 -> 58900 | BF25: =+'Exp 2025'!AE57 -> 5000 | BJ25: =+'Exp 2025'!AG57 -> 0 | BN25: =+'Exp 2025'!AI57 -> 5000 | BR25: =+'Exp 2025'!AK57 -> 15000 | BV25: =+'Exp 2025'!AM57 -> 10000 | BZ25: =+'Exp 2025'!AO57 -> 35000 | CD25: =+'Exp 2025'!AQ57 -> 60000 | CH25: =+'Exp 2025'!AS57 -> 30000 | CL25: =+'Exp 2025'!AU57 -> 25000 | CP25: =+'Exp 2025'!AW57 -> 20624 | CT25: =+'Exp 2025'!AY57 -> 5000 | CX25: =+BB25+BF25+BJ25+BN25+BR25+BV25+BZ25 -> 128900
C26: Entertainment Expense | F26: =+Exp!AB73 -> 0 | J26: =+Exp!AD73 -> 0 | N26: =+Exp!AF73 -> 17000 | R26: =+'Exp 2024'!J74 -> 0 | V26: 0 | Z26: 0 | AD26: =+'Exp 2024'!P74 -> 250000 | AH26: =+'Exp 2024'!R74 -> 0 | AL26: =+'Exp 2024'!T74 -> 0 | AP26: =+'Exp 2024'!V74 -> 0 | AT26: =+'Exp 2024'!X74 -> 123000 | AX26: 0 | BB26: =+'Exp 2025'!AC75 -> 0 | BF26: =+'Exp 2025'!AE75 -> 0 | BJ26: =+'Exp 2025'!AG75 -> 0 | BN26: =+'Exp 2025'!AI75 -> 0 | BR26: =+'Exp 2025'!AK75 -> 0 | BV26: =+'Exp 2025'!AM75 -> 250000 | BZ26: 0 | CD26: =+'Exp 2025'!AQ75 -> 1800 | CH26: =+'Exp 2025'!AS75 -> 0 | CL26: =+'Exp 2025'!AU75 -> 0 | CP26: 0 | CT26: 0 | CX26: =+BB26+BF26+BJ26+BN26+BR26+BV26+BZ26 -> 250000
C27: Building Expenses - Colour/Ramp Entrance filling | F27: =+Exp!AB62 -> 0 | J27: =+Exp!AD62 -> 0 | N27: =+Exp!AF62 -> 0 | R27: =+'Exp 2024'!J61 -> 0 | V27: 0 | Z27: 0 | AD27: 0 | AH27: =+'Exp 2024'!R60 -> 71000 | AL27: =+'Exp 2024'!T60 -> 6500 | AP27: 0 | AT27: =+'Exp 2024'!X60 -> 0 | AX27: =+'Exp 2024'!Z57+'Exp 2024'!Z58 -> 128540 | BB27: 0 | BF27: 0 | BJ27: 0 | BN27: =+'Exp 2025'!AI58 -> 27510 | BR27: 0 | BV27: 0 | BZ27: 0 | CD27: 0 | CH27: 0 | CL27: =+'Exp 2025'!AU62 -> 261190 | CP27: =+'Exp 2025'!AW62 -> 348160 | CT27: 0 | CX27: =+BB27+BF27+BJ27+BN27+BR27+BV27+BZ27 -> 27510
C28: Building Expenses - Reception Renovation work/Plants | F28: =+Exp!AB65 -> 0 | J28: =+Exp!AD65 -> 44000 | N28: =+Exp!AF63 -> 0 | R28: =+'Exp 2024'!J62 -> 0 | V28: 0 | Z28: 0 | AD28: 0 | AH28: =+'Exp 2024'!R62 -> 0 | AL28: =+'Exp 2024'!T57 -> 0 | AP28: =+'Exp 2024'!V62 -> 5300 | AT28: =+'Exp 2024'!X62 -> 5600 | AX28: =+'Exp 2024'!Z62 -> 46000 | BB28: 0 | BF28: =+'Exp 2025'!AE106 -> 25000 | BJ28: 0 | BN28: 0 | BR28: 0 | BV28: 0 | BZ28: =+'Exp 2025'!AO105 -> 2627500 | CD28: 0 | CH28: =+'Exp 2025'!AS67 -> 60000 | CL28: 0 | CP28: 0 | CT28: 0 | CX28: =+BB28+BF28+BJ28+BN28+BR28+BV28+BZ28 -> 2652500
C29: Building Expenses - Guard Room | N29: =+Exp!AF64 -> 15900 | R29: =+'Exp 2024'!J63 -> 0 | V29: 0 | Z29: 0 | AD29: 0 | AH29: 0 | AL29: 0 | AP29: 0 | AT29: 0 | AX29: 0 | BB29: 0 | BF29: 0 | BJ29: 0 | BN29: 0 | BR29: 0 | BV29: 0 | BZ29: =+'Exp 2025'!AO107 -> 238000 | CD29: 0 | CH29: 0 | CL29: 0 | CP29: 0 | CT29: 0 | CX29: =+BB29+BF29+BJ29+BN29+BR29+BV29+BZ29 -> 238000
C30: Building Expenses - Grill Work at 14th floor/Fire Refilling | Z30: =+'Exp 2024'!N65 -> 34500 | AD30: 0 | AH30: 0 | AL30: 0 | AP30: 0 | AT30: 0 | AX30: 0 | BB30: 0 | BF30: 0 | BJ30: 0 | BN30: 0 | BR30: 0 | BV30: 0 | BZ30: =+'Exp 2025'!AO108 -> 15000 | CD30: 0 | CH30: 0 | CL30: =+'Exp 2025'!AU113 -> 38300 | CP30: 0 | CT30: 0 | CX30: =+BB30+BF30+BJ30+BN30+BR30+BV30+BZ30 -> 15000
C31: Building Expenses - Vertical Acs for community hall | AH31: =+'Exp 2024'!R64 -> 32000 | AL31: 0 | AP31: 0 | AT31: 0 | AX31: 0 | BB31: 0 | BF31: 0 | BJ31: 0 | BN31: 0 | BR31: 0 | BV31: 0 | BZ31: =+'Exp 2025'!AO110 -> 422500 | CD31: 0 | CH31: 0 | CL31: 0 | CP31: 0 | CT31: 0 | CX31: =+BB31+BF31+BJ31+BN31+BR31+BV31+BZ31 -> 422500
C32: Electrical Appliances - Air Conditioners | BB32: 0 | BF32: =+'Exp 2025'!AE112 -> 220000 | BJ32: 0 | BN32: 0 | BR32: 0 | BV32: 0 | BZ32: 0 | CD32: 0 | CH32: 0 | CL32: 0 | CP32: 0 | CT32: 0 | CX32: =+BB32+BF32+BJ32+BN32+BR32+BV32+BZ32 -> 220000
C33: Power Factor + Installation Work | BB33: 0 | BF33: 0 | BJ33: =+'Exp 2025'!AG116 -> 350000 | BN33: =+'Exp 2025'!AI115 -> 20600 | BR33: =+'Exp 2025'!AK116 -> 150000 | BV33: 0 | BZ33: 0 | CD33: 0 | CH33: 0 | CL33: 0 | CP33: 0 | CT33: 0 | CX33: =+BB33+BF33+BJ33+BN33+BR33+BV33+BZ33 -> 520600
C34: Gym Expenses | F34: =+Exp!AB102 -> 0 | J34: =+Exp!AD102 -> 0 | N34: =+Exp!AF102 -> 0 | R34: =+'Exp 2024'!J103 -> 3500 | V34: 0 | Z34: =+'Exp 2024'!N103 -> 25000 | AD34: 0 | AH34: =+'Exp 2024'!R103 -> 21000 | AL34: =+'Exp 2024'!T101 -> 8000 | AP34: 0 | AT34: =+'Exp 2024'!X101 -> 0 | AX34: 0 | BB34: 0 | BF34: 0 | BJ34: =+'Exp 2025'!AG104 -> 420000 | BN34: =+'Exp 2025'!AI104 -> 0 | BR34: =+'Exp 2025'!AK104 -> 0 | BV34: 0 | BZ34: 0 | CD34: =+'Exp 2025'!AQ104 -> 17000 | CH34: =+'Exp 2025'!AS104 -> 5300 | CL34: =+'Exp 2025'!AU104 -> 0 | CP34: 0 | CT34: 0 | CX34: =+BB34+BF34+BJ34+BN34+BR34+BV34+BZ34 -> 420000
C35: Water - Machine and Plumbering Work | F35: =+Exp!AB85 -> 29960 | J35: =+Exp!AD85 -> 0 | N35: =+Exp!AF85 -> 37790 | R35: =+'Exp 2024'!J86 -> 22080 | V35: =+'Exp 2024'!L86 -> 0 | Z35: =+'Exp 2024'!N86 -> 17000 | AD35: =+'Exp 2024'!P86 -> 81170 | AH35: =+'Exp 2024'!R86 -> 17900 | AL35: =+'Exp 2024'!T86 -> 1500 | AP35: =+'Exp 2024'!V86 -> 23900 | AT35: =+'Exp 2024'!X86 -> 14570 | AX35: =+'Exp 2024'!Z86 -> 2500 | BB35: =+'Exp 2025'!AC87 -> 42020 | BF35: =+'Exp 2025'!AE87 -> 7080 | BJ35: =+'Exp 2025'!AG87 -> 32700 | BN35: =+'Exp 2025'!AI87 -> 123670 | BR35: =+'Exp 2025'!AK87 -> 2000 | BV35: =+'Exp 2025'!AM87 -> 0 | BZ35: =+'Exp 2025'!AO87 -> 131085 | CD35: =+'Exp 2025'!AQ87 -> 0 | CH35: =+'Exp 2025'!AS87 -> 49280 | CL35: =+'Exp 2025'!AU87 -> 74020 | CP35: =+'Exp 2025'!AW87 -> 57210 | CT35: =+'Exp 2025'!AY87 -> 11070 | CX35: =+BB35+BF35+BJ35+BN35+BR35+BV35+BZ35 -> 338555
C36: Qurbani Expenses | F36: =+Exp!AB91 -> 0 | J36: =+Exp!AD91 -> 0 | N36: =+Exp!AF91 -> 0 | R36: =+'Exp 2024'!J92 -> 0 | V36: 0 | Z36: =+'Exp 2024'!N92 -> 66050 | AD36: 0 | AH36: 0 | AL36: 0 | AP36: 0 | AT36: 0 | AX36: 0 | BB36: 0 | BF36: 0 | BJ36: 0 | BN36: =+'Exp 2025'!AI93 -> 0 | BR36: =+'Exp 2025'!AK93 -> 17500 | BV36: =+'Exp 2025'!AM93 -> 14000 | BZ36: 0 | CD36: 0 | CH36: 0 | CL36: =+'Exp 2025'!AU93 -> 9600 | CP36: 0 | CT36: 0 | CX36: =+BB36+BF36+BJ36+BN36+BR36+BV36+BZ36 -> 31500
C37: Mosque/Ramzan Expense | F37: =+Exp!AB98 -> 0 | J37: =+Exp!AD98 -> 0 | N37: =+Exp!AF98 -> 70150 | R37: =+'Exp 2024'!J99 -> 120460 | V37: 0 | Z37: 0 | AD37: 0 | AH37: 0 | AL37: 0 | AP37: 0 | AT37: 0 | AX37: 0 | BB37: 0 | BF37: =+'Exp 2025'!AE100 -> 51400 | BJ37: =+'Exp 2025'!AG100 -> 147561 | BN37: =+'Exp 2025'!AI100 -> 0 | BR37: 0 | BV37: 0 | BZ37: 0 | CD37: 0 | CH37: 0 | CL37: 0 | CP37: 0 | CT37: 0 | CX37: =+BB37+BF37+BJ37+BN37+BR37+BV37+BZ37 -> 198961
C38: Electrical work Expenses | F38: =+Exp!AB47 -> 0 | J38: =+Exp!AD47 -> 0 | N38: =+Exp!AF47 -> 21900 | R38: =+'Exp 2024'!J46 -> 1000 | V38: =+'Exp 2024'!L46 -> 7500 | Z38: =+'Exp 2024'!N46 -> 9600 | AD38: 0 | AH38: =+'Exp 2024'!R46 -> 9200 | AL38: =+'Exp 2024'!T46 -> 0 | AP38: =+'Exp 2024'!V46 -> 0 | AT38: =+'Exp 2024'!X46 -> 61700 | AX38: =+'Exp 2024'!Z46 -> 20000 | BB38: =+'Exp 2025'!AC47 -> 0 | BF38: =+'Exp 2025'!AE47 -> 0 | BJ38: =+'Exp 2025'!AG47 -> 27150 | BN38: =+'Exp 2025'!AI47 -> 6980 | BR38: =+'Exp 2025'!AK47 -> 20000 | BV38: =+'Exp 2025'!AM47 -> 5250 | BZ38: 0 | CD38: =+'Exp 2025'!AQ47 -> 9500 | CH38: =+'Exp 2025'!AS47 -> 48300 | CL38: =+'Exp 2025'!AU47 -> 101200 | CP38: =+'Exp 2025'!AW47 -> 24000 | CT38: =+'Exp 2025'!AY47 -> 38980 | CX38: =+BB38+BF38+BJ38+BN38+BR38+BV38+BZ38 -> 59380
C39: Play Area Expenses | F39: 0 | J39: 0 | N39: =+Exp!AF68 -> 7000 | R39: =+'Exp 2024'!J69 -> 8500 | V39: =+'Exp 2024'!N69 -> 0 | Z39: =+'Exp 2024'!X69 -> 0 | AD39: 0 | AH39: 0 | AL39: 0 | AP39: 0 | AT39: 0 | AX39: 0 | BB39: 0 | BF39: 0 | BJ39: =+'Exp 2025'!AG70 -> 400 | BN39: =+'Exp 2025'!AI70 -> 19600 | BR39: 0 | BV39: 0 | BZ39: =+'Exp 2025'!AO70 -> 31000 | CD39: 0 | CH39: 0 | CL39: 0 | CP39: 0 | CT39: 0 | CX39: =+BB39+BF39+BJ39+BN39+BR39+BV39+BZ39 -> 51000
C40: =+'Exp 2025'!B111 -> New Cameras Installation/Purchases | F40: 0 | J40: 0 | N40: 0 | R40: 0 | V40: 0 | Z40: 0 | AD40: 0 | AH40: 0 | AL40: 0 | AP40: 0 | AT40: 0 | AX40: 0 | BB40: 0 | BF40: 0 | BJ40: 0 | BN40: 0 | BR40: 0 | BV40: 0 | BZ40: =+'Exp 2025'!AO111 -> 80000 | CD40: =+'Exp 2025'!AQ112 -> 124000 | CH40: =+'Exp 2025'!AS111 -> 18000 | CL40: =+'Exp 2025'!AU112 -> 65000 | CP40: =+'Exp 2025'!AW112 -> 109000 | CT40: 0 | CX40: =+BB40+BF40+BJ40+BN40+BR40+BV40+BZ40 -> 80000
C41: Adjustment - Old Maintenance issue adjusted | CD41: =+'Recpt 2025'!CW81 -> 14500 | CH41: =+'Recpt 2025'!DA81 -> 0 | CP41: 0 | CT41: 0
C42: Registration Expense of AV Union | AH42: =+'Exp 2024'!R59 -> 100000 | AL42: 0 | AP42: =+'Exp 2024'!V59 -> 80000 | AT42: 0 | AX42: =+'Exp 2024'!Z59 -> 12000 | BB42: 0 | BF42: 0 | BJ42: 0 | BN42: 0 | BR42: 0 | BV42: 0 | CP42: 0 | CT42: 0 | CX42: =+BB42+BF42+BJ42+BN42+BR42+BV42+BZ42 -> 0
F43: =SUM(F19:F40) -> 712305 | J43: =SUM(J19:J40) -> 666071 | N43: =SUM(N19:N40) -> 708641 | R43: =SUM(R19:R40) -> 666802 | V43: =SUM(V19:V40) -> 534100 | Z43: =SUM(Z19:Z40) -> 698134 | AD43: =SUM(AD19:AD40) -> 884891 | AH43: =SUM(AH19:AH42) -> 830664 | AL43: =SUM(AL19:AL42) -> 542130 | AP43: =SUM(AP19:AP42) -> 650998 | AT43: =SUM(AT19:AT42) -> 731154 | AX43: =SUM(AX19:AX42) -> 852282 | BB43: =SUM(BB19:BB42) -> 572277 | BF43: =SUM(BF19:BF42) -> 778328 | BJ43: =SUM(BJ19:BJ42) -> 1464758 | BN43: =SUM(BN19:BN42) -> 785813 | BR43: =SUM(BR19:BR42) -> 705590 | BV43: =SUM(BV19:BV42) -> 819558 | BZ43: =SUM(BZ19:BZ42) -> 4114035 | CD43: =SUM(CD19:CD42) -> 783572 | CH43: =SUM(CH19:CH42) -> 813732 | CL43: =SUM(CL19:CL42) -> 1221338 | CP43: =SUM(CP19:CP42) -> 1194342 | CT43: =SUM(CT19:CT42) -> 583171 | CX43: =SUM(CX19:CX42) -> 9240359
B44: Cash in Hand - Closing Balance | H44: =H8+F16-F43 -> 5868083 | L44: =L8+J16-J43 -> 5402512 | P44: =P8+N16-N43 -> 4906871 | T44: =T8+R16-R43 -> 6708131.5 | X44: =X8+V16-V43 -> 6335031.5 | AB44: =AB8+Z16-Z43 -> 5916397.5 | AF44: =AF8+AD16-AD43 -> 7296569.5 | AJ44: =AJ8+AH16-AH43 -> 6644905.5 | AN44: =AN8+AL16-AL43 -> 6393275.5 | AR44: =AR8+AP16-AP43 -> 8088340.5 | AV44: =AV8+AT16-AT43 -> 7578686.5 | AZ44: =AZ8+AX16-AX43 -> 7140404.5 | BD44: =BD8+BB16-BB43 -> 8934190.5 | BH44: =BH8+BF16-BF43 -> 8376862.5 | BL44: =BL8+BJ16-BJ43 -> 7269104.5 | BP44: =BP8+BN16-BN43 -> 6903791.5 | BT44: =BT8+BR16-BR43 -> 8155264.1 | BX44: =BX8+BV16-BV43 -> 7555206.1 | CB44: =CB8+BZ16-BZ43 -> 3819671.1 | CF44: =CF8+CD16-CD43 -> 6119099.1 | CJ44: =CJ8+CH16-CH43 -> 6605867.1 | CN44: =CN8+CL16-CL43 -> 6121029.1 | CR44: =CR8+CP16-CP43 -> 6154187.1 | CV44: =CV8+CT16-CT43 -> 6442017.1
B46: Funds in Hand
C47: Danish | H47: =+'Funds Breakup'!C5+'Funds Breakup'!C26 -> 5868083 | L47: =+'Funds Breakup'!C5+'Funds Breakup'!C26+'Funds Breakup'!C47 -> 5402512 | P47: =+'Funds Breakup'!C5+'Funds Breakup'!C26+'Funds Breakup'!C47+'Funds Breakup'!C71 -> 4906871 | T47: =+'Funds Breakup'!C5+'Funds Breakup'!C26+'Funds Breakup'!C47+'Funds Breakup'!C71+'Funds Breakup'!C95 -> 6708131.5 | X47: =+'Funds Breakup'!C5+'Funds Breakup'!C26+'Funds Breakup'!C47+'Funds Breakup'!C71+'Funds Breakup'!C95+'Funds Breakup'!C119 -> 6335031.5 | AB47: =+'Funds Breakup'!C5+'Funds Breakup'!C26+'Funds Breakup'!C47+'Funds Breakup'!C71+'Funds Breakup'!C95+'Funds Breakup'!C119+'Funds Breakup'!C144 -> 5916397.5 | AF47: =+'Funds Breakup'!C5+'Funds Breakup'!C26+'Funds Breakup'!C47+'Funds Breakup'!C71+'Funds Breakup'!C95+'Funds Breakup'!C119+'Funds Breakup'!C144+'Funds Breakup'!C168 -> 7296569.5 | AJ47: =+'Funds Breakup'!C5+'Funds Breakup'!C26+'Funds Breakup'!C47+'Funds Breakup'!C71+'Funds Breakup'!C95+'Funds Breakup'!C119+'Funds Breakup'!C144+'Funds Breakup'!C168+'Funds Breakup'!C194 -> 6644905.5 | AN47: =+'Funds Breakup'!C5+'Funds Breakup'!C26+'Funds Breakup'!C47+'Funds Breakup'!C71+'Funds Breakup'!C95+'Funds Breakup'!C119+'Funds Breakup'!C144+'Funds Breakup'!C168+'Funds Breakup'!C194+'Funds Breakup'!C218 -> 6393275.5 | AR47: =+'Funds Breakup'!C5+'Funds Breakup'!C26+'Funds Breakup'!C47+'Funds Breakup'!C71+'Funds Breakup'!C95+'Funds Breakup'!C119+'Funds Breakup'!C144+'Funds Breakup'!C168+'Funds Breakup'!C194+'Funds Breakup'!C218+'Funds Breakup'!C242 -> 8088340.5 | AV47: =+'Funds Breakup'!C5+'Funds Breakup'!C26+'Funds Breakup'!C47+'Funds Breakup'!C71+'Funds Breakup'!C95+'Funds Breakup'!C119+'Funds Breakup'!C144+'Funds Breakup'!C168+'Funds Breakup'!C194+'Funds Breakup'!C218+'Funds Breakup'!C242+'Funds Breakup'!C266 -> 7578686.5 | AZ47: ='Funds Breakup'!C5+'Funds Breakup'!C26+'Funds Breakup'!C47+'Funds Breakup'!C71+'Funds Breakup'!C95+'Funds Breakup'!C119+'Funds Breakup'!C144+'Funds Breakup'!C168+'Funds Breakup'!C194+'Funds Breakup'!C218+'Funds Breakup'!C242+'Funds Breakup'!C266+'Funds Breakup'!C290 -> 7140404.5 | BD47: =+'Funds Breakup'!C292+'Funds Breakup'!C317 -> 8934190.5 | BH47: =+'Funds Breakup'!C292+'Funds Breakup'!C317+'Funds Breakup'!C344 -> 8376862.5 | BL47: =+'Funds Breakup'!C292+'Funds Breakup'!C317+'Funds Breakup'!C344+'Funds Breakup'!C371 -> 7269104.5 | BP47: =+'Funds Breakup'!C292+'Funds Breakup'!C317+'Funds Breakup'!C344+'Funds Breakup'!C371+'Funds Breakup'!C398 -> 6903791.5 | BT47: =+'Funds Breakup'!C292+'Funds Breakup'!C317+'Funds Breakup'!C344+'Funds Breakup'!C371+'Funds Breakup'!C398+'Funds Breakup'!C425 -> 8155264.1 | BX47: =+'Funds Breakup'!C292+'Funds Breakup'!C317+'Funds Breakup'!C344+'Funds Breakup'!C371+'Funds Breakup'!C398+'Funds Breakup'!C425+'Funds Breakup'!C452 -> 7555206.1 | CB47: =+'Funds Breakup'!C292+'Funds Breakup'!C317+'Funds Breakup'!C344+'Funds Breakup'!C371+'Funds Breakup'!C398+'Funds Breakup'!C425+'Funds Breakup'!C452+'Funds Breakup'!C478 -> 3819671.1 | CF47: =+'Funds Breakup'!C292+'Funds Breakup'!C317+'Funds Breakup'!C344+'Funds Breakup'!C371+'Funds Breakup'!C398+'Funds Breakup'!C425+'Funds Breakup'!C452+'Funds Breakup'!C478+'Funds Breakup'!C504 -> 4315241.1 | CJ47: =+'Funds Breakup'!C292+'Funds Breakup'!C317+'Funds Breakup'!C344+'Funds Breakup'!C371+'Funds Breakup'!C398+'Funds Breakup'!C425+'Funds Breakup'!C452+'Funds Breakup'!C478+'Funds Breakup'!C504+'Funds Breakup'!C531 -> 2823241.1 | CN47: =+'Funds Breakup'!C292+'Funds Breakup'!C317+'Funds Breakup'!C344+'Funds Breakup'!C371+'Funds Breakup'!C398+'Funds Breakup'!C425+'Funds Breakup'!C452+'Funds Breakup'!C478+'Funds Breakup'!C504+'Funds Breakup'!C531+'Funds Breakup'!C558 -> 2923241.1 | CR47: =+'Funds Breakup'!C292+'Funds Breakup'!C317+'Funds Breakup'!C344+'Funds Breakup'!C371+'Funds Breakup'!C398+'Funds Breakup'!C425+'Funds Breakup'!C452+'Funds Breakup'!C478+'Funds Breakup'!C504+'Funds Breakup'!C531+'Funds Breakup'!C558+'Funds Breakup'!C582 -> 2923241.1 | CV47: =+'Funds Breakup'!C292+'Funds Breakup'!C317+'Funds Breakup'!C344+'Funds Breakup'!C371+'Funds Breakup'!C398+'Funds Breakup'!C425+'Funds Breakup'!C452+'Funds Breakup'!C478+'Funds Breakup'!C504+'Funds Breakup'!C531+'Funds Breakup'!C558+'Funds Breakup'!C582+'Funds Breakup'!C606 -> 2923241.1
C48: Ali | CB48: 0 | CF48: 0 | CJ48: =+'Funds Breakup'!O478+'Funds Breakup'!O504+'Funds Breakup'!O531+'Funds Breakup'!O558 -> 930000 | CN48: =+'Funds Breakup'!O478+'Funds Breakup'!O504+'Funds Breakup'!O531+'Funds Breakup'!O558 -> 930000 | CR48: =+'Funds Breakup'!O478+'Funds Breakup'!O504+'Funds Breakup'!O531+'Funds Breakup'!O558+'Funds Breakup'!O582 -> 930000 | CV48: =+'Funds Breakup'!O478+'Funds Breakup'!O504+'Funds Breakup'!O531+'Funds Breakup'!O558+'Funds Breakup'!O582+'Funds Breakup'!O606 -> 930000 | DB48: 910000
C49: Dilshad | CB49: 0 | CF49: =+'Funds Breakup'!I478+'Funds Breakup'!I504 -> 1000000 | CJ49: =+'Funds Breakup'!I478+'Funds Breakup'!I504+'Funds Breakup'!I531 -> 604580 | CN49: =+'Funds Breakup'!I478+'Funds Breakup'!I504+'Funds Breakup'!I531+'Funds Breakup'!I558 -> 548360 | CR49: =+'Funds Breakup'!I478+'Funds Breakup'!I504+'Funds Breakup'!I531+'Funds Breakup'!I558+'Funds Breakup'!I582 -> 646938 | CV49: =+'Funds Breakup'!I478+'Funds Breakup'!I504+'Funds Breakup'!I531+'Funds Breakup'!I558+'Funds Breakup'!I582+'Funds Breakup'!I606 -> 982878 | DB49: 1000000
C50: Asif | CB50: 0 | CF50: 0 | CJ50: =+'Funds Breakup'!L478+'Funds Breakup'!L504+'Funds Breakup'!L531 -> 1381000 | CN50: =+'Funds Breakup'!L478+'Funds Breakup'!L504+'Funds Breakup'!L531+'Funds Breakup'!L558 -> 1381000 | CR50: =+'Funds Breakup'!L478+'Funds Breakup'!L504+'Funds Breakup'!L531+'Funds Breakup'!L558+'Funds Breakup'!L582 -> 1381000 | CV50: =+'Funds Breakup'!L478+'Funds Breakup'!L504+'Funds Breakup'!L531+'Funds Breakup'!L558+'Funds Breakup'!L582+'Funds Breakup'!L606 -> 1381000 | DB50: 783000
C51: Naveed | CB51: 0 | CF51: =+'Funds Breakup'!F478+'Funds Breakup'!F504 -> 803858 | CJ51: =+'Funds Breakup'!F478+'Funds Breakup'!F504+'Funds Breakup'!F531 -> 867046 | CN51: =+'Funds Breakup'!F478+'Funds Breakup'!F504+'Funds Breakup'!F531+'Funds Breakup'!F558 -> 338428 | CR51: =+'Funds Breakup'!F478+'Funds Breakup'!F504+'Funds Breakup'!F531+'Funds Breakup'!F558+'Funds Breakup'!F582 -> 273008 | CV51: =+'Funds Breakup'!F478+'Funds Breakup'!F504+'Funds Breakup'!F531+'Funds Breakup'!F558+'Funds Breakup'!F582+'Funds Breakup'!F606 -> 224898
H52: =SUM(H47) -> 5868083 | L52: =SUM(L47:L47) -> 5402512 | P52: =SUM(P47:P47) -> 4906871 | T52: =SUM(T47:T47) -> 6708131.5 | X52: =SUM(X47:X47) -> 6335031.5 | AB52: =SUM(AB47:AB47) -> 5916397.5 | AF52: =SUM(AF47:AF47) -> 7296569.5 | AJ52: =SUM(AJ47:AJ47) -> 6644905.5 | AN52: =SUM(AN47:AN47) -> 6393275.5 | AR52: =SUM(AR47:AR47) -> 8088340.5 | AV52: =SUM(AV47:AV47) -> 7578686.5 | AZ52: =SUM(AZ47:AZ47) -> 7140404.5 | BD52: =SUM(BD47:BD47) -> 8934190.5 | BH52: =SUM(BH47:BH47) -> 8376862.5 | BL52: =SUM(BL47:BL47) -> 7269104.5 | BP52: =SUM(BP47:BP47) -> 6903791.5 | BT52: =SUM(BT47:BT47) -> 8155264.1 | BX52: =SUM(BX47:BX47) -> 7555206.1 | CB52: =SUM(CB47:CB51) -> 3819671.1 | CF52: =SUM(CF47:CF51) -> 6119099.1 | CJ52: =SUM(CJ47:CJ51) -> 6605867.1 | CN52: =SUM(CN47:CN51) -> 6121029.1 | CR52: =SUM(CR47:CR51) -> 6154187.1 | CV52: =SUM(CV47:CV51) -> 6442017.1
H55: =H52-H44 -> 0 | L55: =L52-L44 -> 0 | P55: =P52-P44 -> 0 | T55: =T52-T44 -> 0 | X55: =X52-X44 -> 0 | AB55: =AB52-AB44 -> 0 | AF55: =AF52-AF44 -> 0 | AJ55: =AJ52-AJ44 -> 0 | AN55: =AN52-AN44 -> 0 | AR55: =AR52-AR44 -> 0 | AV55: =AV52-AV44 -> 0 | AZ55: =AZ52-AZ44 -> 0 | BD55: =BD52-BD44 -> 0 | BH55: =BH52-BH44 -> 0 | BL55: =BL52-BL44 -> 0 | BP55: =BP52-BP44 -> 0 | BT55: =BT52-BT44 -> 0 | BX55: =BX52-BX44 -> 0 | CB55: =CB52-CB44 -> 0 | CF55: =CF52-CF44 -> 0 | CJ55: =CJ52-CJ44 -> 0 | CN55: =CN52-CN44 -> 0 | CR55: =CR52-CR44 -> 0 | CV55: =CV52-CV44 -> 0

Sheet Recpt 2025
B3: Anum Vista | AP3: Anum Vista | DR3: Anum Vista | EG3: Anum Vista
B4: Residents - Receipts - Till Jul 2025 | AP4: Residents - Receipts 2024 | DR4: Residents - Consolidated Oustanding Maintenance Position as of Mar 31, 2024 | EG4: Residents - Consolidated Oustanding Maintenance Position as of Jan 31, 2026
B5: Particulars | D5: Advance / Overdue | E5: 44927 | H5: 44958 | K5: 44986 | N5: 45017 | Q5: 45047 | T5: 45078 | W5: 45108 | Z5: 45139 | AC5: 45170 | AF5: 45200 | AI5: 45231 | AL5: 45261 | AP5: 45292 | AS5: 45323 | AV5: 45352 | AY5: 45383 | BB5: 45413 | BE5: 45444 | BH5: 45474 | BK5: 45505 | BN5: 45536 | BQ5: 45566 | BT5: 45597 | BW5: 45627 | CA5: 45658 | CD5: 45689 | CG5: 45717 | CJ5: 45748 | CM5: 45778 | CP5: 45809 | CS5: 45839 | CV5: 45870 | CY5: 45901 | DB5: 45931 | DE5: 45962 | DH5: 45992 | DK5: 46023 | DN5: 46054 | DR5: Appartment No. | DS5: Name of Resident | DT5: Monthly Maintenance | DU5: Maintenance Recived during the Year 2023 | DV5: Due for the Year 2023 | DW5: Due for the last Year 2022 | DX5: Total Amount Due (2022+2023) | DY5: Maintenance Amount for the year 2024 | DZ5: Maintenance Amount Received till Dec 31, 2024 | EA5: Outstanding amount till Dec 31, 2024 | EB5: Maintenance Amount for the year 2025 | EC5: Maintenance Recived till Dec 31 2025 | ED5: Outstanding amount till Dec 31, 2025 | EE5: One time adjustment | EG5: Appartment No. | EH5: Name of Resident | EI5: Monthly Maintenance | EJ5: Dues till Dec 31, 2025 | EK5: Maintenance amunt till Feb 2026 | EL5: Maintenance Recived during the Year 2026 | EM5: Dues till Feb, 2026
B6: Residents Name | C6: Appartment No. | E6: Amount | F6: Receipt No. | G6: Date | H6: Amount | I6: Receipt No. | J6: Date | K6: Amount | L6: Receipt No. | M6: Date | N6: Amount | O6: Receipt No. | P6: Date | Q6: Amount | R6: Receipt No. | S6: Date | T6: Amount | U6: Receipt No. | V6: Date | W6: Amount | X6: Receipt No. | Y6: Date | Z6: Amount | AA6: Receipt No. | AB6: Date | AC6: Amount | AD6: Receipt No. | AE6: Date | AF6: Amount | AG6: Receipt No. | AH6: Date | AI6: Amount | AJ6: Receipt No. | AK6: Date | AL6: Amount | AM6: Receipt No. | AN6: Date | AP6: Amount | AQ6: Receipt No. | AR6: Date | AS6: Amount | AT6: Receipt No. | AU6: Date | AV6: Amount | AW6: Receipt No. | AX6: Date | AY6: Amount | AZ6: Receipt No. | BA6: Date | BB6: Amount | BC6: Receipt No. | BD6: Date | BE6: Amount | BF6: Receipt No. | BG6: Date | BH6: Amount | BI6: Receipt No. | BJ6: Date | BK6: Amount | BL6: Receipt No. | BM6: Date | BN6: Amount | BO6: Receipt No. | BP6: Date | BQ6: Amount | BR6: Receipt No. | BS6: Date | BT6: Amount | BU6: Receipt No. | BV6: Date | BW6: Amount | BX6: Receipt No. | BY6: Date | CA6: Amount | CB6: Receipt No. | CC6: Date | CD6: Amount | CE6: Receipt No. | CF6: Date | CG6: Amount | CH6: Receipt No. | CI6: Date | CJ6: Amount | CK6: Receipt No. | CL6: Date | CM6: Amount | CN6: Receipt No. | CO6: Date | CP6: Amount | CQ6: Receipt No. | CR6: Date | CS6: Amount | CT6: Receipt No. | CU6: Date | CV6: Amount | CW6: Receipt No. | CX6: Date | CY6: Amount | CZ6: Receipt No. | DA6: Date | DB6: Amount | DC6: Receipt No. | DD6: Date | DE6: Amount | DF6: Receipt No. | DG6: Date | DH6: Amount | DI6: Receipt No. | DJ6: Date | DK6: Amount | DL6: Receipt No. | DM6: Date | DN6: Amount | DO6: Receipt No. | DP6: Date
B8: Mr. Rehan | C8: 101 | D8: =-15000+-7500+22500 -> 0 | H8: 15000 | I8: 1302 | J8: 44958 | K8: 7500 | L8: 1345 | M8: 44988 | N8: 7500 | O8: 1368 | P8: 45019 | Q8: 7500 | R8: 1417 | S8: 45062 | T8: 7500 | U8: 1446 | V8: 45107 | W8: 7500 | X8: 1447 | Y8: 45110 | AC8: =7500+7500 -> 15000 | AD8: 1508/1509 | AE8: 45173 | AL8: 15000 | AM8: 1573 | AN8: 45263 | AP8: =7500+15000 -> 22500 | AQ8: 1620/1621 | AR8: Jan 20, 25 - 2024 | AS8: 7500 | AT8: 1644 | AU8: 45351 | AV8: 7500 | AW8: 1656 | AX8: 45356 | AY8: 7500 | AZ8: 1682 | BA8: 45387 | BB8: 7500 | BC8: 1706 | BD8: 45414 | BE8: 7500 | BF8: 1734 | BG8: 45446 | BK8: 15000 | BL8: 1782 | BM8: 45510 | BN8: 7500 | BO8: 1835 | BP8: 45538 | BQ8: 7500 | BR8: 1836 | BS8: 45568 | CA8: 15000 | CB8: 1928 | CC8: 45668 | CS8: 57000 | CT8: 057 | CU8: 45849 | CY8: 28500 | CZ8: 128 | DA8: 45908 | DK8: 28500 | DL8: 229 | DM8: 46028 | DR8: 101 | DS8: Mr. Rehan | DT8: =7500*12 -> 90000 | DU8: =E8+H8+K8+N8+Q8+T8+W8+Z8+AC8+AF8+AI8+AL8 -> 82500 | DV8: =DT8-DU8 -> 7500 | DW8: 7500 | DX8: =DV8+DW8 -> 15000 | DY8: =7500*12 -> 90000 | DZ8: =+AP8+AS8+AV8+AY8+BB8+BE8+BH8+BK8+BN8+BQ8+BT8+BW8 -> 90000 | EA8: =DX8+DY8-DZ8 -> 15000 | EB8: =9500*12 -> 114000 | EC8: =CA8+CD8+CG8+CJ8+CM8+CP8+CS8+CV8+CY8+DB8+DE8+DH8 -> 100500 | ED8: =EA8+EB8-EC8 -> 28500 | EG8: 101 | EH8: Mr. Rehan | EI8: =9500*12 -> 114000 | EJ8: 28500 | EK8: =9500*2 -> 19000 | EL8: =DK8+DN8 -> 28500 | EM8: =EJ8+EK8-EL8 -> 19000
B9: Mr. Faisal A. Khan | C9: 102 | D9: =-21000-7000+14000-7000-7000-7000+21000 -> -14000 | H9: 7000 | I9: 1328 | J9: 44975 | K9: 7000 | L9: 1343 | M9: 44989 | N9: 7000 | O9: 1389 | P9: 45029 | T9: =7000+7000 -> 14000 | U9: 1426/1427 | V9: 45080 | Z9: =7000+7000 -> 14000 | AA9: 1495/1496 | AB9: 45158 | AI9: 21000 | AJ9: 1553 | AK9: 45237 | AP9: =7000+7000 -> 14000 | AQ9: 1605/1606 | AR9: 45305 | AY9: =7000+7000+7000 -> 21000 | AZ9: 1691/1692/1693 | BA9: 45399 | BN9: =7000+7000+7000+7000 -> 28000 | BO9: 1824 to 1827 | BP9: 45559 | CD9: =7000+7000+7000+7000+7000 -> 35000 | CE9: 1955 to 1959 | CF9: 45713 | CS9: 7000 | CT9: 1828 Adj | CU9: 45559 | CV9: =7000*6 -> 42000 | CW9: 114 | CX9: 45900 | CY9: 7000 | CZ9: 137 | DA9: 45927 | DB9: 7000 | DC9: 170 | DD9: 45960 | DK9: 14000 | DL9: 239 | DM9: 46030 | DN9: 7000 | DO9: 263 | DP9: 46058 | DR9: 102 | DS9: Mr. Faisal A. Khan | DT9: =7000*12 -> 84000 | DU9: =E9+H9+K9+N9+Q9+T9+W9+Z9+AC9+AF9+AI9+AL9 -> 70000 | DV9: =DT9-DU9 -> 14000 | DW9: 7000 | DX9: =DV9+DW9 -> 21000 | DY9: =7000*12 -> 84000 | DZ9: =+AP9+AS9+AV9+AY9+BB9+BE9+BH9+BK9+BN9+BQ9+BT9+BW9 -> 63000 | EA9: =DX9+DY9-DZ9 -> 42000 | EB9: =7000*12 -> 84000 | EC9: =CA9+CD9+CG9+CJ9+CM9+CP9+CS9+CV9+CY9+DB9+DE9+DH9 -> 98000 | ED9: =EA9+EB9-EC9 -> 28000 | EG9: 102 | EH9: Mr. Faisal A. Khan | EI9: =7000*12 -> 84000 | EJ9: 28000 | EK9: =7000*2 -> 14000 | EL9: =DK9+DN9 -> 21000 | EM9: =EJ9+EK9-EL9 -> 21000
B10: Mrs. Rashid | C10: 103 | D10: =2500-2500 -> 0 | H10: 5000 | I10: 1332 | J10: 44983 | K10: 2500 | L10: 1380 | M10: 45016 | Q10: 5000 | R10: 1421 | S10: 45066 | AC10: 10000 | AD10: 1540 | AE10: 45199 | AL10: 7500 | AM10: 1611 | AN10: 45291 | AV10: 7500 | AW10: 1700 | AX10: 45362 | AY10: 0 | BE10: 7500 | BF10: 1741 | BG10: 45473 | BW10: 15000 | BX10: 1899 | BY10: 45656 | CG10: 7500 | CH10: 2000 | CI10: 45747 | CS10: 10000 | CT10: 073 | CU10: 45869 | CV10: 2500 | CW10: 111 | CX10: 45900 | CY10: 2500 | CZ10: 147 | DA10: 45930 | DB10: 2500 | DC10: 179 | DD10: 45961 | DH10: 5000 | DI10: 222 | DJ10: 46022 | DR10: 103 | DS10: Mrs. Rashid | DT10: =2500*12 -> 30000 | DU10: =E10+H10+K10+N10+Q10+T10+W10+Z10+AC10+AF10+AI10+AL10 -> 30000 | DV10: =DT10-DU10 -> 0 | DW10: 0 | DX10: =DV10+DW10 -> 0 | DY10: =2500*12 -> 30000 | DZ10: =+AP10+AS10+AV10+AY10+BB10+BE10+BH10+BK10+BN10+BQ10+BT10+BW10 -> 30000 | EA10: =DX10+DY10-DZ10 -> 0 | EB10: =2500*12 -> 30000 | EC10: =CA10+CD10+CG10+CJ10+CM10+CP10+CS10+CV10+CY10+DB10+DE10+DH10 -> 30000 | ED10: =EA10+EB10-EC10 -> 0 | EG10: 103 | EH10: Mrs. Rashid | EI10: =2500*12 -> 30000 | EJ10: 0 | EK10: =2500*2 -> 5000 | EL10: =DK10+DN10 -> 0 | EM10: =EJ10+EK10-EL10 -> 5000
B11: Mr. Dilshad | C11: 104 | D11: 0 | E11: 7000 | F11: 1282 | G11: 44932 | H11: 7000 | I11: 1312 | J11: 44963 | K11: 7000 | L11: 1346 | M11: 44990 | N11: 7000 | O11: 1366 | P11: 45018 | Q11: 7000 | R11: 1401 | S11: 45054 | T11: 7000 | U11: 1433 | V11: 45085 | W11: 7000 | X11: 1450 | Y11: 45110 | Z11: 7000 | AA11: 1474 | AB11: 45140 | AC11: 7000 | AD11: 1505 | AE11: 45171 | AF11: 7000 | AG11: 1530 | AH11: 45202 | AI11: 7000 | AJ11: 1555 | AK11: 45237 | AL11: 7000 | AM11: 1572 | AN11: 45262 | AP11: 7000 | AQ11: 1595 | AR11: 45297 | AS11: 7000 | AT11: 1628 | AU11: 45326 | AV11: 7000 | AW11: 1660 | AX11: 45362 | AY11: 7000 | AZ11: 1683 | BA11: 45388 | BB11: 7000 | BC11: 1712 | BD11: 45420 | BE11: 7000 | BF11: 1731 | BG11: 45444 | BH11: 7000 | BI11: 1757 | BJ11: 45477 | BK11: 7000 | BL11: 1753 | BM11: 45477 | BN11: 7000 | BO11: 1813 | BP11: 45541 | BQ11: 7000 | BR11: 1839 | BS11: 45570 | BW11: 14000 | BX11: 1908 | BY11: 45656 | CA11: 7000 | CB11: 1924 | CC11: 45667 | CV11: 49000 | CW11: 095 | CX11: 45892 | CY11: 7000 | CZ11: 118 | DA11: 45905 | DE11: 14000 | DF11: 180 | DG11: 45965 | DH11: 7000 | DI11: 217 | DJ11: 46010 | DK11: 7000 | DL11: 237 | DM11: 46029 | DN11: 7000 | DO11: 254 | DP11: 46055 | DR11: 104 | DS11: Mr. Dilshad | DT11: =7000*12 -> 84000 | DU11: =E11+H11+K11+N11+Q11+T11+W11+Z11+AC11+AF11+AI11+AL11 -> 84000 | DV11: =DT11-DU11 -> 0 | DW11: 0 | DX11: =DV11+DW11 -> 0 | DY11: =7000*12 -> 84000 | DZ11: =+AP11+AS11+AV11+AY11+BB11+BE11+BH11+BK11+BN11+BQ11+BT11+BW11 -> 84000 | EA11: =DX11+DY11-DZ11 -> 0 | EB11: =7000*12 -> 84000 | EC11: =CA11+CD11+CG11+CJ11+CM11+CP11+CS11+CV11+CY11+DB11+DE11+DH11 -> 84000 | ED11: =EA11+EB11-EC11 -> 0 | EG11: 104 | EH11: Mr. Dilshad | EI11: =7000*12 -> 84000 | EJ11: 0 | EK11: =7000*2 -> 14000 | EL11: =DK11+DN11 -> 14000 | EM11: =EJ11+EK11-EL11 -> 0
B13: Mr. Kashif Shamim | C13: 201 | D13: 0 | E13: 5500 | F13: 1294 | G13: 44927 | H13: 5500 | I13: 1301 | J13: 44958 | K13: 5500 | L13: 1333 | M13: 44987 | N13: 5500 | O13: 1367 | P13: 45018 | Q13: 5500 | R13: 1395 | S13: 45047 | T13: 5500 | U13: 1425 | V13: 45078 | W13: 5500 | X13: 1449 | Y13: 45110 | Z13: 5500 | AA13: 1472 | AB13: 45140 | AC13: 5500 | AD13: 1507 | AE13: 45171 | AF13: 5500 | AG13: 1526 | AH13: 45201 | AI13: 5500 | AJ13: 1551 | AK13: 45232 | AL13: 5500 | AM13: 1570 | AN13: 45261 | AP13: 5500 | AQ13: 1592 | AR13: 45293 | AS13: 5500 | AT13: 1623 | AU13: 45323 | AV13: 5500 | AW13: 1652 | AX13: 45353 | AY13: 5500 | AZ13: 1672 | BA13: 45383 | BB13: 5500 | BC13: 1707 | BD13: 45414 | BE13: 5500 | BF13: 1732 | BG13: 45444 | BH13: 5500 | BI13: 1755 | BJ13: 45475 | BK13: 5500 | BL13: 1774 | BM13: 45505 | BN13: 5500 | BO13: 1803 | BP13: 45536 | BQ13: 5500 | BR13: 1829 | BS13: 45566 | BT13: 5500 | BU13: 1853 | BV13: 45597 | BW13: 5500 | BX13: 1880 | BY13: 45627 | CA13: 5500 | CB13: 1915 | CC13: 45658 | CD13: 5500 | CE13: 1935 | CF13: 45689 | CG13: 5500 | CH13: 1961 | CI13: 45718 | CJ13: 5500 | CK13: 1982 | CL13: 45748 | CM13: 5500 | CN13: 006 | CO13: 45781 | CP13: 5500 | CQ13: 028 | CR13: 45810 | CS13: 5500 | CT13: 049 | CU13: 45839 | CV13: 5500 | CW13: 074 | CX13: 45873 | CY13: 5500 | CZ13: 123 | DA13: 45907 | DB13: 5500 | DC13: 153 | DD13: 45931 | DE13: 5500 | DF13: 173 | DG13: 45962 | DH13: 5500 | DI13: 202 | DJ13: 45992 | DK13: 5500 | DL13: 235 | DM13: 46028 | DN13: 5500 | DO13: 255 | DP13: 46055 | DR13: 201 | DS13: Mr. Kashif Shamim | DT13: =5500*12 -> 66000 | DU13: =E13+H13+K13+N13+Q13+T13+W13+Z13+AC13+AF13+AI13+AL13 -> 66000 | DV13: =DT13-DU13 -> 0 | DW13: 0 | DX13: =DV13+DW13 -> 0 | DY13: =5500*12 -> 66000 | DZ13: =+AP13+AS13+AV13+AY13+BB13+BE13+BH13+BK13+BN13+BQ13+BT13+BW13 -> 66000 | EA13: =DX13+DY13-DZ13 -> 0 | EB13: =5500*12 -> 66000 | EC13: =CA13+CD13+CG13+CJ13+CM13+CP13+CS13+CV13+CY13+DB13+DE13+DH13 -> 66000 | ED13: =EA13+EB13-EC13 -> 0 | EG13: 201 | EH13: Mr. Ammar | EI13: =5500*12 -> 66000 | EJ13: 0 | EK13: =5500*2 -> 11000 | EL13: =DK13+DN13 -> 11000 | EM13: =EJ13+EK13-EL13 -> 0
B14: Mr. Faisal | C14: 202 | D14: -1500 | E14: 7000 | F14: 1289 | G14: 44937 | H14: 7000 | I14: 1314 | J14: 44964 | K14: 7000 | L14: 1360 | M14: 45011 | T14: 21500 | U14: 1444 | V14: 45091 | AI14: 35000 | AJ14: 1567 | AK14: 45252 | AL14: 7000 | AM14: 1586 | AN14: 45282 | AY14: 28000 | AZ14: 1684 | BA14: 45387 | BN14: 35000 | BO14: 1808 | BP14: 45539 | BW14: 21000 | BX14: 1906 | BY14: 45656 | CS14: 36000 | CT14: 069 | CU14: 45853 | CV14: 26000 | CW14: 102 | CX14: 45899 | DB14: 14000 | DC14: 148 | DD14: 45931 | DK14: 21000 | DL14: 245 | DM14: 46034 | DR14: 202 | DS14: Mr. Faisal | DT14: =7000*12 -> 84000 | DU14: =E14+H14+K14+N14+Q14+T14+W14+Z14+AC14+AF14+AI14+AL14 -> 84500 | DV14: =DT14-DU14 -> -500 | DW14: 500 | DX14: =DV14+DW14 -> 0 | DY14: =7000*12 -> 84000 | DZ14: =+AP14+AS14+AV14+AY14+BB14+BE14+BH14+BK14+BN14+BQ14+BT14+BW14 -> 84000 | EA14: =DX14+DY14-DZ14 -> 0 | EB14: =7000+7000+7000+9000+9000+7000+9000+7000+7000+7000+7000+7000 -> 90000 | EC14: =CA14+CD14+CG14+CJ14+CM14+CP14+CS14+CV14+CY14+DB14+DE14+DH14 -> 76000 | ED14: =EA14+EB14-EC14 -> 14000 | EG14: 202 | EH14: Mr. Faisal | EI14: =7000*12 -> 84000 | EJ14: 14000 | EK14: =7000*2 -> 14000 | EL14: =DK14+DN14 -> 21000 | EM14: =EJ14+EK14-EL14 -> 7000
B15: Mr. Bakshish | C15: 203 | D15: 0 | E15: 21000 | F15: 1284 | G15: 44932 | H15: 7000 | I15: 1317 | J15: 44965 | N15: 14000 | O15: 1391 | P15: 45040 | T15: 14000 | U15: 1432 | V15: 45082 | Z15: 14000 | AA15: 1497 | AB15: 45159 | AI15: 28000 | AJ15: 1564 | AK15: 45248 | AS15: 14000 | AT15: 1638 | AU15: 45335 | AY15: 21000 | AZ15: 1701 | BA15: 45410 | BE15: 14000 | BF15: 1747 | BG15: 45456 | BT15: 28000 | BU15: 1859 | BV15: 45601 | BW15: 7000 | BX15: 1914 | BY15: 45657 | CM15: 35000 | CN15: 009 | CO15: 45785 | CP15: 7000 | CQ15: 034 | CR15: 45817 | CV15: 14000 | CW15: 094 | CX15: 45892 | CY15: 7000 | CZ15: 120 | DA15: 45905 | DB15: 7000 | DC15: 149 | DD15: 45931 | DE15: 7000 | DF15: 189 | DG15: 45969 | DH15: 7000 | DI15: 220 | DJ15: 46018 | DK15: 7000 | DL15: 241 | DM15: 46030 | DR15: 203 | DS15: Mr. Bakshish | DT15: =7000*12 -> 84000 | DU15: =E15+H15+K15+N15+Q15+T15+W15+Z15+AC15+AF15+AI15+AL15 -> 98000 | DV15: =DT15-DU15 -> -14000 | DW15: 14000 | DX15: =DV15+DW15 -> 0 | DY15: =7000*12 -> 84000 | DZ15: =+AP15+AS15+AV15+AY15+BB15+BE15+BH15+BK15+BN15+BQ15+BT15+BW15 -> 84000 | EA15: =DX15+DY15-DZ15 -> 0 | EB15: =7000*12 -> 84000 | EC15: =CA15+CD15+CG15+CJ15+CM15+CP15+CS15+CV15+CY15+DB15+DE15+DH15 -> 84000 | ED15: =EA15+EB15-EC15 -> 0 | EG15: 203 | EH15: Mr. Bakshish | EI15: =7000*12 -> 84000 | EJ15: 0 | EK15: =7000*2 -> 14000 | EL15: =DK15+DN15 -> 7000 | EM15: =EJ15+EK15-EL15 -> 7000
B16: Mr. Taimur | C16: 204 | D16: -7500 | E16: 7500 | F16: 1297 | G16: 44943 | H16: 7500 | I16: 1305 | J16: 44960 | K16: 7500 | L16: 1341 | M16: 44988 | N16: 7500 | O16: 1377 | P16: 45023 | Q16: 7500 | R16: 1398 | S16: 45049 | T16: 7500 | U16: 1430 | V16: 45081 | W16: 7500 | X16: 1468 | Y16: 45128 | Z16: 7500 | AA16: 1499 | AB16: 45163 | AC16: 7500 | AD16: 1522 | AE16: 45189 | AI16: 7500 | AJ16: 1558 | AK16: 45240 | AL16: 7500 | AM16: 1589 | AN16: 45290 | AP16: 15000 | AQ16: 1603 | AR16: 45302 | AS16: 7500 | AT16: 1647 | AU16: 45343 | AV16: 7500 | AW16: 1671 | AX16: 45375 | AY16: 7500 | AZ16: 1697 | BA16: 45407 | BB16: 7500 | BC16: 1728 | BD16: 45438 | BE16: 7500 | BF16: 1751 | BG16: 45471 | BH16: 7500 | BI16: 1777 | BJ16: 45503 | BK16: 7500 | BL16: 1801 | BM16: 45531 | BN16: 7500 | BO16: 1831 | BP16: 45565 | BQ16: 7500 | BR16: 1855 | BS16: 45596 | BW16: =7500+7500 -> 15000 | BX16: 1889/1910 | BY16: 9,30 Dec | CA16: 7500 | CB16: 1932 | CC16: 45683 | CD16: 7500 | CE16: 1965 | CF16: 45716 | CG16: 7500 | CH16: 1985 | CI16: 45746 | CJ16: 7500 | CK16: 1999 | CL16: 45773 | CV16: 30000 | CW16: 100 | CX16: 45894 | CY16: 7500 | CZ16: 138 | DA16: 45927 | DB16: 7500 | DC16: 168 | DD16: 45954 | DE16: 7500 | DF16: 201 | DG16: 45987 | DH16: 7500 | DI16: 219 | DJ16: 46017 | DK16: 7500 | DL16: 251 | DM16: 46052 | DR16: 204 | DS16: Mr. Taimur | DT16: =7500*12 -> 90000 | DU16: =E16+H16+K16+N16+Q16+T16+W16+Z16+AC16+AF16+AI16+AL16 -> 82500 | DV16: =DT16-DU16 -> 7500 | DW16: 0 | DX16: =DV16+DW16 -> 7500 | DY16: =7500*12 -> 90000 | DZ16: =+AP16+AS16+AV16+AY16+BB16+BE16+BH16+BK16+BN16+BQ16+BT16+BW16 -> 97500 | EA16: =DX16+DY16-DZ16 -> 0 | EB16: =7500*12 -> 90000 | EC16: =CA16+CD16+CG16+CJ16+CM16+CP16+CS16+CV16+CY16+DB16+DE16+DH16 -> 90000 | ED16: =EA16+EB16-EC16 -> 0 | EG16: 204 | EH16: Mr. Taimur | EI16: =7500*12 -> 90000 | EJ16: 0 | EK16: =7500*2 -> 15000 | EL16: =DK16+DN16 -> 7500 | EM16: =EJ16+EK16-EL16 -> 7500
B18: Mr. Zia | C18: 301 | D18: -5500 | E18: 5500 | F18: 1280 | G18: 44929 | H18: 5500 | I18: 1313 | J18: 44963 | K18: 5500 | L18: 1351 | M18: 44994 | N18: 5500 | O18: 1372 | P18: 45021 | Q18: 5500 | R18: 1409 | S18: 45056 | T18: 5500 | U18: 1435 | V18: 45087 | W18: 5500 | X18: 1469 | Y18: 45127 | Z18: 5500 | AA18: 1479 | AB18: 45144 | AC18: 5500 | AD18: 1725 | AE18: 45199 | AF18: 5500 | AG18: 1533 | AH18: 45207 | AI18: 5500 | AJ18: 1557 | AK18: 45239 | AL18: 5500 | AM18: 1577 | AN18: 45268 | AP18: 5500 | AQ18: 1607 | AR18: 45305 | AS18: 5500 | AT18: 1635 | AU18: 45335 | AV18: 5500 | AW18: 1661 | AX18: 45362 | AY18: 5500 | AZ18: 1687 | BA18: 45391 | BB18: 5500 | BC18: 1715 | BD18: 45424 | BE18: 5500 | BF18: 1740 | BG18: 45450 | BH18: 5500 | BI18: 1766 | BJ18: 45484 | BK18: 5500 | BL18: 1785 | BM18: 45513 | BN18: 5500 | BO18: 1815 | BP18: 45542 | BQ18: 5500 | BR18: 1846 | BS18: 45576 | BT18: 5500 | BU18: 1874 | BV18: 45610 | BW18: 5500 | BX18: 1891 | BY18: 45636 | CA18: 5500 | CB18: 1930 | CC18: 45673 | CD18: 5500 | CE18: 1943 | CF18: 45693 | CG18: 5500 | CH18: 1963 | CI18: 45718 | CJ18: 5500 | CK18: 1990 | CL18: 45758 | CM18: 5500 | CN18: 015 | CO18: 45788 | CP18: 5500 | CQ18: 040 | CR18: 45819 | CS18: 7500 | CT18: 062 | CU18: 45854 | CV18: 7500 | CW18: 086 | CX18: 45884 | CY18: 5500 | CZ18: 125 | DA18: 45907 | DB18: 5500 | DC18: 158 | DD18: 45937 | DE18: 5500 | DF18: 182 | DG18: 45966 | DH18: 5500 | DI18: 206 | DJ18: 45997 | DK18: 5500 | DL18: 233 | DM18: 46027 | DN18: 5500 | DO18: 264 | DP18: 46059 | DR18: 301 | DS18: Mr. Zia | DT18: =5500*12 -> 66000 | DU18: =E18+H18+K18+N18+Q18+T18+W18+Z18+AC18+AF18+AI18+AL18 -> 66000 | DV18: =DT18-DU18 -> 0 | DW18: 0 | DX18: =DV18+DW18 -> 0 | DY18: =5500*12 -> 66000 | DZ18: =+AP18+AS18+AV18+AY18+BB18+BE18+BH18+BK18+BN18+BQ18+BT18+BW18 -> 66000 | EA18: =DX18+DY18-DZ18 -> 0 | EB18: =5500+5500+5500+5500+5500+5500+7500+7500+5500+5500+5500+5500 -> 70000 | EC18: =CA18+CD18+CG18+CJ18+CM18+CP18+CS18+CV18+CY18+DB18+DE18+DH18 -> 70000 | ED18: =EA18+EB18-EC18 -> 0 | EG18: 301 | EH18: Mr. Zia | EI18: =5500*12 -> 66000 | EJ18: 0 | EK18: =5500*2 -> 11000 | EL18: =DK18+DN18 -> 11000 | EM18: =EJ18+EK18-EL18 -> 0
B19: Mr. Ashraf | C19: 302 | D19: =45000-7500-7500-7500-7500 -> 15000 | H19: 45000 | I19: 1326 | J19: 44971 | W19: 45000 | X19: 1456 | Y19: 45117 | AP19: 45000 | AQ19: 1619 | AR19: 45311 | BT19: 45000 | BU19: 1868 | BV19: 45608 | CG19: 45000 | CH19: 1980 | CI19: 45742 | CY19: 33000 | CZ19: 115 | DA19: 45905 | DR19: 302 | DS19: Mr. Ashraf | DT19: =7500*12 -> 90000 | DU19: =E19+H19+K19+N19+Q19+T19+W19+Z19+AC19+AF19+AI19+AL19 -> 90000 | DV19: =DT19-DU19 -> 0 | DW19: 0 | DX19: =DV19+DW19 -> 0 | DY19: =7500*12 -> 90000 | DZ19: =+AP19+AS19+AV19+AY19+BB19+BE19+BH19+BK19+BN19+BQ19+BT19+BW19 -> 90000 | EA19: =DX19+DY19-DZ19 -> 0 | EB19: =7500+7500+7500+7500+7500+7500+5500+5500+5500+5500+5500+5500 -> 78000 | EC19: =CA19+CD19+CG19+CJ19+CM19+CP19+CS19+CV19+CY19+DB19+DE19+DH19 -> 78000 | ED19: =EA19+EB19-EC19 -> 0 | EG19: 302 | EH19: Mr. Ashraf | EI19: =5500*12 -> 66000 | EJ19: 0 | EK19: =5500*2 -> 11000 | EL19: =DK19+DN19 -> 0 | EM19: =EJ19+EK19-EL19 -> 11000
B20: Mr. Mubeen | C20: 303 | D20: 0 | E20: 9000 | F20: 1292 | G20: 44939 | H20: 9000 | I20: 1310 | J20: 44960 | K20: 9000 | L20: 1352 | M20: 44995 | N20: 9000 | O20: 1371 | P20: 45027 | Q20: 9000 | R20: 1410 | S20: 45057 | T20: 9000 | U20: 1440 | V20: 45089 | W20: 9000 | X20: 1462 | Y20: 45118 | Z20: 9000 | AA20: 1491 | AB20: 45153 | AC20: 9000 | AD20: 1516 | AE20: 45180 | AF20: 9000 | AG20: 1534 | AH20: 45209 | AI20: 9000 | AJ20: 1554 | AK20: 45236 | AL20: 9000 | AM20: 1576 | AN20: 45267 | AP20: 9000 | AQ20: 1599 | AR20: 45302 | AS20: 9000 | AT20: 1636 | AU20: 45335 | AV20: 9000 | AW20: 1664 | AX20: 45362 | AY20: 9000 | AZ20: 1678 | BA20: 45386 | BB20: 9000 | BC20: 1716 | BD20: 45425 | BE20: 9000 | BF20: 1746 | BG20: 45456 | BH20: 9000 | BI20: 1760 | BJ20: 45480 | BK20: 9000 | BL20: 1783 | BM20: 45511 | BN20: 9000 | BO20: 1809 | BP20: 45540 | BQ20: 9000 | BR20: 1842 | BS20: 45571 | BT20: 9000 | BU20: 1875 | BV20: 45608 | BW20: 9000 | BX20: 1893 | BY20: 45641 | CA20: 9000 | CB20: 1922 | CC20: 45664 | CD20: 9000 | CE20: 1944 | CF20: 45696 | CG20: 9000 | CH20: 1979 | CI20: 45727 | CJ20: 9000 | CK20: 1989 | CL20: 45758 | CM20: 9000 | CN20: 019 | CO20: 45789 | CP20: 9000 | CQ20: 033 | CR20: 45816 | CS20: 9000 | CT20: 061 | CU20: 45853 | CV20: 9000 | CW20: 082 | CX20: 45877 | CY20: 9000 | CZ20: 126 | DA20: 45907 | DB20: 9000 | DC20: 161 | DD20: 45938 | DE20: 9000 | DF20: 184 | DG20: 45967 | DH20: 9000 | DI20: 210 | DJ20: 46002 | DK20: 9000 | DL20: 236 | DM20: 46028 | DN20: 9000 | DO20: 269 | DP20: 46062 | DR20: 303 | DS20: Mr. Mubeen | DT20: =9000*12 -> 108000 | DU20: =E20+H20+K20+N20+Q20+T20+W20+Z20+AC20+AF20+AI20+AL20 -> 108000 | DV20: =DT20-DU20 -> 0 | DW20: 0 | DX20: =DV20+DW20 -> 0 | DY20: =9000*12 -> 108000 | DZ20: =+AP20+AS20+AV20+AY20+BB20+BE20+BH20+BK20+BN20+BQ20+BT20+BW20 -> 108000 | EA20: =DX20+DY20-DZ20 -> 0 | EB20: =9000*12 -> 108000 | EC20: =CA20+CD20+CG20+CJ20+CM20+CP20+CS20+CV20+CY20+DB20+DE20+DH20 -> 108000 | ED20: =EA20+EB20-EC20 -> 0 | EG20: 303 | EH20: Mr. Mubeen | EI20: =9000*12 -> 108000 | EJ20: 0 | EK20: =9000*2 -> 18000 | EL20: =DK20+DN20 -> 18000 | EM20: =EJ20+EK20-EL20 -> 0
B21: Mr. Farhan | C21: 304 | D21: -74000 | K21: 22000 | L21: 1362 | M21: 45016 | Z21: 33000 | AA21: 1492 | AB21: 45158 | AP21: 33000 | AQ21: 1651 | AR21: 45305 | BQ21: 44000 | BR21: 1865 | BS21: 45573 | CP21: 55000 | CQ21: 068 | CR21: 45822 | CY21: 57500 | CZ21: 119 | DA21: 45905 | DB21: 5500 | DC21: 159 | DD21: 45937 | DE21: 5500 | DF21: 187 | DG21: 45967 | DH21: 5500 | DI21: 203 | DJ21: 45993 | DK21: 5500 | DL21: 234 | DM21: 46028 | DN21: 5500 | DO21: 261 | DP21: 46058 | DR21: 304 | DS21: Mr. Farhan | DT21: =5500*12 -> 66000 | DU21: =E21+H21+K21+N21+Q21+T21+W21+Z21+AC21+AF21+AI21+AL21 -> 55000 | DV21: =DT21-DU21 -> 11000 | DW21: 63000 | DX21: =DV21+DW21 -> 74000 | DY21: =5500*12 -> 66000 | DZ21: =+AP21+AS21+AV21+AY21+BB21+BE21+BH21+BK21+BN21+BQ21+BT21+BW21 -> 77000 | EA21: =DX21+DY21-DZ21 -> 63000 | EB21: =5500*12 -> 66000 | EC21: =CA21+CD21+CG21+CJ21+CM21+CP21+CS21+CV21+CY21+DB21+DE21+DH21 -> 129000 | ED21: =EA21+EB21-EC21 -> 0 | EG21: 304 | EH21: Mr. Farhan | EI21: =5500*12 -> 66000 | EJ21: 0 | EK21: =5500*2 -> 11000 | EL21: =DK21+DN21 -> 11000 | EM21: =EJ21+EK21-EL21 -> 0
B23: Dr. Nazim | C23: 401 | D23: 0 | E23: 7500 | F23: 1283 | G23: 44931 | H23: 7500 | I23: 1308 | J23: 44960 | K23: 7500 | L23: 1336 | M23: 44988 | N23: 7500 | O23: 1371 | P23: 45021 | Q23: 7500 | R23: 1394 | S23: 45047 | T23: 7500 | U23: 1431 | V23: 45080 | W23: 7500 | X23: 1453 | Y23: 45114 | Z23: 7500 | AA23: 1473 | AB23: 45140 | AC23: 7500 | AD23: 1504 | AE23: 45171 | AF23: 7500 | AG23: 1528 | AH23: 45201 | AI23: 7500 | AJ23: 1552 | AK23: 45232 | AL23: 7500 | AM23: 1571 | AN23: 45261 | AP23: 7500 | AQ23: 1594 | AR23: 45295 | AS23: 7500 | AT23: 1627 | AU23: 45325 | AV23: 7500 | AW23: 1723 | AX23: 45382 | AY23: 7500 | AZ23: 1677 | BA23: 45386 | BB23: 7500 | BC23: 1705 | BD23: 45414 | BE23: 7500 | BF23: 1733 | BG23: 45445 | BH23: 7500 | BI23: 1756 | BJ23: 45477 | BK23: 7500 | BL23: 1775 | BM23: 45505 | BN23: 7500 | BO23: 1802 | BP23: 45536 | BQ23: 7500 | BR23: 1837 | BS23: 45568 | BT23: 7500 | BU23: 1852 | BV23: 45597 | BW23: 7500 | BX23: 1882 | BY23: 45628 | CA23: 7500 | CB23: 1919 | CC23: 45662 | CD23: 7500 | CE23: 1938 | CF23: 45690 | CG23: 7500 | CH23: 1962 | CI23: 45718 | CJ23: 7500 | CK23: 1984 | CL23: 45749 | CM23: 7500 | CN23: 010 | CO23: 45786 | CP23: 7500 | CQ23: 030 | CR23: 45812 | CS23: 7500 | CT23: 054 | CU23: 45842 | CV23: =7500+16000 -> 23500 | CW23: 080/096 | CX23: 6,24 Aug | CY23: 9500 | CZ23: 130 | DA23: 45910 | DB23: 9500 | DC23: 154 | DD23: 45934 | DE23: 9500 | DF23: 183 | DG23: 45966 | DH23: 9500 | DI23: 207 | DJ23: 45998 | DK23: 9500 | DL23: 230 | DM23: 46026 | DN23: 9500 | DO23: 257 | DP23: 46058 | DR23: 401 | DS23: Dr. Nazim | DT23: =7500*12 -> 90000 | DU23: =E23+H23+K23+N23+Q23+T23+W23+Z23+AC23+AF23+AI23+AL23 -> 90000 | DV23: =DT23-DU23 -> 0 | DW23: 0 | DX23: =DV23+DW23 -> 0 | DY23: =7500*12 -> 90000 | DZ23: =+AP23+AS23+AV23+AY23+BB23+BE23+BH23+BK23+BN23+BQ23+BT23+BW23 -> 90000 | EA23: =DX23+DY23-DZ23 -> 0 | EB23: =9500*12 -> 114000 | EC23: =CA23+CD23+CG23+CJ23+CM23+CP23+CS23+CV23+CY23+DB23+DE23+DH23 -> 114000 | ED23: =EA23+EB23-EC23 -> 0 | EG23: 401 | EH23: Dr. Nazim | EI23: =9500*12 -> 114000 | EJ23: 0 | EK23: =9500*2 -> 19000 | EL23: =DK23+DN23 -> 19000 | EM23: =EJ23+EK23-EL23 -> 0
B24: Mr. Zai | C24: 402 | D24: -30000 | N24: 44000 | O24: 1392 | P24: 45043 | AY24: 56500 | AZ24: 1685 | BA24: 45387 | BW24: =27500+33000 -> 60500 | BX24: 1895/1896 | BY24: 45644 | CP24: 33000 | CQ24: 046 | CR24: 45837 | DK24: 33000 | DL24: 227 | DM24: 46023 | DR24: 402 | DS24: Mr. Zai | DT24: =55500+4500 -> 60000 | DU24: =E24+H24+K24+N24+Q24+T24+W24+Z24+AC24+AF24+AI24+AL24 -> 44000 | DV24: =DT24-DU24 -> 16000 | DW24: 18500 | DX24: =DV24+DW24+1500 -> 36000 | DY24: =4000*12 -> 48000 | DZ24: =+AP24+AS24+AV24+AY24+BB24+BE24+BH24+BK24+BN24+BQ24+BT24+BW24 -> 117000 | EA24: =DX24+DY24-DZ24 -> -33000 | EB24: =5500*12 -> 66000 | EC24: =CA24+CD24+CG24+CJ24+CM24+CP24+CS24+CV24+CY24+DB24+DE24+DH24 -> 33000 | ED24: =EA24+EB24-EC24 -> 0 | EG24: 402 | EH24: Mr. Junaid | EI24: =5500*12 -> 66000 | EJ24: 0 | EK24: =5500*2 -> 11000 | EL24: =DK24+DN24 -> 33000 | EM24: =EJ24+EK24-EL24 -> -22000
B25: Mr. Asif Siddiqui | C25: 403 | D25: -35000 | E25: 7000 | F25: 1295 | G25: 44941 | H25: 14000 | I25: 1320 | J25: 44967 | K25: 14000 | L25: 1342 | M25: 44989 | T25: 14000 | U25: 1428 | V25: 45081 | Z25: 14000 | AA25: 1480 | AB25: 45145 | AY25: 63000 | AZ25: 1722 | BA25: 45411 | CV25: 112000 | CW25: 103 | CX25: 45900 | DE25: 21000 | DF25: 186 | DG25: 45966 | DR25: 403 | DS25: Mr. Asif Siddiqui | DT25: =7000*12 -> 84000 | DU25: =E25+H25+K25+N25+Q25+T25+W25+Z25+AC25+AF25+AI25+AL25 -> 63000 | DV25: =DT25-DU25 -> 21000 | DW25: 14000 | DX25: =DV25+DW25 -> 35000 | DY25: =7000*12 -> 84000 | DZ25: =+AP25+AS25+AV25+AY25+BB25+BE25+BH25+BK25+BN25+BQ25+BT25+BW25 -> 63000 | EA25: =DX25+DY25-DZ25 -> 56000 | EB25: =7000*12 -> 84000 | EC25: =CA25+CD25+CG25+CJ25+CM25+CP25+CS25+CV25+CY25+DB25+DE25+DH25 -> 133000 | ED25: =EA25+EB25-EC25 -> 7000 | EG25: 403 | EH25: Mr. Asif Siddiqui | EI25: =7000*12 -> 84000 | EJ25: 7000 | EK25: =7000*2 -> 14000 | EL25: =DK25+DN25 -> 0 | EM25: =EJ25+EK25-EL25 -> 21000
B26: Mr. Khalid Ashraf Lari | C26: 404 | D26: -127500 | AP26: =7500*14 -> 105000 | AQ26: 1650 | AR26: 45311 | CV26: 172500 | CW26: 104 | CX26: 45900 | CY26: 7500 | CZ26: 117 | DA26: 45902 | DR26: 404 | DS26: Mr. Khalid Ashraf Lari | DT26: =7500*12 -> 90000 | DU26: =E26+H26+K26+N26+Q26+T26+W26+Z26+AC26+AF26+AI26+AL26 -> 0 | DV26: =DT26-DU26 -> 90000 | DW26: 37500 | DX26: =DV26+DW26 -> 127500 | DY26: =7500*12 -> 90000 | DZ26: =+AP26+AS26+AV26+AY26+BB26+BE26+BH26+BK26+BN26+BQ26+BT26+BW26 -> 105000 | EA26: =DX26+DY26-DZ26 -> 112500 | EB26: =7500*12 -> 90000 | EC26: =CA26+CD26+CG26+CJ26+CM26+CP26+CS26+CV26+CY26+DB26+DE26+DH26 -> 180000 | ED26: =EA26+EB26-EC26 -> 22500 | EG26: 404 | EH26: Mr. Khalid Ashraf Lari | EI26: =7500*12 -> 90000 | EJ26: 22500 | EK26: =7500*2 -> 15000 | EL26: =DK26+DN26 -> 0 | EM26: =EJ26+EK26-EL26 -> 37500
B28: Mr. Tanveer Iqbal | C28: 501 | D28: -18500 | N28: 16000 | O28: 1384 | P28: 45027 | Q28: 5500 | R28: 1414 | S28: 45057 | W28: 5500 | X28: 1464 | Y28: 45118 | AF28: 16500 | AG28: 1538 | AH28: 45214 | AI28: 6000 | AJ28: 1562 | AK28: 45246 | AP28: 16500 | AQ28: 1615 | AR28: 45306 | AS28: 6000 | AT28: 1794 | AU28: 45342 | BE28: 5500 | BF28: 1414 Adjust | BG28: 45473 | BH28: 33000 | BI28: 1795 | BJ28: 45502 | BK28: 12000 | BL28: 1793 | BM28: 45523 | CG28: 33000 | CH28: 1970 | CI28: 45719 | CV28: =20000+5500+5500+5500+5500 -> 42000 | CW28: 105 | CX28: 45900 | DB28: 16500 | DC28: 169 | DD28: 45956 | DE28: 20500 | DF28: 195 | DG28: 45983 | DR28: 501 | DS28: Mr. Tanveer Iqbal | DT28: =16000+44000+8000 -> 68000 | DU28: =E28+H28+K28+N28+Q28+T28+W28+Z28+AC28+AF28+AI28+AL28 -> 49500 | DV28: =DT28-DU28 -> 18500 | DW28: 0 | DX28: =DV28+DW28 -> 18500 | DY28: =7500*12 -> 90000 | DZ28: =+AP28+AS28+AV28+AY28+BB28+BE28+BH28+BK28+BN28+BQ28+BT28+BW28 -> 73000 | EA28: =DX28+DY28-DZ28 -> 35500 | EB28: =7500+7500+7500+7500+7500+7500+5500+5500+5500+7500+7500+7500 -> 84000 | EC28: =CA28+CD28+CG28+CJ28+CM28+CP28+CS28+CV28+CY28+DB28+DE28+DH28 -> 112000 | ED28: =EA28+EB28-EC28 -> 7500 | EG28: 501 | EH28: Mr. Saad | EI28: =7500*12 -> 90000 | EJ28: 7500 | EK28: =7500*2 -> 15000 | EL28: =DK28+DN28 -> 0 | EM28: =EJ28+EK28-EL28 -> 22500
B29: Mr. Naveed Ansari | C29: 502 | D29: 0 | H29: 11000 | I29: 1330 | J29: 44983 | K29: 5500 | L29: 1378 | M29: 45016 | Q29: 11000 | R29: 1419 | S29: 45066 | AC29: 22000 | AD29: 1542 | AE29: 45199 | AL29: =5500*3 -> 16500 | AM29: 1609 | AN29: 45291 | AV29: 16500 | AW29: 1698 | AX29: 45382 | AY29: 0 | BE29: =5500*3 -> 16500 | BF29: 1901 | BG29: 45473 | BW29: 33000 | BX29: 1903 | BY29: 45656 | CS29: 38500 | CT29: 070 | CU29: 45869 | CV29: 5500 | CW29: 108 | CX29: 45900 | CY29: 5500 | CZ29: 144 | DA29: 45930 | DR29: 502 | DS29: Mr. Naveed Ansari | DT29: =5500*12 -> 66000 | DU29: =E29+H29+K29+N29+Q29+T29+W29+Z29+AC29+AF29+AI29+AL29 -> 66000 | DV29: =DT29-DU29 -> 0 | DW29: 0 | DX29: =DV29+DW29 -> 0 | DY29: =5500*12 -> 66000 | DZ29: =+AP29+AS29+AV29+AY29+BB29+BE29+BH29+BK29+BN29+BQ29+BT29+BW29 -> 66000 | EA29: =DX29+DY29-DZ29 -> 0 | EB29: =5500*12 -> 66000 | EC29: =CA29+CD29+CG29+CJ29+CM29+CP29+CS29+CV29+CY29+DB29+DE29+DH29 -> 49500 | ED29: =EA29+EB29-EC29 -> 16500 | EG29: 502 | EH29: Mr. Naveed Ansari | EI29: =5500*12 -> 66000 | EJ29: 16500 | EK29: =5500*2 -> 11000 | EL29: =DK29+DN29 -> 0 | EM29: =EJ29+EK29-EL29 -> 27500
B30: Mr. Salman Khan | C30: 503 | D30: -28000 | H30: 14000 | I30: 1318 | J30: 44966 | M30: *- | Z30: 33000 | AA30: 1489 | AB30: 45149 | AP30: 28000 | AQ30: 1648 | AR30: 45309 | BQ30: 70000 | BR30: 1866 | BS30: 45573 | CV30: 70000 | CW30: 097 | CX30: 45893 | DB30: 14000 | DC30: 152 | DD30: 45932 | DH30: 14000 | DI30: 221 | DJ30: 46021 | DR30: 503 | DS30: Mr. Salman Khan | DT30: =63000+12000 -> 75000 | DU30: =E30+H30+K30+N30+Q30+T30+W30+Z30+AC30+AF30+AI30+AL30 -> 47000 | DV30: =DT30-DU30 -> 28000 | DW30: 0 | DX30: =DV30+DW30 -> 28000 | DY30: =7000*12 -> 84000 | DZ30: =+AP30+AS30+AV30+AY30+BB30+BE30+BH30+BK30+BN30+BQ30+BT30+BW30 -> 98000 | EA30: =DX30+DY30-DZ30 -> 14000 | EB30: =7000*12 -> 84000 | EC30: =CA30+CD30+CG30+CJ30+CM30+CP30+CS30+CV30+CY30+DB30+DE30+DH30 -> 98000 | ED30: =EA30+EB30-EC30 -> 0 | EG30: 503 | EH30: Mr. Salman Khan | EI30: =7000*12 -> 84000 | EJ30: 0 | EK30: =7000*2 -> 14000 | EL30: =DK30+DN30 -> 0 | EM30: =EJ30+EK30-EL30 -> 14000
B31: Mr. Nafis | C31: 504 | D31: =-5500-5500-5500-5500+22000 -> 0 | E31: 7500 | F31: 1296 | G31: 44942 | H31: 7500 | I31: 1316 | J31: 44965 | K31: 7500 | L31: 1350 | M31: 44992 | N31: 7500 | O31: 1387 | P31: 45028 | Q31: 7500 | R31: 1404 | S31: 45056 | AC31: 22000 | AD31: 1541 | AE31: 45199 | AL31: 16500 | AM31: 1612 | AN31: 45291 | AY31: 22000 | AZ31: 1797 | BA31: 45411 | BH31: 11000 | BI31: 1767 | BJ31: 45483 | BK31: 5500 | BL31: 1784 | BM31: 45511 | BN31: 5500 | BO31: 1814 | BP31: 45541 | BQ31: 5500 | BR31: 1845 | BS31: 45573 | BT31: 11000 | BU31: 1869 | BV31: 45607 | BW31: 5500 | BX31: 1885 | BY31: 45631 | CA31: 5500 | CB31: 1918 | CC31: 45660 | CD31: 5500 | CE31: 1952 | CF31: 45708 | CG31: 5500 | CH31: 1972 | CI31: 45723 | CJ31: 5500 | CK31: 1988 | CL31: 45756 | CM31: 5500 | CN31: 013 | CO31: 45788 | CP31: 5500 | CQ31: 041 | CR31: 45820 | CS31: 5500 | CT31: 056 | CU31: 45846 | CV31: 5500 | CW31: 081 | CX31: 45876 | CY31: 5500 | CZ31: 133 | DA31: 45914 | DB31: 5500 | DC31: 151 | DD31: 45932 | DE31: 5500 | DF31: 177 | DG31: 45964 | DH31: 5500 | DI31: 214 | DJ31: 45995 | DK31: 5500 | DL31: 228 | DM31: 46027 | DN31: 5500 | DO31: 259 | DP31: 46058 | DR31: 504 | DS31: Mr. Nafis | DT31: =37500+38500 -> 76000 | DU31: =E31+H31+K31+N31+Q31+T31+W31+Z31+AC31+AF31+AI31+AL31 -> 76000 | DV31: =DT31-DU31 -> 0 | DW31: 0 | DX31: =DV31+DW31 -> 0 | DY31: =5500*12 -> 66000 | DZ31: =+AP31+AS31+AV31+AY31+BB31+BE31+BH31+BK31+BN31+BQ31+BT31+BW31 -> 66000 | EA31: =DX31+DY31-DZ31 -> 0 | EB31: =5500*12 -> 66000 | EC31: =CA31+CD31+CG31+CJ31+CM31+CP31+CS31+CV31+CY31+DB31+DE31+DH31 -> 66000 | ED31: =EA31+EB31-EC31 -> 0 | EG31: 504 | EH31: Mr. Nafis | EI31: =5500*12 -> 66000 | EJ31: 0 | EK31: =5500*2 -> 11000 | EL31: =DK31+DN31 -> 11000 | EM31: =EJ31+EK31-EL31 -> 0
B33: Mr. Sohail | C33: 601 | D33: -5500 | E33: 5500 | F33: 1299 | G33: 44944 | H33: 5500 | I33: 1319 | J33: 44967 | K33: 5500 | L33: 1354 | M33: 44996 | N33: 5500 | O33: 1382 | P33: 45027 | Q33: 5500 | R33: 1411 | S33: 45057 | T33: 5500 | U33: 1442 | V33: 45087 | W33: 5500 | X33: 1463 | Y33: 45111 | Z33: 5500 | AA33: 1485 | AB33: 45149 | AC33: 5500 | AD33: 1519 | AE33: 45182 | AF33: 5500 | AG33: 1539 | AH33: 45215 | AI33: 5500 | AJ33: 1566 | AK33: 45248 | AL33: 5500 | AM33: 1583 | AN33: 45276 | AP33: 5500 | AQ33: 1608 | AR33: 45306 | AS33: 5500 | AT33: 1637 | AU33: 45335 | AV33: 5500 | AW33: 1669 | AX33: 45365 | AY33: 5500 | AZ33: 1694 | BA33: 45405 | BB33: 5500 | BC33: 1727 | BD33: 45441 | BE33: 5500 | BF33: 1750 | BG33: 45468 | BH33: 5500 | BI33: 1770 | BJ33: 45494 | BK33: 5500 | BL33: 1796 | BM33: 45524 | BN33: 5500 | BO33: 1823 | BP33: 45555 | BQ33: 5500 | BR33: 1851 | BS33: 45586 | BT33: 5500 | BU33: 1877 | BV33: 45614 | BW33: 5500 | BX33: 1898 | BY33: 45651 | CA33: 5500 | CB33: 1934 | CC33: 45686 | CD33: 5500 | CE33: 1954 | CF33: 45713 | CG33: 5500 | CH33: 1977 | CI33: 45730 | CJ33: 5500 | CK33: 1997 | CL33: 45769 | CM33: 5500 | CN33: 026 | CO33: 45803 | CP33: 5500 | CQ33: 047 | CR33: 45835 | CS33: 5500 | CT33: 065 | CU33: 45865 | CV33: =5500+5500 -> 11000 | CW33: Adj/099 | CY33: 5500 | CZ33: 136 | DA33: 45919 | DB33: 5500 | DC33: 166 | DD33: 45948 | DE33: 5500 | DF33: 197 | DG33: 45986 | DH33: 5500 | DI33: 225 | DJ33: 46015 | DK33: 5500 | DL33: 258 | DM33: 46048 | DR33: 601 | DS33: Mr. Sohail | DT33: =5500*12 -> 66000 | DU33: =E33+H33+K33+N33+Q33+T33+W33+Z33+AC33+AF33+AI33+AL33 -> 66000 | DV33: =DT33-DU33 -> 0 | DW33: 5500 | DX33: =DV33+DW33 -> 5500 | DY33: =5500*12 -> 66000 | DZ33: =+AP33+AS33+AV33+AY33+BB33+BE33+BH33+BK33+BN33+BQ33+BT33+BW33 -> 66000 | EA33: =DX33+DY33-DZ33 -> 5500 | EB33: =5500*12 -> 66000 | EC33: =CA33+CD33+CG33+CJ33+CM33+CP33+CS33+CV33+CY33+DB33+DE33+DH33 -> 71500 | ED33: =EA33+EB33-EC33 -> 0 | EG33: 601 | EH33: Mr. Sohail | EI33: =5500*12 -> 66000 | EJ33: 0 | EK33: =5500*2 -> 11000 | EL33: =DK33+DN33 -> 5500 | EM33: =EJ33+EK33-EL33 -> 5500
B34: Mr. Nasir | C34: 602 | D34: 0 | E34: 5500 | F34: 1288 | G34: 44937 | H34: 5500 | I34: 1321 | J34: 44967 | K34: 5500 | L34: 1353 | M34: 44995 | N34: 5500 | O34: 1383 | P34: 45027 | Q34: 5500 | R34: 1406 | S34: 45056 | T34: 5500 | U34: 1436 | V34: 45087 | W34: 5500 | X34: 1461 | Y34: 45118 | Z34: 5500 | AA34: 1484 | AB34: 45148 | AC34: 5500 | AD34: 1510 | AE34: 45175 | AF34: 5500 | AG34: 1536 | AH34: 45209 | AI34: 5500 | AJ34: 1560 | AK34: 45241 | AL34: 5500 | AM34: 1578 | AN34: 45270 | AP34: 5500 | AQ34: 1616 | AR34: 45307 | AS34: 5500 | AT34: 1633 | AU34: 45334 | AV34: 5500 | AW34: 1666 | AX34: 45364 | AY34: 5500 | AZ34: 1679 | BA34: 45386 | BB34: 5500 | BC34: 1718 | BD34: 45426 | BE34: 5500 | BF34: 1748 | BG34: 45457 | BH34: 5500 | BI34: 1772 | BJ34: 45495 | BK34: 5500 | BL34: 1792 | BM34: 45520 | BN34: 5500 | BO34: 1822 | BP34: 45555 | BQ34: 5500 | BR34: 1844 | BS34: 45573 | BT34: 5500 | BU34: 1876 | BV34: 45611 | BW34: 5500 | BX34: 1890 | BY34: 45638 | CA34: 5500 | CB34: 1931 | CC34: 45673 | CD34: 5500 | CE34: 1948 | CF34: 45700 | CG34: 5500 | CH34: 1978 | CI34: 45722 | CJ34: 5500 | CK34: 022 | CL34: 45752 | CM34: 5500 | CN34: 017 | CO34: 45789 | CP34: 5500 | CQ34: 044 | CR34: 45821 | CS34: 5500 | CT34: 060 | CU34: 45852 | CV34: 5500 | CW34: 089 | CX34: 45885 | CY34: 5500 | CZ34: 135 | DA34: 45914 | DB34: 5500 | DC34: 164 | DD34: 45941 | DE34: 5500 | DF34: 192 | DG34: 45977 | DH34: 5500 | DI34: 215 | DJ34: 46000 | DK34: 5500 | DL34: 243 | DM34: 46037 | DN34: 5500 | DO34: 273 | DP34: 46060 | DR34: 602 | DS34: Mr. Nasir | DT34: =5500*12 -> 66000 | DU34: =E34+H34+K34+N34+Q34+T34+W34+Z34+AC34+AF34+AI34+AL34 -> 66000 | DV34: =DT34-DU34 -> 0 | DW34: 0 | DX34: =DV34+DW34 -> 0 | DY34: =5500*12 -> 66000 | DZ34: =+AP34+AS34+AV34+AY34+BB34+BE34+BH34+BK34+BN34+BQ34+BT34+BW34 -> 66000 | EA34: =DX34+DY34-DZ34 -> 0 | EB34: =5500*12 -> 66000 | EC34: =CA34+CD34+CG34+CJ34+CM34+CP34+CS34+CV34+CY34+DB34+DE34+DH34 -> 66000 | ED34: =EA34+EB34-EC34 -> 0 | EG34: 602 | EH34: Mr. Nasir | EI34: =5500*12 -> 66000 | EJ34: 0 | EK34: =5500*2 -> 11000 | EL34: =DK34+DN34 -> 11000 | EM34: =EJ34+EK34-EL34 -> 0
B35: Mr. Shahid | C35: 603 | D35: =9000+8000+8000+8000-33000 -> 0 | K35: 33000 | L35: 1361 | M35: 45012 | Q35: 16000 | R35: 1416 | S35: 45061 | T35: 8000 | U35: 1443 | V35: 45091 | W35: 8000 | X35: 1467 | Y35: 45128 | Z35: 8000 | AA35: 1494 | AB35: 45158 | AC35: 8000 | AD35: 1523 | AE35: 45189 | AF35: 8000 | AG35: 1548 | AH35: 45230 | AL35: 16000 | AM35: 1581 | AN35: 45275 | AS35: 16000 | AT35: 1640 | AU35: 45343 | BB35: 24000 | BC35: 1719 | BD35: 45431 | BN35: 16000 | BO35: 1819 | BP35: 45549 | CG35: 40000 | CH35: 045 | CI35: 45747 | CV35: =9000*8 -> 72000 | CW35: 101 | CX35: 45899 | CY35: 9000 | CZ35: 139 | DA35: 45930 | DN35: 18000 | DO35: 267 | DP35: 46061 | DR35: 603 | DS35: Mr. Shahid | DT35: =8000*12 -> 96000 | DU35: =E35+H35+K35+N35+Q35+T35+W35+Z35+AC35+AF35+AI35+AL35 -> 105000 | DV35: =DT35-DU35 -> -9000 | DW35: 9000 | DX35: =DV35+DW35 -> 0 | DY35: =8000*12 -> 96000 | DZ35: =+AP35+AS35+AV35+AY35+BB35+BE35+BH35+BK35+BN35+BQ35+BT35+BW35 -> 56000 | EA35: =DX35+DY35-DZ35 -> 40000 | EB35: =9000*12 -> 108000 | EC35: =CA35+CD35+CG35+CJ35+CM35+CP35+CS35+CV35+CY35+DB35+DE35+DH35 -> 121000 | ED35: =EA35+EB35-EC35 -> 27000 | EG35: 603 | EH35: Mr. Shahid | EI35: =9000*12 -> 108000 | EJ35: 27000 | EK35: =9000*2 -> 18000 | EL35: =DK35+DN35 -> 18000 | EM35: =EJ35+EK35-EL35 -> 27000
B36: Mr. Ashfaque Sb | C36: 604 | D36: =-44000-5500-5500+49500-5500+5500-5500+11000-5500-5500-5500-5500+22000 -> 0 | H36: 49500 | I36: 1315 | J36: 44964 | K36: 5500 | L36: 1348 | M36: 44990 | N36: 11000 | O36: 1374 | P36: 45022 | Z36: 22000 | AA36: 1501 | AB36: 45165 | AC36: 5500 | AD36: 1524 | AE36: 45191 | AL36: 16500 | AM36: 1584 | AN36: 45281 | AP36: 5500 | AQ36: 1622 | AR36: 45318 | AS36: 5500 | AT36: 1645 | AU36: 45351 | AV36: 5500 | AW36: 1673 | AX36: 45380 | AY36: 5500 | AZ36: 1702 | BA36: 45412 | BB36: 5500 | BC36: 1726 | BD36: 45442 | BE36: 5500 | BF36: 1752 | BG36: 45473 | BH36: 5500 | BI36: 1771 | BJ36: 45503 | BN36: 11000 | BO36: 1830 | BP36: 45564 | BQ36: 5500 | BR36: 1857 | BS36: 45596 | BT36: 5500 | BU36: 1878 | BV36: 45624 | BW36: 5500 | BX36: 1911 | BY36: 45657 | CA36: 5500 | CB36: 1940 | CC36: 45688 | CG36: 11000 | CH36: 1981 | CI36: 45744 | CJ36: 5500 | CK36: 007 | CL36: 45775 | CM36: 5500 | CN36: 029 | CO36: 45808 | CP36: 5500 | CQ36: 050 | CR36: 45838 | CS36: 5500 | CT36: 076 | CU36: 45869 | CV36: 5500 | CW36: 091 | CX36: 45886 | CY36: 5500 | CZ36: 141 | DA36: 45928 | DB36: 5500 | DC36: 172 | DD36: 45961 | DE36: 5500 | DF36: 198 | DG36: 45991 | DH36: 5500 | DI36: 218 | DJ36: 46016 | DK36: 5500 | DL36: 260 | DM36: 46051 | DR36: 604 | DS36: Mr. Ashfaque Sb | DT36: =5500*12 -> 66000 | DU36: =E36+H36+K36+N36+Q36+T36+W36+Z36+AC36+AF36+AI36+AL36 -> 110000 | DV36: =DT36-DU36 -> -44000 | DW36: 44000 | DX36: =DV36+DW36 -> 0 | DY36: =5500*12 -> 66000 | DZ36: =+AP36+AS36+AV36+AY36+BB36+BE36+BH36+BK36+BN36+BQ36+BT36+BW36 -> 66000 | EA36: =DX36+DY36-DZ36 -> 0 | EB36: =5500*12 -> 66000 | EC36: =CA36+CD36+CG36+CJ36+CM36+CP36+CS36+CV36+CY36+DB36+DE36+DH36 -> 66000 | ED36: =EA36+EB36-EC36 -> 0 | EG36: 604 | EH36: Mr. Ashfaque Sb | EI36: =5500*12 -> 66000 | EJ36: 0 | EK36: =5500*2 -> 11000 | EL36: =DK36+DN36 -> 5500 | EM36: =EJ36+EK36-EL36 -> 5500
B38: Mr. Anis | C38: 701 | H38: 7500 | I38: 1325 | J38: 44970 | K38: 7500 | L38: 1349 | M38: 44992 | N38: 7500 | O38: 1373 | P38: 45022 | Q38: 7500 | R38: 1407 | S38: 45056 | T38: 7500 | U38: 1434 | V38: 45085 | W38: 7500 | X38: 1460 | Y38: 45118 | Z38: 7500 | AA38: 1481 | AB38: 45146 | AC38: 7500 | AD38: 1514 | AE38: 45180 | AF38: 7500 | AG38: 1537 | AH38: 45209 | AI38: 7500 | AJ38: 1559 | AK38: 45241 | AL38: 7500 | AM38: 1580 | AN38: 45272 | AP38: 7500 | AQ38: 1601 | AR38: 45301 | AS38: 7500 | AT38: 1632 | AU38: 45333 | AV38: 7500 | AW38: 1667 | AX38: 45364 | AY38: 7500 | AZ38: 1690 | BA38: 45394 | BB38: 7500 | BC38: 1717 | BD38: 45426 | BE38: 7500 | BF38: 1749 | BG38: 45460 | BH38: 7500 | BI38: 1769 | BJ38: 45486 | BK38: 7500 | BL38: 1791 | BM38: 45519 | BN38: 7500 | BO38: 1821 | BP38: 45554 | BT38: 15000 | BU38: 1870 | BV38: 45607 | BW38: 7500 | BX38: 1897 | BY38: 45653 | CA38: 7500 | CB38: 1933 | CC38: 45683 | CD38: 5500 | CE38: 1953 | CF38: 45711 | CG38: 5500 | CH38: 1993 | CI38: 45744 | CJ38: 5500 | CK38: 1994 | CL38: 45762 | CM38: 7500 | CN38: 024 | CO38: 45795 | CP38: 5500 | CQ38: 036 | CR38: 45818 | CV38: 11000 | CW38: 085 | CX38: 45884 | DB38: 15000 | DC38: 150 | DD38: 45932 | DE38: 5500 | DF38: 194 | DG38: 45980 | DH38: 5501 | DI38: 209 | DJ38: 46000 | DK38: 5500 | DL38: 244 | DM38: 46033 | DR38: 701 | DS38: Mr. Anis | DT38: =7500*12 -> 90000 | DU38: =E38+H38+K38+N38+Q38+T38+W38+Z38+AC38+AF38+AI38+AL38 -> 82500 | DV38: =DT38-DU38 -> 7500 | DW38: -7500 | DX38: =DV38+DW38 -> 0 | DY38: =7500*12 -> 90000 | DZ38: =+AP38+AS38+AV38+AY38+BB38+BE38+BH38+BK38+BN38+BQ38+BT38+BW38 -> 90000 | EA38: =DX38+DY38-DZ38 -> 0 | EB38: =7500+5500+5500+5500+7500+5500+5500+5500+7500+7500+5501+5500 -> 74001 | EC38: =CA38+CD38+CG38+CJ38+CM38+CP38+CS38+CV38+CY38+DB38+DE38+DH38 -> 74001 | ED38: =EA38+EB38-EC38 -> 0 | EG38: 701 | EH38: Mr. Anis | EI38: =5500*12 -> 66000 | EJ38: 0 | EK38: =5500*2 -> 11000 | EL38: =DK38+DN38 -> 5500 | EM38: =EJ38+EK38-EL38 -> 5500
B39: Mrs. Younus | C39: 702 | D39: =+#REF! -> #REF! | E39: 5500 | F39: 1291 | G39: 44938 | H39: 5500 | I39: 1324 | J39: 44970 | K39: 5500 | L39: 1356 | M39: 44997 | N39: 5500 | O39: 1385 | P39: 45027 | Q39: 5500 | R39: 1413 | S39: 45057 | T39: 5500 | U39: 1441 | V39: 45090 | W39: 5500 | X39: 1457 | Y39: 45117 | Z39: 5500 | AA39: 1482 | AB39: 45147 | AC39: 5500 | AD39: 1517 | AE39: 45181 | AL39: =4000+4000+5500 -> 13500 | AM39: 1585 | AN39: 45281 | AP39: 5500 | AQ39: 1600 | AR39: 45302 | AS39: 5500 | AT39: 1631 | AU39: 45332 | AV39: 5500 | AW39: 1659 | AX39: 45362 | AY39: 5500 | AZ39: 1689 | BA39: 45386 | BB39: 5500 | BC39: 1714 | BD39: 45424 | BE39: 5500 | BF39: 1742 | BG39: 45453 | BH39: 5500 | BI39: 1764 | BJ39: 45484 | BK39: 5500 | BL39: 1788 | BM39: 45515 | BN39: 5500 | BO39: 1820 | BP39: 45550 | BQ39: 5500 | BR39: 1847 | BS39: 45576 | BT39: 5500 | BU39: 1871 | BV39: 45608 | BW39: 5500 | BX39: 1892 | BY39: 45640 | CA39: 5500 | CB39: 1927 | CC39: 45669 | CD39: 5500 | CE39: 1949 | CF39: 45701 | CG39: 5500 | CH39: 1969 | CI39: 45723 | CJ39: 5500 | CK39: 1998 | CL39: 45770 | CM39: 5500 | CN39: 014 | CO39: 45788 | CP39: 5500 | CQ39: 037 | CR39: 45818 | CS39: 5500 | CT39: 058 | CU39: 45852 | CV39: 5500 | CW39: 083 | CX39: 45879 | CY39: 5500 | CZ39: 131 | DA39: 45913 | DN39: 21500 | DO39: 268 | DP39: 46061 | DR39: 702 | DS39: Mrs. Younus | DT39: =55000+8000 -> 63000 | DU39: =E39+H39+K39+N39+Q39+T39+W39+Z39+AC39+AF39+AI39+AL39 -> 63000 | DV39: =DT39-DU39 -> 0 | DW39: 0 | DX39: =DV39+DW39 -> 0 | DY39: =5500*12 -> 66000 | DZ39: =+AP39+AS39+AV39+AY39+BB39+BE39+BH39+BK39+BN39+BQ39+BT39+BW39 -> 66000 | EA39: =DX39+DY39-DZ39 -> 0 | EB39: =5500+5500+5500+5500+5500+5500+5500+5500+5500+4000+4000+4000 -> 61500 | EC39: =CA39+CD39+CG39+CJ39+CM39+CP39+CS39+CV39+CY39+DB39+DE39+DH39 -> 49500 | ED39: =EA39+EB39-EC39 -> 12000 | EG39: 702 | EH39: Mrs. Younus | EI39: =5500*12 -> 66000 | EJ39: 12000 | EK39: =4000+5500 -> 9500 | EL39: =DK39+DN39 -> 21500 | EM39: =EJ39+EK39-EL39 -> 0
B40: Mr. Yousuf | C40: 703 | D40: -9000 | E40: 9000 | F40: 1293 | G40: 44940 | H40: 9000 | I40: 1322 | J40: 44969 | K40: 9000 | L40: 1357 | M40: 44997 | Q40: 9000 | R40: 1403 | S40: 45055 | T40: 9000 | U40: 1437 | V40: 45088 | W40: 9000 | X40: 1465 | Y40: 45111 | Z40: 9000 | AA40: 1477 | AB40: 45144 | AC40: 9000 | AD40: 1513 | AE40: 45180 | AF40: 9000 | AG40: 1547 | AH40: 45217 | AI40: 9000 | AJ40: 1565 | AK40: 45247 | AL40: 9000 | AM40: 1588 | AN40: 45287 | AP40: 9000 | AQ40: 1618 | AR40: 45310 | AS40: 9000 | AT40: 1643 | AU40: 45350 | AV40: 9000 | AW40: 1670 | AX40: 45367 | AY40: 9000 | AZ40: 1703 | BA40: 45412 | BB40: 9000 | BC40: 1720 | BD40: 45437 | BE40: 9000 | BF40: 1737 | BG40: 45448 | BH40: 9000 | BI40: 1762 | BJ40: 45482 | BK40: 9000 | BL40: 1786 | BM40: 45514 | BN40: 9000 | BO40: 1811 | BP40: 45540 | BQ40: 9000 | BR40: 1848 | BS40: 45578 | BT40: 9000 | BU40: 1860 | BV40: 45601 | BW40: 9000 | BX40: 1888 | BY40: 45635 | CA40: 9000 | CB40: 1925 | CC40: 45667 | CD40: 9000 | CE40: 1941 | CF40: 45691 | CG40: 9000 | CH40: 1967 | CI40: 45722 | CJ40: 9000 | CK40: 1996 | CL40: 45767 | CM40: 11000 | CN40: 025 | CO40: 45795 | CP40: 11000 | CQ40: 042 | CR40: 45820 | CS40: 11000 | CT40: 063 | CU40: 45858 | CV40: =11000+9000 -> 20000 | CW40: 077/Adj | CX40: 45874 | CY40: 11000 | CZ40: 124 | DA40: 45907 | DB40: 11000 | DC40: 160 | DD40: 45937 | DE40: 11000 | DF40: 178 | DG40: 45964 | DH40: 11000 | DI40: 216 | DJ40: 46009 | DK40: 11000 | DL40: 247 | DM40: 46035 | DN40: 11000 | DO40: 271 | DP40: 46065 | DR40: 703 | DS40: Mr. Yousuf | DT40: =9000*12 -> 108000 | DU40: =E40+H40+K40+N40+Q40+T40+W40+Z40+AC40+AF40+AI40+AL40 -> 99000 | DV40: =DT40-DU40 -> 9000 | DW40: 0 | DX40: =DV40+DW40 -> 9000 | DY40: =9000*12 -> 108000 | DZ40: =+AP40+AS40+AV40+AY40+BB40+BE40+BH40+BK40+BN40+BQ40+BT40+BW40 -> 108000 | EA40: =DX40+DY40-DZ40 -> 9000 | EB40: =9000+9000+9000+9000+11000+11000+11000+11000+11000+11000+11000+11000 -> 124000 | EC40: =CA40+CD40+CG40+CJ40+CM40+CP40+CS40+CV40+CY40+DB40+DE40+DH40 -> 133000 | ED40: =EA40+EB40-EC40 -> 0 | EG40: 703 | EH40: Mr. Yousuf | EI40: =11000*12 -> 132000 | EJ40: 0 | EK40: =11000*2 -> 22000 | EL40: =DK40+DN40 -> 22000 | EM40: =EJ40+EK40-EL40 -> 0
B41: Mr. Annus Raza | C41: 704 | D41: 7500 | E41: =7500+15000 -> 22500 | F41: 1278/1281 | G41: 3, 4 Jan 2023 | K41: 30000 | L41: 1364 | M41: 45016 | AF41: 30000 | AG41: 1546 | AH41: 45221 | AL41: 30000 | AM41: 1613 | AN41: 45282 | AY41: 22500 | AZ41: 1798 | BA41: 45350 | BN41: 30000 | BO41: 1867 | BP41: 45563 | BW41: 30000 | BX41: 1909 | BY41: 45656 | CV41: 60000 | CW41: 098 | CX41: 45893 | CY41: 7500 | CZ41: 127 | DA41: 45907 | DE41: 7500 | DF41: 188 | DG41: 45967 | DK41: =7500+5500 -> 13000 | DL41: 248/242 | DM41: 12/13 Jan | DN41: 5500 | DO41: 275 | DP41: 46069 | DR41: 704 | DS41: Mr. Annus Raza | DT41: =7500*12 -> 90000 | DU41: =E41+H41+K41+N41+Q41+T41+W41+Z41+AC41+AF41+AI41+AL41 -> 112500 | DV41: =DT41-DU41 -> -22500 | DW41: 15000 | DX41: =DV41+DW41 -> -7500 | DY41: =7500*12 -> 90000 | DZ41: =+AP41+AS41+AV41+AY41+BB41+BE41+BH41+BK41+BN41+BQ41+BT41+BW41 -> 82500 | EA41: =DX41+DY41-DZ41 -> 0 | EB41: =7500*12 -> 90000 | EC41: =CA41+CD41+CG41+CJ41+CM41+CP41+CS41+CV41+CY41+DB41+DE41+DH41 -> 75000 | ED41: =EA41+EB41-EC41 -> 15000 | EG41: 704 | EH41: Mr. Taj | EI41: =5500*12 -> 66000 | EJ41: 15000 | EK41: =5500*2 -> 11000 | EL41: =DK41+DN41 -> 18500 | EM41: =EJ41+EK41-EL41 -> 7500
B43: Mr. Malik | C43: 801 | D43: 0 | K43: 22500 | L43: 1363 | M43: 45016 | Z43: 37500 | AA43: 1493 | AB43: 45158 | AL43: 30000 | AM43: 1614 | AN43: 45291 | BE43: =7500*6 -> 45000 | BF43: 1800 | BG43: 45473 | BW43: =7500*6 -> 45000 | BX43: 1900 | BY43: 45656 | CS43: 66500 | CT43: 071 | CU43: 45869 | CV43: 4000 | CW43: 110 | CX43: 45900 | DB43: 16000 | DC43: 145 | DD43: 45934 | DN43: 11000 | DO43: 274 | DP43: 46068 | DR43: 801 | DS43: Mr. Malik | DT43: =7500*12 -> 90000 | DU43: =E43+H43+K43+N43+Q43+T43+W43+Z43+AC43+AF43+AI43+AL43 -> 90000 | DV43: =DT43-DU43 -> 0 | DW43: 0 | DX43: =DV43+DW43 -> 0 | DY43: =7500*12 -> 90000 | DZ43: =+AP43+AS43+AV43+AY43+BB43+BE43+BH43+BK43+BN43+BQ43+BT43+BW43 -> 90000 | EA43: =DX43+DY43-DZ43 -> 0 | EB43: =9500+9500+9500+9500+9500+9500+9500+4000+4000+4000+4000+4000 -> 86500 | EC43: =CA43+CD43+CG43+CJ43+CM43+CP43+CS43+CV43+CY43+DB43+DE43+DH43 -> 86500 | ED43: =EA43+EB43-EC43 -> 0 | EG43: 801 | EH43: Mr. Kashif Patel | EI43: =5500*12 -> 66000 | EJ43: 0 | EK43: =5500*2 -> 11000 | EL43: =DK43+DN43 -> 11000 | EM43: =EJ43+EK43-EL43 -> 0
B44: Mr. Munaf | C44: 802 | D44: -27500 | E44: 5500 | F44: 1300 | G44: 44953 | K44: 5500 | L44: 1335 | M44: 44987 | Q44: 5500 | R44: 1412 | S44: 45057 | T44: 11000 | U44: 1500 | V44: 45081 | W44: 5500 | X44: 1470 | Y44: 45131 | Z44: 5500 | AA44: 1478 | AB44: 45144 | AP44: 27500 | AQ44: 1617 | AR44: 45308 | AS44: 5500 | AT44: 1625 | AU44: 45324 | AY44: 11000 | AZ44: 1676 | BA44: 45384 | BB44: 5500 | BC44: 1710 | BD44: 45419 | BE44: 5500 | BF44: 1739 | BG44: 45448 | BH44: 5500 | BI44: 1759 | BJ44: 45479 | BK44: 5500 | BL44: 1781 | BM44: 45510 | BN44: 5500 | BO44: 1812 | BP44: 45540 | BQ44: 5500 | BR44: 1833 | BS44: 45566 | BT44: 5500 | BU44: 1856 | BV44: 45597 | BW44: 5500 | BX44: 1879 | BY44: 45627 | CA44: 5500 | CB44: 1913 | CC44: 45659 | CD44: 5500 | CE44: 1936 | CF44: 45689 | CG44: 5500 | CH44: 1964 | CI44: 45719 | CJ44: 5500 | CK44: 1986 | CL44: 45751 | CM44: 5500 | CN44: 005 | CO44: 45781 | CP44: 5500 | CQ44: 027 | CR44: 45809 | CS44: 5500 | CT44: 055 | CU44: 45845 | CV44: 5500 | CW44: 067 | CX44: 45870 | CY44: 5500 | CZ44: 122 | DA44: 45906 | DB44: 5500 | DC44: 157 | DD44: 45937 | DE44: 5500 | DF44: 190 | DG44: 45974 | DH44: 5500 | DI44: 208 | DJ44: 46001 | DK44: 7500 | DL44: 232 | DM44: 46026 | DN44: 7500 | DO44: 270 | DP44: 46065 | DR44: 802 | DS44: Mr. Munaf | DT44: =5500*12-5500 -> 60500 | DU44: =E44+H44+K44+N44+Q44+T44+W44+Z44+AC44+AF44+AI44+AL44 -> 38500 | DV44: =DT44-DU44 -> 22000 | DW44: 0 | DX44: =DV44+DW44 -> 22000 | DY44: =5500*12 -> 66000 | DZ44: =+AP44+AS44+AV44+AY44+BB44+BE44+BH44+BK44+BN44+BQ44+BT44+BW44 -> 88000 | EA44: =DX44+DY44-DZ44 -> 0 | EB44: =5500*12 -> 66000 | EC44: =CA44+CD44+CG44+CJ44+CM44+CP44+CS44+CV44+CY44+DB44+DE44+DH44 -> 66000 | ED44: =EA44+EB44-EC44 -> 0 | EG44: 802 | EH44: Mr. Munaf | EI44: =7500*12 -> 90000 | EJ44: 0 | EK44: =7500*2 -> 15000 | EL44: =DK44+DN44 -> 15000 | EM44: =EJ44+EK44-EL44 -> 0
B45: Mr. Shamim | C45: 803 | D45: =118000-100000-18000 -> 0 | E45: 7000 | F45: 1286 | G45: 44934 | H45: 7000 | I45: 1304 | J45: 44958 | K45: 7000 | L45: 1355 | M45: 44996 | N45: 7000 | O45: 1390 | P45: 45034 | Q45: 7000 | R45: 1408 | S45: 45056 | T45: 7000 | U45: 1439 | V45: 45088 | W45: 7000 | X45: 1466 | Y45: 45124 | Z45: 7000 | AA45: 1487 | AB45: 45149 | AC45: 7000 | AD45: 1512 | AE45: 45175 | AF45: 7000 | AG45: 1527 | AH45: 45201 | AI45: 7000 | AJ45: 1556 | AK45: 45239 | AL45: 7000 | AM45: 1575 | AN45: 45263 | AP45: 7000 | AQ45: 1598 | AR45: 45300 | AS45: 7000 | AT45: 1630 | AU45: 45330 | AV45: 7000 | AW45: 1663 | AX45: 45362 | BB45: 7000 | BC45: 1721 | BD45: 45436 | BE45: 14000 | BF45: 1743 | BG45: 45454 | BH45: 7000 | BI45: 1765 | BJ45: 45484 | BK45: 7000 | BL45: 1787 | BM45: 45515 | BN45: 7000 | BO45: 1817 | BP45: 45546 | BQ45: 7000 | BR45: 1838 | BS45: 45569 | BT45: 7000 | BU45: 1862 | BV45: 45605 | BW45: 7000 | BX45: 1883 | BY45: 45631 | CA45: 7000 | CB45: 1923 | CC45: 45666 | CD45: 7000 | CE45: 1945 | CF45: 45696 | CG45: 7000 | CH45: 1973 | CI45: 45728 | CJ45: 7000 | CK45: 1991 | CL45: 45757 | CM45: 7000 | CN45: 011 | CO45: 45786 | CP45: 7000 | CQ45: 035 | CR45: 45817 | CS45: 7000 | CT45: 052 | CU45: 45840 | CV45: 7000 | CW45: 088 | CX45: 45885 | CY45: 7000 | CZ45: 129 | DA45: 45910 | DB45: 7000 | DC45: 156 | DD45: 45937 | DE45: 7000 | DF45: 176 | DG45: 45962 | DH45: 7000 | DI45: 205 | DJ45: 45996 | DK45: 7000 | DL45: 231 | DM45: 46026 | DN45: 7000 | DO45: 256 | DP45: 46057 | DR45: 803 | DS45: Mr. Shamim | DT45: =7000*12 -> 84000 | DU45: =E45+H45+K45+N45+Q45+T45+W45+Z45+AC45+AF45+AI45+AL45 -> 84000 | DV45: =DT45-DU45 -> 0 | DW45: 0 | DX45: =DV45+DW45 -> 0 | DY45: =7000*12 -> 84000 | DZ45: =+AP45+AS45+AV45+AY45+BB45+BE45+BH45+BK45+BN45+BQ45+BT45+BW45 -> 84000 | EA45: =DX45+DY45-DZ45 -> 0 | EB45: =7000*12 -> 84000 | EC45: =CA45+CD45+CG45+CJ45+CM45+CP45+CS45+CV45+CY45+DB45+DE45+DH45 -> 84000 | ED45: =EA45+EB45-EC45 -> 0 | EG45: 803 | EH45: Mr. Shamim | EI45: =7000*12 -> 84000 | EJ45: 0 | EK45: =7000*2 -> 14000 | EL45: =DK45+DN45 -> 14000 | EM45: =EJ45+EK45-EL45 -> 0
B46: Mr. Aziz | C46: 804 | D46: -33000 | H46: 38500 | I46: 1309 | J46: 44960 | T46: 33000 | U46: 1445 | V46: 45082 | AP46: 33000 | AQ46: 1642 | AR46: 45347 | AS46: 11000 | AT46: 1641 | AU46: 45346 | AV46: 5500 | AW46: 1668 | AX46: 45364 | AY46: 5500 | AZ46: 1674 | BA46: 45384 | BB46: 5500 | BC46: 1709 | BD46: 45418 | BE46: 5500 | BF46: 1736 | BG46: 45448 | BH46: 5500 | BI46: 1761 | BJ46: 45481 | BK46: 5500 | BL46: 1780 | BM46: 45506 | BN46: 5500 | BO46: 1807 | BP46: 45537 | BQ46: 5500 | BR46: 1834 | BS46: 45567 | BT46: 5500 | BU46: 1872 | BV46: 45608 | BW46: 5500 | BX46: 1886 | BY46: 45632 | CA46: 5500 | CB46: 1917 | CC46: 45660 | CD46: 5500 | CE46: 1947 | CF46: 45698 | CG46: 5500 | CH46: 1966 | CI46: 45720 | CM46: 5500 | CN46: 008 | CO46: 45784 | CP46: 5500 | CQ46: 031 | CR46: 45812 | CS46: 5500 | CT46: 051 | CU46: 45840 | CV46: =5500+5500 -> 11000 | CW46: 079/107 | CX46: 5,30 Aug | CY46: 5500 | CZ46: 113 | DA46: 45902 | DB46: 5500 | DC46: 143 | DD46: 45931 | DE46: 5500 | DF46: 175 | DG46: 45962 | DH46: 5500 | DI46: 200 | DJ46: 45993 | DK46: 5500 | DL46: 224 | DM46: 46023 | DN46: 5500 | DO46: 252 | DP46: 46054 | DR46: 804 | DS46: Mr. Aziz | DT46: =5500*12 -> 66000 | DU46: =E46+H46+K46+N46+Q46+T46+W46+Z46+AC46+AF46+AI46+AL46 -> 71500 | DV46: =DT46-DU46 -> -5500 | DW46: 38500 | DX46: =DV46+DW46 -> 33000 | DY46: =5500*12 -> 66000 | DZ46: =+AP46+AS46+AV46+AY46+BB46+BE46+BH46+BK46+BN46+BQ46+BT46+BW46 -> 99000 | EA46: =DX46+DY46-DZ46 -> 0 | EB46: =5500*12 -> 66000 | EC46: =CA46+CD46+CG46+CJ46+CM46+CP46+CS46+CV46+CY46+DB46+DE46+DH46 -> 66000 | ED46: =EA46+EB46-EC46 -> 0 | EG46: 804 | EH46: Mr. Aziz | EI46: =5500*12 -> 66000 | EJ46: 0 | EK46: =5500*2 -> 11000 | EL46: =DK46+DN46 -> 11000 | EM46: =EJ46+EK46-EL46 -> 0
B48: Mr. Fahad Qureshi | C48: 901 | D48: -16000 | Z48: 32000 | AA48: 1490 | AB48: 45147 | AV48: 28000 | AW48: 1799 | AX48: 45374 | CA48: 36000 | CB48: 1939 | CC48: 45671 | CV48: 32000 | CW48: 116 | CX48: 45900 | DB48: 16000 | DC48: 162 | DD48: 45942 | DR48: 901 | DS48: Mr. Fahad Qureshi | DT48: =4000*12 -> 48000 | DU48: =E48+H48+K48+N48+Q48+T48+W48+Z48+AC48+AF48+AI48+AL48 -> 32000 | DV48: =DT48-DU48 -> 16000 | DW48: 0 | DX48: =DV48+DW48 -> 16000 | DY48: =4000*12 -> 48000 | DZ48: =+AP48+AS48+AV48+AY48+BB48+BE48+BH48+BK48+BN48+BQ48+BT48+BW48 -> 28000 | EA48: =DX48+DY48-DZ48 -> 36000 | EB48: =4000*12 -> 48000 | EC48: =CA48+CD48+CG48+CJ48+CM48+CP48+CS48+CV48+CY48+DB48+DE48+DH48 -> 84000 | ED48: =EA48+EB48-EC48 -> 0 | EG48: 901 | EH48: Mr. Fahad Qureshi | EI48: =4000*12 -> 48000 | EJ48: 0 | EK48: =4000*2 -> 8000 | EL48: =DK48+DN48 -> 0 | EM48: =EJ48+EK48-EL48 -> 8000
B49: Mr. Taj | C49: 902 | D49: 0 | Q49: =5500+16000+4000 -> 25500 | R49: 1399/1402/1405 | S49: 3,8,10 May | T49: 5500 | U49: 1438 | V49: 45088 | W49: 5500 | X49: 1458 | Y49: 45117 | Z49: 5500 | AA49: 1483 | AB49: 45148 | AC49: 5500 | AD49: 1515 | AE49: 45180 | AF49: =5500+4000 -> 9500 | AG49: 1535/1545 | AH49: 10,22 Oct | AI49: 5500 | AJ49: 1561 | AK49: 45243 | AL49: 5500 | AM49: 1579 | AN49: 45271 | AP49: 5500 | AQ49: 1602 | AR49: 45301 | AS49: 5500 | AT49: 1665 | AU49: 45334 | AV49: 5500 | AW49: 1662 | AX49: 45362 | AY49: 5500 | AZ49: 1688 | BA49: 45391 | BB49: 5500 | BC49: 1713 | BD49: 45423 | BE49: 5500 | BF49: 1735 | BG49: 45453 | BH49: 5500 | BI49: 1763 | BJ49: 45483 | BK49: 5500 | BL49: 1789 | BM49: 45518 | BN49: 5500 | BO49: 1818 | BP49: 45548 | BQ49: 5500 | BR49: 1849 | BS49: 45578 | BT49: 5500 | BU49: 1873 | BV49: 45607 | BW49: 5500 | BX49: 1894 | BY49: 45641 | CA49: 5500 | CB49: 1929 | CC49: 45673 | CD49: 5500 | CE49: 1951 | CF49: 45704 | CG49: 5500 | CH49: 1974 | CI49: 45729 | CJ49: 5500 | CK49: 1995 | CL49: 45762 | CM49: 5500 | CN49: 012 | CO49: 45788 | CP49: 5500 | CQ49: 043 | CR49: 45820 | CS49: 5500 | CT49: 059 | CU49: 45852 | CV49: 5500 | CW49: 092 | CX49: 45886 | CY49: 5500 | CZ49: 134 | DA49: 45914 | DB49: 5500 | DC49: 165 | DD49: 45942 | DE49: 5500 | DF49: 193 | DG49: 45977 | DH49: 5500 | DI49: 226 | DJ49: 46022 | DK49: 5500 | DL49: 250 | DM49: 46039 | DR49: 902 | DS49: Mr. Taj | DT49: =16000+44000 -> 60000 | DU49: =E49+H49+K49+N49+Q49+T49+W49+Z49+AC49+AF49+AI49+AL49 -> 68000 | DV49: =DT49-DU49 -> -8000 | DW49: 8000 | DX49: =DV49+DW49 -> 0 | DY49: =5500*12 -> 66000 | DZ49: =+AP49+AS49+AV49+AY49+BB49+BE49+BH49+BK49+BN49+BQ49+BT49+BW49 -> 66000 | EA49: =DX49+DY49-DZ49 -> 0 | EB49: =5500*12 -> 66000 | EC49: =CA49+CD49+CG49+CJ49+CM49+CP49+CS49+CV49+CY49+DB49+DE49+DH49 -> 66000 | ED49: =EA49+EB49-EC49 -> 0 | EG49: 902 | EH49: Mr. Arif 2 | EI49: =5500*12 -> 66000 | EJ49: 0 | EK49: =5500*2 -> 11000 | EL49: =DK49+DN49 -> 5500 | EM49: =EJ49+EK49-EL49 -> 5500
B50: Mr. Muhammad Arif | C50: 903 | D50: =-14000-7000+21000 -> 0 | E50: 14000 | F50: 1290 | G50: 44938 | H50: 7000 | I50: 1327 | J50: 44972 | K50: 7000 | L50: 1344 | M50: 44989 | N50: 7000 | O50: 1375 | P50: 45022 | Q50: 7000 | R50: 1418 | S50: 45066 | W50: 7000 | X50: 1451 | Y50: 45112 | Z50: 14000 | AA50: 1486 | AB50: 45148 | AC50: 7000 | AD50: 1506 | AE50: 45171 | AF50: 7000 | AG50: 1532 | AH50: 45205 | AP50: 21000 | AQ50: 1591 | AR50: 45292 | AS50: 7000 | AT50: 1654 | AU50: 45351 | AV50: 7000 | AW50: 1695 | AX50: 45371 | AY50: =7000 -> 7000 | AZ50: 1696 | BA50: 45406 | BK50: 28000 | BL50: 1778 | BM50: 45505 | BN50: 28000 | BO50: 1806 | BP50: 45537 | CA50: 84000 | CB50: 1921 | CC50: 45665 | DK50: 7000 | DL50: 249 | DM50: 46039 | DR50: 903 | DS50: Mr. Muhammad Arif | DT50: =7000*12 -> 84000 | DU50: =E50+H50+K50+N50+Q50+T50+W50+Z50+AC50+AF50+AI50+AL50 -> 77000 | DV50: =DT50-DU50 -> 7000 | DW50: 7000 | DX50: =DV50+DW50 -> 14000 | DY50: =7000*12 -> 84000 | DZ50: =+AP50+AS50+AV50+AY50+BB50+BE50+BH50+BK50+BN50+BQ50+BT50+BW50 -> 98000 | EA50: =DX50+DY50-DZ50 -> 0 | EB50: =7000*12 -> 84000 | EC50: =CA50+CD50+CG50+CJ50+CM50+CP50+CS50+CV50+CY50+DB50+DE50+DH50 -> 84000 | ED50: =EA50+EB50-EC50 -> 0 | EG50: 903 | EH50: Mr. Muhammad Arif | EI50: =7000*12 -> 84000 | EJ50: 0 | EK50: =7000*2 -> 14000 | EL50: =DK50+DN50 -> 7000 | EM50: =EJ50+EK50-EL50 -> 7000
B51: Mr. Hafeez | C51: 904 | D51: -5500 | E51: 5500 | F51: 1298 | G51: 44943 | H51: 5500 | I51: 1306 | J51: 44960 | K51: 5500 | L51: 1340 | M51: 44988 | N51: 5500 | O51: 1376 | P51: 45023 | Q51: 5500 | R51: 1399 | S51: 45049 | T51: 5500 | U51: 1429 | V51: 45081 | W51: 5500 | X51: 1455 | Y51: 45115 | Z51: 5500 | AA51: 1498 | AB51: 45160 | AC51: 5500 | AD51: 1521 | AE51: 45185 | AI51: =5500+5500 -> 11000 | AJ51: 1551/1568 | AK51: 1, 30 Nov | AP51: 11000 | AQ51: 1604 | AR51: 45304 | AS51: 5500 | AT51: 1658 | AU51: 45350 | AV51: 5500 | AW51: 1657 | AX51: 45357 | AY51: 5500 | AZ51: 1686 | BA51: 45388 | BB51: 5500 | BC51: 1729 | BD51: 45443 | BH51: 5500 | BI51: 1773 | BJ51: 45498 | BN51: 11000 | BO51: 1804 | BP51: 45536 | BQ51: 11000 | BR51: 1850 | BS51: 45579 | BT51: 5500 | BU51: 1861 | BV51: 45599 | BW51: 5500 | BX51: 1916 | BY51: 45657 | CD51: 11000 | CE51: 1950 | CF51: 45702 | CG51: 5500 | CH51: 1975 | CI51: 45722 | CJ51: 5500 | CK51: 1987 | CL51: 45754 | CM51: 5500 | CN51: 020 | CO51: 45789 | CP51: 5500 | CQ51: 039 | CR51: 45818 | CS51: 5500 | CT51: 053 | CU51: 45841 | CV51: 5500 | CW51: 084 | CX51: 45882 | CY51: 5500 | CZ51: 140 | DA51: 45922 | DB51: 5500 | DC51: 167 | DD51: 45950 | DE51: 5500 | DF51: 191 | DG51: 45976 | DH51: 5500 | DI51: 213 | DJ51: 46008 | DK51: 5500 | DL51: 246 | DM51: 46034 | DN51: 5500 | DO51: 276 | DP51: 46070 | DR51: 904 | DS51: Mr. Hafeez | DT51: =5500*12 -> 66000 | DU51: =E51+H51+K51+N51+Q51+T51+W51+Z51+AC51+AF51+AI51+AL51 -> 60500 | DV51: =DT51-DU51 -> 5500 | DW51: 0 | DX51: =DV51+DW51 -> 5500 | DY51: =5500*12 -> 66000 | DZ51: =+AP51+AS51+AV51+AY51+BB51+BE51+BH51+BK51+BN51+BQ51+BT51+BW51 -> 71500 | EA51: =DX51+DY51-DZ51 -> 0 | EB51: =5500*12 -> 66000 | EC51: =CA51+CD51+CG51+CJ51+CM51+CP51+CS51+CV51+CY51+DB51+DE51+DH51 -> 66000 | ED51: =EA51+EB51-EC51 -> 0 | EG51: 904 | EH51: Mr. Hafeez | EI51: =5500*12 -> 66000 | EJ51: 0 | EK51: =5500*2 -> 11000 | EL51: =DK51+DN51 -> 11000 | EM51: =EJ51+EK51-EL51 -> 0
B53: Mr. Danish | C53: 1001 | D53: 0 | H53: 15000 | I53: 1331 | J53: 44983 | K53: 7500 | L53: 1379 | M53: 45016 | Q53: 15000 | R53: 1420 | S53: 45066 | Z53: =7500*3 -> 22500 | AA53: 1502 | AB53: 45165 | AC53: 7500 | AD53: 1544 | AE53: 45199 | AL53: =7500*3 -> 22500 | AM53: 1610 | AN53: 45291 | AV53: =7500*3 -> 22500 | AW53: 1699 | AX53: 45382 | BE53: =7500*3 -> 22500 | BF53: 1902 | BG53: 45473 | BW53: =7500*6 -> 45000 | BX53: 1904 | BY53: 45656 | CS53: 38500 | CT53: 072 | CU53: 45869 | CV53: 5500 | CW53: 109 | CX53: 45900 | CY53: 4000 | CZ53: 146 | DA53: 45930 | DR53: 1001 | DS53: Mr. Danish | DT53: =7500*12 -> 90000 | DU53: =E53+H53+K53+N53+Q53+T53+W53+Z53+AC53+AF53+AI53+AL53 -> 90000 | DV53: =DT53-DU53 -> 0 | DW53: 0 | DX53: =DV53+DW53 -> 0 | DY53: =7500*12 -> 90000 | DZ53: =+AP53+AS53+AV53+AY53+BB53+BE53+BH53+BK53+BN53+BQ53+BT53+BW53 -> 90000 | EA53: =DX53+DY53-DZ53 -> 0 | EB53: =5500+5500+5500+5500+5500+5500+5500+5500+4000+4000+4000+4000 -> 60000 | EC53: =CA53+CD53+CG53+CJ53+CM53+CP53+CS53+CV53+CY53+DB53+DE53+DH53 -> 48000 | ED53: =EA53+EB53-EC53 -> 12000 | EG53: 1001 | EH53: Mr. Danish | EI53: =4000*12 -> 48000 | EJ53: 12000 | EK53: =4000*2 -> 8000 | EL53: =DK53+DN53 -> 0 | EM53: =EJ53+EK53-EL53 -> 20000
B54: Dr. Mansoor | C54: 1002 | D54: 0 | E54: 5500 | F54: 1279 | G54: 44929 | H54: 5500 | I54: 1303 | J54: 44958 | K54: 5500 | L54: 1334 | M54: 44986 | N54: 5500 | O54: 1365 | P54: 45019 | Q54: 5500 | R54: 1393 | S54: 45047 | T54: 5500 | U54: 1423 | V54: 45078 | W54: 5500 | X54: 1448 | Y54: 45110 | Z54: 5500 | AA54: 1471 | AB54: 45140 | AC54: 5500 | AD54: 1503 | AE54: 45170 | AF54: 5500 | AG54: 1525 | AH54: 45201 | AI54: 5500 | AJ54: 1549 | AK54: 45231 | AL54: 5500 | AM54: 1569 | AN54: 45261 | AP54: 5500 | AQ54: 1590 | AR54: 45292 | AS54: 5500 | AT54: 1624 | AU54: 45323 | AV54: 5500 | AW54: 1646 | AX54: 45352 | AY54: 5500 | AZ54: 1675 | BA54: 45384 | BB54: 5500 | BC54: 1704 | BD54: 45413 | BE54: 5500 | BF54: 1730 | BG54: 45444 | BH54: 5500 | BI54: 1754 | BJ54: 45474 | BK54: 5500 | BL54: 1776 | BM54: 45505 | BN54: 5500 | BO54: 1805 | BP54: 45537 | BQ54: 5500 | BR54: 1832 | BS54: 45566 | BT54: 5500 | BU54: 1854 | BV54: 45597 | BW54: 5500 | BX54: 1881 | BY54: 45628 | CA54: 5500 | CB54: 1912 | CC54: 45658 | CD54: 5500 | CE54: 1937 | CF54: 45689 | CG54: 5500 | CH54: 1960 | CI54: 45717 | CJ54: 5500 | CK54: 1983 | CL54: 45748 | CM54: 5500 | CN54: 004 | CO54: 45781 | CP54: 5500 | CQ54: 016 | CR54: 45809 | CS54: 5500 | CT54: 048 | CU54: 45839 | CV54: 5500 | CW54: 066 | CX54: 45870 | CY54: 5500 | CZ54: 112 | DA54: 45901 | DB54: 5500 | DC54: 142 | DD54: 45931 | DE54: 5500 | DF54: 174 | DG54: 45962 | DH54: 5500 | DI54: 199 | DJ54: 45992 | DK54: 5500 | DL54: 223 | DM54: 46023 | DN54: 5500 | DO54: 253 | DP54: 46054 | DR54: 1002 | DS54: Dr. Mansoor | DT54: =5500*12 -> 66000 | DU54: =E54+H54+K54+N54+Q54+T54+W54+Z54+AC54+AF54+AI54+AL54 -> 66000 | DV54: =DT54-DU54 -> 0 | DW54: 0 | DX54: =DV54+DW54 -> 0 | DY54: =5500*12 -> 66000 | DZ54: =+AP54+AS54+AV54+AY54+BB54+BE54+BH54+BK54+BN54+BQ54+BT54+BW54 -> 66000 | EA54: =DX54+DY54-DZ54 -> 0 | EB54: =5500*12 -> 66000 | EC54: =CA54+CD54+CG54+CJ54+CM54+CP54+CS54+CV54+CY54+DB54+DE54+DH54 -> 66000 | ED54: =EA54+EB54-EC54 -> 0 | EG54: 1002 | EH54: Dr. Mansoor | EI54: =5500*12 -> 66000 | EJ54: 0 | EK54: =5500*2 -> 11000 | EL54: =DK54+DN54 -> 11000 | EM54: =EJ54+EK54-EL54 -> 0
B55: Mr. Wajih | C55: 1003 | D55: -9000 | E55: 9000 | F55: 1285 | G55: 44933 | H55: 9000 | I55: 1311 | J55: 44962 | K55: 9000 | L55: 1338 | M55: 44988 | N55: 9000 | O55: 1370 | P55: 45020 | Q55: 9000 | R55: 1396 | S55: 45049 | T55: 9000 | U55: 1424 | V55: 45078 | W55: 9000 | X55: 1452 | Y55: 45113 | Z55: 9000 | AA55: 1476 | AB55: 45142 | AC55: 9000 | AD55: 1511 | AE55: 45175 | AF55: 9000 | AG55: 1531 | AH55: 45204 | AL55: 9000 | AM55: 1582 | AN55: 45274 | AP55: 9000 | AQ55: 1593 | AR55: 45295 | AS55: 9000 | AT55: 1634 | AU55: 45334 | AV55: 9000 | AW55: 1655 | AX55: 45356 | AY55: 9000 | AZ55: 1680 | BA55: 45386 | BB55: 9000 | BC55: 1711 | BD55: 45419 | BE55: 9000 | BF55: 1738 | BG55: 45448 | BH55: 9000 | BI55: 1758 | BJ55: 45479 | BK55: 9000 | BL55: 1790 | BM55: 45518 | BN55: 9000 | BO55: 1816 | BP55: 45545 | BQ55: 9000 | BR55: 1840 | BS55: 45570 | BT55: 9000 | BU55: 1863 | BV55: 45605 | BW55: 9000 | BX55: 1884 | BY55: 45630 | CA55: 9000 | CB55: 1926 | CC55: 45667 | CD55: 9000 | CE55: 1942 | CF55: 45692 | CG55: 9000 | CH55: 1971 | CI55: 45723 | CJ55: 9000 | CK55: 023 | CL55: 45753 | CM55: 9000 | CN55: 018 | CO55: 45789 | CP55: 9000 | CQ55: 038 | CR55: 45818 | CS55: 9000 | CT55: 075 | CU55: 45869 | CV55: 18000 | CW55: 090 | CX55: 45874 | CY55: 9000 | CZ55: 121 | DA55: 45905 | DB55: 9000 | DC55: 155 | DD55: 45936 | DE55: 9000 | DF55: 181 | DG55: 45966 | DH55: 9000 | DI55: 204 | DJ55: 45996 | DK55: 9000 | DL55: 238 | DM55: 46030 | DN55: 9000 | DO55: 262 | DP55: 46058 | DR55: 1003 | DS55: Mr. Wajih | DT55: =9000*12 -> 108000 | DU55: =E55+H55+K55+N55+Q55+T55+W55+Z55+AC55+AF55+AI55+AL55 -> 99000 | DV55: =DT55-DU55 -> 9000 | DW55: 0 | DX55: =DV55+DW55 -> 9000 | DY55: =9000*12 -> 108000 | DZ55: =+AP55+AS55+AV55+AY55+BB55+BE55+BH55+BK55+BN55+BQ55+BT55+BW55 -> 108000 | EA55: =DX55+DY55-DZ55 -> 9000 | EB55: =9000*12 -> 108000 | EC55: =CA55+CD55+CG55+CJ55+CM55+CP55+CS55+CV55+CY55+DB55+DE55+DH55 -> 117000 | ED55: =EA55+EB55-EC55 -> 0 | EG55: 1003 | EH55: Mr. Wajih | EI55: =9000*12 -> 108000 | EJ55: 0 | EK55: =9000*2 -> 18000 | EL55: =DK55+DN55 -> 18000 | EM55: =EJ55+EK55-EL55 -> 0
B56: Mr. Ali | C56: 1004 | D56: -5500 | E56: 5500 | F56: 1287 | G56: 44934 | H56: 5500 | I56: 1307 | J56: 44960 | K56: 5500 | L56: 1347 | M56: 44990 | N56: 5500 | O56: 1386 | P56: 45027 | Q56: 5500 | R56: 1397 | S56: 45049 | T56: 5500 | U56: 1422 | V56: 45078 | W56: 5500 | X56: 1459 | Y56: 45118 | Z56: 5500 | AA56: 1475 | AB56: 45142 | AC56: 5500 | AD56: 1520 | AE56: 45183 | AF56: 5500 | AG56: 1529 | AH56: 45202 | AI56: 5500 | AJ56: 1724 | AK56: 45260 | AL56: 5500 | AM56: 1574 | AN56: 45263 | AP56: 5500 | AQ56: 1597 | AR56: 45300 | AS56: 5500 | AT56: 1629 | AU56: 45330 | AV56: 5500 | AW56: 1653 | AX56: 45355 | AY56: 5500 | AZ56: 1681 | BA56: 45387 | BB56: 5500 | BC56: 1708 | BD56: 45415 | BE56: 5500 | BF56: 1735 | BG56: 45447 | BH56: 5500 | BI56: 1768 | BJ56: 45486 | BK56: 5500 | BL56: 1779 | BM56: 45505 | BN56: 5500 | BO56: 1810 | BP56: 45539 | BQ56: 5500 | BR56: 1843 | BS56: 45571 | BT56: 5500 | BU56: 1858 | BV56: 45598 | BW56: 5500 | BX56: 1887 | BY56: 45635 | CA56: 5500 | CB56: 1920 | CC56: 45662 | CD56: 5500 | CE56: 1946 | CF56: 45696 | CG56: 5500 | CH56: 1976 | CI56: 45730 | CJ56: 5500 | CK56: 1992 | CL56: 45760 | CM56: 5500 | CN56: 001 | CO56: 45781 | CP56: 5500 | CQ56: 032 | CR56: 45812 | CS56: 5500 | CT56: 093 | CU56: 45869 | CV56: 5500 | CW56: 078 | CX56: 45874 | CY56: 5500 | CZ56: 132 | DA56: 45914 | DB56: 5500 | DC56: 163 | DD56: 45938 | DE56: 5500 | DF56: 185 | DG56: 45967 | DH56: 5500 | DI56: 211 | DJ56: 46007 | DK56: 5500 | DL56: 240 | DM56: 46030 | DN56: 5500 | DO56: 272 | DP56: 46065 | DR56: 1004 | DS56: Mr. Ali | DT56: =5500*12 -> 66000 | DU56: =E56+H56+K56+N56+Q56+T56+W56+Z56+AC56+AF56+AI56+AL56 -> 66000 | DV56: =DT56-DU56 -> 0 | DW56: 0 | DX56: =DV56+DW56 -> 0 | DY56: =5500*12 -> 66000 | DZ56: =+AP56+AS56+AV56+AY56+BB56+BE56+BH56+BK56+BN56+BQ56+BT56+BW56 -> 66000 | EA56: =DX56+DY56-DZ56 -> 0 | EB56: =5500*12 -> 66000 | EC56: =CA56+CD56+CG56+CJ56+CM56+CP56+CS56+CV56+CY56+DB56+DE56+DH56 -> 66000 | ED56: =EA56+EB56-EC56 -> 0 | EG56: 1004 | EH56: Mr. Ali | EI56: =5500*12 -> 66000 | EJ56: 0 | EK56: =5500*2 -> 11000 | EL56: =DK56+DN56 -> 11000 | EM56: =EJ56+EK56-EL56 -> 0
DX57: =DV57+DW57 -> 0
B58: Total | E58: =SUM(E8:E56) -> 184500 | H58: =SUM(H8:H56) -> 350000 | K58: =SUM(K8:K56) -> 291500 | N58: =SUM(N8:N56) -> 212500 | Q58: =SUM(Q8:Q56) -> 213000 | T58: =SUM(T8:T56) -> 236000 | W58: =SUM(W8:W56) -> 191500 | Z58: =SUM(Z8:Z56) -> 362500 | AC58: =SUM(AC8:AC56) -> 210000 | AF58: =SUM(AF8:AF56) -> 160000 | AI58: =SUM(AI8:AI56) -> 194000 | AL58: =SUM(AL8:AL56) -> 293000 | AP58: =SUM(AP8:AP56) -> 477000 | AS58: =SUM(AS8:AS56) -> 185500 | AV58: =SUM(AV8:AV56) -> 213000 | AY58: =SUM(AY8:AY56) -> 376500 | BB58: =SUM(BB8:BB56) -> 161000 | BE58: =SUM(BE8:BE56) -> 249500 | BH58: =SUM(BH8:BH56) -> 173500 | BK58: =SUM(BK8:BK56) -> 179000 | BN58: =SUM(BN8:BN56) -> 290500 | BQ58: =SUM(BQ8:BQ56) -> 254500 | BT58: =SUM(BT8:BT56) -> 206500 | BW58: =SUM(BW8:BW56) -> 406000 | CA58: =SUM(CA8:CA56) -> 264500 | CD58: =SUM(CD8:CD56) -> 161000 | CG58: =SUM(CG8:CG56) -> 257000 | CJ58: =SUM(CJ8:CJ56) -> 120500 | CM58: =SUM(CM8:CM56) -> 157500 | CP58: =SUM(CP8:CP56) -> 215500 | CS58: =SUM(CS8:CS56) -> 370500 | CV58: =SUM(CV8:CV56) -> 912000 | CY58: =SUM(CY8:CY56) -> 300500 | DB58: =SUM(DB8:DB56) -> 232500 | DE58: =SUM(DE8:DE56) -> 200000 | DH58: =SUM(DH8:DH56) -> 163001 | DK58: =SUM(DK8:DK56) -> 262500 | DN58: =SUM(DN8:DN56) -> 172500 | DR58: Total | DT58: =SUM(DT8:DT56) -> 3084500 | DU58: =SUM(DU8:DU56) -> 2898500 | DV58: =SUM(DV8:DV56) -> 186000 | DW58: =SUM(DW8:DW56) -> 281500 | DX58: =SUM(DX8:DX56) -> 469000 | DZ58: =SUM(DZ8:DZ56) -> 3172500 | EA58: =SUM(EA8:EA56) -> 404500 | EB58: =SUM(EB8:EB56) -> 3140001 | EC58: =SUM(EC8:EC56) -> 3354501 | ED58: =SUM(ED8:ED56) -> 190000 | EE58: =SUM(EE8:EE56) -> 0 | EG58: Shop Maint. (A) | EI58: =7500*12 -> 90000 | EJ58: 22500 | EK58: =7500*2 -> 15000 | EL58: =DK61+DN61 -> 0 | EM58: =EJ58+EK58-EL58 -> 37500
B60: Other Income : | EG60: Total | EI60: =SUM(EI8:EI58) -> 3186000 | EJ60: =SUM(EJ8:EJ58) -> 212500 | EK60: =SUM(EK8:EK58) -> 529500 | EL60: =SUM(EL8:EL58) -> 435000 | EM60: =SUM(EM8:EM58) -> 307000
B61: Shop Maintenance (A) | D61: =-7500-7500+7500-7500-7500+15000-7500-7500-7500+15000-7500+15000-7500+7500 -> -7500 | H61: 7500 | I61: 1323 | J61: 44969 | N61: 15000 | O61: 1388 | P61: 45028 | W61: 15000 | X61: 1454 | Y61: 45115 | Z61: 15000 | AA61: 1488 | AB61: 45149 | AC61: 7500 | AD61: 1518 | AE61: 45182 | AI61: 15000 | AJ61: 1563 | AK61: 45247 | AP61: 15000 | AQ61: 1596 | AR61: 45294 | AS61: 15000 | AT61: 1629 | AU61: 45342 | BE61: =15000+15000 -> 30000 | BF61: 1741/1744 | BG61: 45453 | BT61: 15000 | BU61: 1864 | BV61: 45605 | CV61: 90000 | CW61: 105 | CX61: 45900 | DE61: 7500 | DF61: 0196 | DG61: 45983 | DR61: Shop Maint. (A) | DT61: =7500*12 -> 90000 | DU61: =E61+H61+K61+N61+Q61+T61+W61+Z61+AC61+AF61+AI61+AL61 -> 75000 | DV61: =DT61-DU61 -> 15000 | DW61: 0 | DX61: =DV61+DW61 -> 15000 | DY61: =7500*12 -> 90000 | DZ61: =+AP61+AS61+AV61+AY61+BB61+BE61+BH61+BK61+BN61+BQ61+BT61+BW61 -> 75000 | EA61: =DX61+DY61-DZ61 -> 30000 | EB61: =7500*12 -> 90000 | EC61: =CA61+CD61+CG61+CJ61+CM61+CP61+CS61+CV61+CY61+DB61+DE61+DH61 -> 97500 | ED61: =EA61+EB61-EC61 -> 22500
B62: Rent Community Hall | H62: 4000 | I62: 1339 | J62: 44960 | K62: =4000 -> 4000 | L62: 1358 | M62: 45004 | N62: 4000 | O62: 1369 | P62: 45020 | Q62: 4000 | R62: 1415 | S62: 45060 | AL62: 4000 | AM62: 1587 | AN62: 45282 | BW62: =4000+4000 -> 8000 | BX62: 1905/1907 | BY62: 24/30 Dec | CM62: 8000 | CN62: 021 | CO62: 45789 | CP62: 4000 | CQ62: 069 | CR62: 45853 | CS62: 8000 | CT62: 064 | CU62: 45865 | DB62: 4000 | DC62: 171 | DD62: 45957 | DH62: 8000 | DI62: 212 | DJ62: 46007
B63: Advertisement - Asif (A) | E63: 500000 | G63: 44957 | H63: 500000 | J63: 44985 | K63: 625000 | M63: 45016 | N63: 1625000 | W63: 1625000 | AF63: 1625000 | AP63: =+Advertisment!D22 -> 1706250 | AY63: =+Advertisment!D23 -> 1791562.5 | BH63: =+Advertisment!D24 -> 1791563 | BQ63: =+Advertisment!D25 -> 1791563 | BT63: 0 | CA63: =+Advertisment!D26 -> 1791563 | CM63: =+Advertisment!D27-89578 -> 1791562.6 | CN63: Received Short amount | CV63: =1100000+781000 -> 1881000 | CY63: 600000 | CZ63: Rec. Asif | DA63: 45924 | DB63: 500000 | DC63: Rec. Dilshad | DD63: 45951 | DE63: =600000+270000 -> 870000 | DF63: Rec. Dilshad | DG63: Nov 20, Dec 01 | DH63: 500000 | DI63: Rec. Dilshad | DJ63: 46010 | ED63: =7500*4 -> 30000
B64: Advertisement - Raza (B) | E64: 400000 | G64: 44957 | Q64: 400000 | AF64: 400000 | CG64: 100000 | CH64: 2 Adds Adhoc | CY64: 300000
B65: Advertisement - Shehryar (C) | E65: 300000 | G65: 44957 | N65: 300000 | P65: 45046 | W65: 300000 | Y65: 45115 | AF65: 300000 | AH65: 45230 | AP65: 300000 | AR65: 45322 | AY65: 300000 | BA65: 45412 | BH65: 300000 | BJ65: 45504 | BQ65: =+Advertisment!D58 -> 300000 | BS65: 45596 | BT65: 0 | CA65: 300000 | CC65: 45688 | CJ65: 300000 | CL65: 45777 | CV65: 200000 | CY65: 100000 | DE65: 150000 | DF65: Rec. Dilshad | DG65: 45979 | DH65: 150000 | DI65: Rec. Dilshad | DJ65: 46006
B66: Scrap Sale / AC | CA66: 10000 | CD66: 60000 | DH66: 50000 | DI66: Rec. Dilshad | DJ66: 45993
B67: Advertisement Utility Bill Collection
B68: Gross Total | E68: =E62+E63+E64+E65+E58+E61 -> 1384500 | H68: =H62+H63+H64+H65+H58+H61 -> 861500 | K68: =K62+K63+K64+K65+K58+K61 -> 920500 | N68: =N62+N63+N64+N65+N58+N61 -> 2156500 | Q68: =Q62+Q63+Q64+Q65+Q58+Q61 -> 617000 | T68: =T62+T63+T64+T65+T58+T61 -> 236000 | W68: =W62+W63+W64+W65+W58+W61 -> 2131500 | Z68: =Z62+Z63+Z64+Z65+Z58+Z61 -> 377500 | AC68: =AC62+AC63+AC64+AC65+AC58+AC61 -> 217500 | AF68: =AF62+AF63+AF64+AF65+AF58+AF61 -> 2485000 | AI68: =AI62+AI63+AI64+AI65+AI58+AI61 -> 209000 | AL68: =AL62+AL63+AL64+AL65+AL58+AL61 -> 297000 | AP68: =AP62+AP63+AP64+AP65+AP58+AP61 -> 2498250 | AS68: =AS62+AS63+AS64+AS65+AS58+AS61 -> 200500 | AV68: =AV62+AV63+AV64+AV65+AV58+AV61 -> 213000 | AY68: =AY62+AY63+AY64+AY65+AY58+AY61 -> 2468062.5 | BB68: =BB62+BB63+BB64+BB65+BB58+BB61 -> 161000 | BE68: =BE62+BE63+BE64+BE65+BE58+BE61 -> 279500 | BH68: =BH62+BH63+BH64+BH65+BH58+BH61 -> 2265063 | BK68: =BK62+BK63+BK64+BK65+BK58+BK61 -> 179000 | BN68: =BN62+BN63+BN64+BN65+BN58+BN61 -> 290500 | BQ68: =BQ62+BQ63+BQ64+BQ65+BQ58+BQ61 -> 2346063 | BT68: =BT62+BT63+BT64+BT65+BT58+BT61 -> 221500 | BW68: =BW62+BW63+BW64+BW65+BW58+BW61 -> 414000 | CA68: =CA62+CA63+CA64+CA65+CA58+CA61+CA66 -> 2366063 | CD68: =CD62+CD63+CD64+CD65+CD58+CD61+CD66 -> 221000 | CG68: =CG62+CG63+CG64+CG65+CG58+CG61+CG66 -> 357000 | CJ68: =CJ62+CJ63+CJ64+CJ65+CJ58+CJ61+CJ66 -> 420500 | CM68: =CM62+CM63+CM64+CM65+CM58+CM61+CM66 -> 1957062.6 | CP68: =CP62+CP63+CP64+CP65+CP58+CP61+CP66 -> 219500 | CS68: =CS62+CS63+CS64+CS65+CS58+CS61+CS66 -> 378500 | CV68: =CV62+CV63+CV64+CV65+CV58+CV61+CV66 -> 3083000 | CY68: =CY62+CY63+CY64+CY65+CY58+CY61+CY66 -> 1300500 | DB68: =DB62+DB63+DB64+DB65+DB58+DB61+DB66 -> 736500 | DE68: =DE62+DE63+DE64+DE65+DE58+DE61+DE66 -> 1227500 | DH68: =DH62+DH63+DH64+DH65+DH58+DH61+DH66 -> 871001 | DK68: =DK62+DK63+DK64+DK65+DK58+DK61+DK66 -> 262500 | DN68: =DN62+DN63+DN64+DN65+DN58+DN61+DN66 -> 172500
CM70: =CM63-CA63 -> -0.375 | CS70: Maintenance Received By Naveed | CV70: =CV9+CV10+CV11+CV14+CV15+CV16+CV25+CV26+CV28+CV29+CV30+CV35+CV41+CV48+CV55+CV61 -> 837500 | CW70: =CV70+CV84+CV85 -> 859000 | CY70: 300500 | DB70: =+DB58+DB62 -> 236500 | DE70: =+DE58+DE61 -> 207500 | DH70: =+DH58+DH62 -> 171001 | DK70: =+DK58+DK62 -> 262500 | DN70: =+DN58+DN62 -> 172500
CS76: Maintenance Received By Danish | CV76: =CV13+CV18+CV20+CV23+CV31+CV33+CV34+CV36+CV38+CV39+CV40+CV43+CV44+CV45+CV46+CV49+CV51+CV53+CV54+CV56 -> 164500 | CW76: =CV76-CV87-CV88-CV84-CV85 -> 128500 | CY76: 0 | DB76: 0 | DE76: 0
CS77: Advertisement Received by Danish | CV77: =CV63+CV65 -> 2081000 | CW77: =CV63+CV65 -> 2081000 | CY77: =+CY64+CY65 -> 400000 | DB77: 0 | DE77: 0
CS78: Funds Received By Asif | CY78: =+CY63 -> 600000 | DB78: 0 | DE78: 0
CS79: Funds Received By Dilshad | DB79: =+DB63 -> 500000 | DE79: =+DE63+DE64 -> 870000 | DH79: =+DH63+DH65+DH66 -> 700000
CS80: Funds Received By Ali
CS81: Adjustment - Old issue adjusted | CW81: =+CV87+CV88 -> 14500
CV82: =CV70+CV76+CV77 -> 3083000 | CW82: =CW70+CW76+CW77+CW81 -> 3083000
CT84: Dr. Nazim | CV84: 16000
CT85: Irfan Bhai 804 | CV85: 5500 | DG85: Moved Below in Receipt 2026
DC86: Transfer from Danish | DE86: =+Naveed!AZ151 -> 206030 | DG86: 206030
CT87: Adj Sohail | CV87: 5500 | DE87: =CW70+CY70+DB70+DE70+DH70+'Recpt 2026'!D58+'Recpt 2026'!G58+'Recpt 2026'!J58 -> 2450001 | DG87: =CW70+CY70+DB70+DE70+DH70 -> 1774501
CT88: Adj Yousuf | CV88: 9000
DB89: Kelectric | DC89: 45901 | DD89: 261172
DB90: Kelectric | DC90: 45931 | DD90: 237312
DB91: Imam Sb salary | DC91: 45933 | DD91: 25000
DB92: Transfer to Danish | DC92: 45934 | DD92: 100000
DB93: Cash Salaries | DC93: 45931 | DD93: 129000
DB94: Kelectric | DC94: 45964 | DD94: 249928
DB95: Kelectric | DC95: 46025 | DD95: 219111
DB96: Kelectric | DC96: 46055 | DD96: 226381
DB97: Kelectric | DC97: 46087 | DD97: 242468
DE98: =-SUM(DD89:DD97) -> -1690372
DB100: Colour Payment | DC100: 45910 | DD100: 48960
DB101: Colour Payment | DC101: 45971 | DD101: 17900
DB102: Amanat Labour | DC102: 45971 | DD102: 20000
DB103: Amanat Labour | DC103: 18/10/2025 | DD103: 20000
DB104: Colour Payment | DC104: 20/10/2025 | DD104: 29850
DB105: Amanat Labour | DC105: 25/10/2025 | DD105: 20000
DB106: Amanat Labour | DC106: 27/10/2025 | DD106: 30000
DB107: Colour Payment | DC107: 28/10/2025 | DD107: 74480
DB108: Colour Payment | DC108: 45727 | DD108: 51640
DB109: Amanat Labour | DC109: 45727 | DD109: 30000
DB110: Colour Payment | DC110: 45788 | DD110: 6260
DB111: Colour Payment | DC111: 45788 | DD111: 6000
DB112: Colour Payment | DC112: 45880 | DD112: 62570
DB113: Amanat Labour | DC113: 45880 | DD113: 60000
DB114: Amanat Labour | DC114: 45972 | DD114: 50000
DB115: Colour Payment | DC115: 23/11/2025 | DD115: 6450
DE116: =-SUM(DD100:DD115) -> -534110
DE117: =DE86+DE87+DE98+DE116 -> 431549
DC119: Account balance as of | DE119: 126516
DC120: Cash n Hand | DE120: 247000
DE121: =DE117-DE119-DE120 -> 58033
DC123: Shahid Bhai | DE123: 7000
...

Sheet Sheet1
A1: Appartment No. | B1: Monthly Maintenance | C1: Maintenance Recived during the Year 2023 | D1: Due for the Year 2023 | E1: Due for the last Year 2022 | F1: Total Amount Due (2022+2023) | G1: Monthly Maintenance Amount till April 2024 | H1: Maintenance Amount Received till April 2024 | I1: Still Outstanding
A3: 101 | B3: 90000 | C3: 82500 | D3: 7500 | E3: 7500 | F3: 15000 | G3: 30000 | H3: 45000 | I3: 0
A4: 102 | B4: 84000 | C4: 70000 | D4: 14000 | E4: 7000 | F4: 21000 | G4: 28000 | H4: 35000 | I4: 14000
A5: 103 | B5: 30000 | C5: 30000 | D5: 0 | E5: 0 | F5: 0 | G5: 10000 | H5: =7500+2500 -> 10000 | I5: 0
A6: 104 | B6: 84000 | C6: 84000 | D6: 0 | E6: 0 | F6: 0 | G6: 28000 | H6: 28000 | I6: 0
A8: 201 | B8: 66000 | C8: 66000 | D8: 0 | E8: 0 | F8: 0 | G8: 22000 | H8: 22000 | I8: 0
A9: 202 | B9: 84000 | C9: 83000 | D9: 1000 | E9: 500 | F9: 1500 | G9: 28000 | H9: 28000 | I9: 1500
A10: 203 | B10: 84000 | C10: 98000 | D10: -14000 | E10: 14000 | F10: 0 | G10: 28000 | H10: 14000 | I10: 14000
A11: 204 | B11: 90000 | C11: 82500 | D11: 7500 | E11: 0 | F11: 7500 | G11: 30000 | H11: 37500 | I11: 0
A13: 301 | B13: 66000 | C13: 60500 | D13: 5500 | E13: 0 | F13: 5500 | G13: 22000 | H13: 22000 | I13: 5500
A14: 302 | B14: 90000 | C14: 90000 | D14: 0 | E14: 0 | F14: 0 | G14: 30000 | H14: 45000 | I14: -15000
A15: 303 | B15: 108000 | C15: 108000 | D15: 0 | E15: 0 | F15: 0 | G15: 36000 | H15: 36000 | I15: 0
A16: 304 | B16: 66000 | C16: 55000 | D16: 11000 | E16: 63000 | F16: 74000 | G16: 22000 | H16: 33000 | I16: 63000
A18: 401 | B18: 90000 | C18: 90000 | D18: 0 | E18: 0 | F18: 0 | G18: 30000 | H18: 22500 | I18: 7500
A19: 402 | B19: 55500 | C19: 44000 | D19: 11500 | E19: 18500 | F19: 30000 | G19: 22000 | H19: 56500 | I19: -4500
A20: 403 | B20: 84000 | C20: 63000 | D20: 21000 | E20: 14000 | F20: 35000 | G20: 28000 | H20: 0 | I20: 63000
... A51: 1004 | B51: 66000 | C51: 60500 | D51: 5500 | E51: 0 | F51: 5500 | G51: 22000 | H51: 22000 | I51: 5500

Sheet Exp
B3: Anum Vista
B4: Expenses - 2023
B5: Particulars | D5: 44927 | F5: 44958 | H5: 44986 | J5: 45017 | L5: 45047 | N5: 45078 | P5: 45108 | R5: 45139 | T5: 45170 | V5: 45200 | X5: 45231 | Z5: 45261 | AB5: 45292 | AD5: 45323 | AF5: 45352 | AH5: 45383 | AJ5: 45413 | AL5: 45444 | AO5: Others - Petty Expenses | AT5: Others - Petty Expenses | AY5: Others - Petty Expenses
B6: Discription | C6: Name | D6: Amount | E6: Date | F6: Amount | G6: Date | H6: Amount | I6: Date | J6: Amount | K6: Date | L6: Amount | M6: Date | N6: Amount | O6: Date | P6: Amount | Q6: Date | R6: Amount | S6: Date | T6: Amount | U6: Date | V6: Amount | W6: Date | X6: Amount | Y6: Date | Z6: Amount | AA6: Date | AB6: Amount | AC6: Date | AD6: Amount | AE6: Date | AF6: Amount | AG6: Date | AH6: Amount | AI6: Date | AJ6: Amount | AK6: Date | AL6: Amount | AM6: Date | AP6: Particulors | AQ6: Date | AR6: Amount | AU6: Particulors | AV6: Date | AW6: Amount | AZ6: Particulors | BA6: Date | BB6: Amount
B7: Water Tanker | C7: Abid | D7: 8500 | E7: 44951 | F7: =8500+8500+8500 -> 25500 | G7: 9,10 Feb | J7: 8500 | K7: 45026 | L7: 8500 | M7: 45048 | N7: 8500 | O7: 45088 | P7: =9000+9000+9000 -> 27000 | Q7: 45111 | R7: 9000 | S7: 45140 | T7: =9000+9000 -> 18000 | U7: 45182 | V7: 10000 | W7: 45201 | X7: 10000 | Y7: 45234 | Z7: =10000*6 -> 60000 | AA7: 1-6 Dec | AB7: 20000 | AC7: 45292 | AD7: 30000 | AE7: 2,8 Feb | AF7: 20000 | AG7: 1,2 Mar | AH7: 11500 | AI7: 45406 | AO7: 1 | AP7: Clearing Material - Albert | AQ7: 44932 | AR7: 1300 | AT7: 1 | AU7: Tube | AV7: 45170 | AW7: 250 | AY7: 1 | AZ7: Clearing Material - Albert | BA7: 45296 | BB7: 4500
C8: Abid | D8: =8500+8500 -> 17000 | E8: 28,29 Jan | F8: =8500+8500 -> 17000 | G8: 11, 13 Feb | J8: 8500 | K8: 45027 | L8: =8500+8500 -> 17000 | M8: 45054 | N8: =9000+9000+9000 -> 27000 | O8: 22,23,26 Jun | P8: =9000+9000+9000 -> 27000 | Q8: 45113 | R8: 9000 | S8: 45143 | T8: 9000 | U8: 45184 | V8: 10000 | W8: 45203 | X8: =10000*4 -> 40000 | Y8: 45234 | Z8: =10000+10000+10000+10000+10000 -> 50000 | AA8: 7, 8, 9 Dec | AB8: 10000 | AC8: 45292 | AD8: 70000 | AE8: 10,15 Feb | AF8: 34500 | AG8: 3,5 Mar | AO8: 2 | AP8: Garbage Collection | AQ8: 44932 | AR8: 2500 | AT8: 2 | AU8: Mirrir Center TABLE | AV8: 45170 | AW8: 1200 | AY8: 2 | AZ8: Intercom - Monthly Maintenance | BA8: 45306 | BB8: 5000
C9: Abid | D9: =8500+8500+8500 -> 25500 | E9: 30,31 Jan | F9: 8500 | G9: 44971 | J9: 8500 | K9: 45035 | L9: 8500 | M9: 45057 | N9: =9000+9000+9000 -> 27000 | O9: 27,28,30 Jun | P9: 9000 | Q9: 45123 | R9: 9000 | S9: 45148 | T9: 9000 | U9: 45186 | V9: =10000+10000 -> 20000 | W9: 10,12 Oct | X9: =10000+10000 -> 20000 | Y9: 12,15 Nov | Z9: =10000*3 -> 30000 | AA9: 9, 10, 11 Dec | AB9: 70000 | AC9: 5,10 Jan | AD9: 90000 | AE9: 22,29 Feb | AF9: 27500 | AG9: 45356 | AO9: 3 | AP9: Clearing Material - Albert | AQ9: 44938 | AR9: 1000 | AT9: 3 | AU9: Intercom - Monthly Maintenance | AV9: 45177 | AW9: 2500 | AY9: 3 | AZ9: Reception Handle | BA9: 45316 | BB9: 5000
C10: Abid | F10: 8500 | G10: 44976 | J10: =8500+8500+8500 -> 25500 | K10: 45038 | L10: 8500 | M10: 45061 | N10: 9000 | O10: 45107 | P10: 9000 | Q10: 45137 | R10: =9000+9000 -> 18000 | S10: 45152 | T10: 9000 | U10: 45187 | V10: =10000+10000+10000 -> 30000 | W10: 14,16 Oct | X10: =10000+10000 -> 20000 | Y10: 45249 | Z10: =10000*3 -> 30000 | AA10: 45275 | AB10: 60000 | AC10: 13,16 Jan | AD10: 20000 | AE10: 45351 | AF10: 28000 | AG10: 45358 | AO10: 4 | AP10: Tea & biscuits for function | AQ10: 44938 | AR10: 1000 | AT10: 4 | AU10: Garbage Collection | AV10: 45177 | AW10: 2500 | AY10: 4 | AZ10: Tap | BA10: 45316 | BB10: 350
C11: Abid | J11: =8500+8500 -> 17000 | K11: 45039 | L11: =8500 -> 8500 | M11: 45063 | R11: 9000 | S11: 45158 | T11: =9000+10000 -> 19000 | U11: 45190 | V11: =10000+20000 -> 30000 | W11: 18,20 Oct | X11: =10000+10000+10000+10000 -> 40000 | Y11: 20,23,24 Nov | Z11: =10000*4 -> 40000 | AA11: 45276 | AB11: 60000 | AC11: 25,31 Jan | AO11: 5 | AP11: Clearing Material - Albert | AQ11: 44945 | AR11: 5000 | AT11: 5 | AU11: Clearing Material - Albert | AV11: 45184 | AW11: 1000 | AY11: 5
C12: Abid | J12: 8500 | K12: 45045 | L12: =8500+8500 -> 17000 | M12: 45066 | R12: . | V12: 10000 | W12: 45224 | X12: =10000*3 -> 30000 | Y12: 45621 | Z12: 40000 | AA12: 18,19,21 Dec | AO12: 6 | AP12: H2O Stop | AQ12: 44945 | AR12: 2000 | AT12: 6 | AU12: Gate & other lock work | AV12: 45190 | AW12: 8900
J13: =8500+8500 -> 17000 | K13: 45046 | L13: 8500 | M13: 45075 | X13: =10000*6 -> 60000 | Y13: 26-30 Nov | Z13: =10000*9 -> 90000 | AA13: 22 - 30 Dec | AO13: 7 | AP13: Intercom - Monthly Maintenance | AQ13: 44946 | AR13: 2500 | AT13: 45170 | AW13: =SUM(AW7:AW12) -> 16350 | AY13: 45292 | BB13: =SUM(BB7:BB12) -> 14850
D14: =SUM(D7:D13) -> 51000 | F14: =SUM(F7:F13) -> 59500 | H14: =SUM(H7:H13) -> 0 | J14: =SUM(J7:J13) -> 93500 | L14: =SUM(L7:L13) -> 76500 | N14: =SUM(N7:N13) -> 71500 | P14: =SUM(P7:P13) -> 72000 | R14: =SUM(R7:R13) -> 54000 | T14: =SUM(T7:T13) -> 64000 | V14: =SUM(V7:V13) -> 110000 | X14: =SUM(X7:X13) -> 220000 | Z14: =SUM(Z7:Z13) -> 340000 | AB14: =SUM(AB7:AB13) -> 220000 | AD14: =SUM(AD7:AD13) -> 210000 | AF14: =SUM(AF7:AF13) -> 110000 | AH14: =SUM(AH7:AH13) -> 11500 | AJ14: =SUM(AJ7:AJ13) -> 0 | AL14: =SUM(AL7:AL13) -> 0 | AO14: 8 | AP14: Community hall | AQ14: 44951 | AR14: 2700
B15: Salaries and Wages | C15: Nadeem - 28000 | D15: 25000 | E15: 44930 | F15: 25000 | G15: 44959 | H15: 25000 | I15: 44986 | J15: 25000 | K15: 45017 | L15: 25000 | M15: 45049 | N15: 25000 | O15: 45079 | P15: 25000 | Q15: 45108 | R15: 24000 | S15: 45142 | T15: 25000 | U15: 45170 | V15: 12500 | W15: 45201 | X15: 14500 | Y15: 45234 | Z15: 28000 | AA15: 45266 | AB15: 28000 | AC15: 45292 | AD15: 28000 | AE15: 45324 | AF15: 28000 | AG15: 45358 | AH15: 28000 | AI15: 45383 | AJ15: 28000 | AK15: 45414 | AO15: 9 | AP15: Towel Fabric | AQ15: 44957 | AR15: 1000 | AT15: 1 | AU15: Glass for table | AV15: 45201 | AW15: 1000 | AY15: 1 | AZ15: Clearing Material - Albert | BA15: 45332 | BB15: 5300
C16: Imam Sb - 20000 from Feb | D16: 18000 | E16: 44929 | F16: 20000 | G16: 44958 | H16: 20000 | I16: 44988 | J16: 20000 | K16: 45017 | L16: 20000 | M16: 45049 | N16: 20000 | O16: 45079 | P16: 20000 | Q16: 45108 | R16: 20000 | S16: 45142 | T16: 22000 | U16: 45170 | V16: 20000 | W16: 45201 | X16: 24000 | Y16: 45233 | Z16: 22000 | AA16: 45266 | AB16: 22000 | AC16: 45292 | AD16: 22000 | AE16: 45326 | AF16: 22000 | AG16: 45358 | AH16: 22000 | AI16: 45383 | AJ16: 22000 | AK16: 45414 | AO16: 10 | AP16: Motor Pana | AQ16: 44957 | AR16: 1000 | AT16: 2 | AU16: Vacume Cleaner repair | AV16: 45202 | AW16: 3600 | AY16: 2 | AZ16: Garbage Collection | BA16: 45336 | BB16: 3000
C17: Jahangir 17000 + 1000 Attendance Allowance | D17: 18000 | E17: 44929 | F17: 17000 | G17: 44958 | H17: 17000 | I17: 44988 | J17: 19000 | K17: 45019 | L17: 18000 | M17: 45049 | N17: 14000 | O17: 45079 | P17: 17000 | Q17: 45108 | R17: 13000 | S17: 45142 | T17: 16000 | U17: 45170 | V17: 17000 | W17: 45201 | X17: 17000 | Y17: 45233 | Z17: 12000 | AA17: 45266 | AB17: 7500 | AC17: 45292 | AD17: 17000 | AE17: 45326 | AF17: 18000 | AG17: 45358 | AH17: 18000 | AI17: 45383 | AJ17: 18000 | AK17: 45414 | AO17: 44927 | AR17: =SUM(AR7:AR16) -> 20000 | AT17: 3 | AU17: Drinking Water - Aqua | AV17: 45202 | AW17: 2100 | AY17: 3 | AZ17: Outside guter cover | BA17: 45344 | BB17: 800
C18: Ali - 15000 + 1000 Attendance Allowance | D18: 16000 | E18: 44930 | F18: 16000 | G18: 44958 | H18: 16000 | I18: 44986 | J18: 17000 | K18: 45019 | L18: 16000 | M18: 45049 | N18: 18000 | O18: 45079 | P18: 18000 | Q18: 45108 | R18: 18000 | S18: 45142 | T18: 18000 | U18: 45170 | V18: 18000 | W18: 45201 | X18: 18000 | Y18: 45234 | Z18: 18000 | AA18: 45266 | AB18: 18000 | AC18: 45292 | AD18: 11000 | AE18: 45326 | AF18: 19000 | AG18: 45358 | AH18: 20000 | AI18: 45383 | AJ18: 19000 | AK18: 45414 | AT18: 4 | AU18: Intercom - Monthly Maintenance | AV18: 45202 | AW18: 2500 | AY18: 4 | AZ18: Intercom - Monthly Maintenance | BA18: 45347 | BB18: 2500
C19: Shahzad - Sajjid - Full and Final Sajjid 15/5/2023 | D19: 16000 | E19: 44929 | F19: 20000 | G19: 44959 | H19: 20000 | I19: 44989 | J19: 20000 | K19: 45017 | L19: =23000+10000 -> 33000 | M19: 45049 | AO19: 1 | AP19: Garbage Collection | AQ19: 44964 | AR19: 2500 | AT19: 5 | AU19: Drinking Water - Aqua | AV19: 45209 | AW19: 4360 | AY19: 5 | AZ19: Welding gate | BA19: 45347 | BB19: 3500
C20: Adnan - 15000 + 1000 Attendance Allowance | D20: 15000 | E20: 44929 | F20: 15000 | G20: 44958 | H20: 16000 | I20: 44988 | J20: 17000 | K20: 45019 | L20: 15000 | M20: 45049 | N20: 13000 | O20: 45079 | P20: 17000 | Q20: 45108 | R20: 17000 | S20: 45142 | T20: 17000 | U20: 45170 | V20: 17000 | W20: 45201 | X20: 18000 | Y20: 45233 | Z20: 18000 | AA20: 45266 | AB20: 18000 | AC20: 45292 | AD20: 17000 | AE20: 45324 | AF20: 17000 | AG20: 45358 | AH20: 18000 | AI20: 45383 | AJ20: 18000 | AK20: 45414 | AO20: 2 | AP20: Dinner | AQ20: 44965 | AR20: 1000 | AT20: 6 | AU20: Garbage Collection | AV20: 45209 | AW20: 2500 | AY20: 6
B21: Janitorial | C21: Albert - 30000 from Jan | D21: 30000 | E21: 44930 | F21: 30000 | G21: 44959 | H21: 30000 | I21: 44989 | J21: 30000 | K21: 45019 | L21: 30000 | M21: 45049 | N21: 30000 | O21: 45083 | P21: 30000 | Q21: 45108 | R21: 30000 | S21: 45142 | T21: 30000 | U21: 45170 | V21: 30000 | W21: 45201 | X21: 30000 | Y21: 45233 | Z21: 30000 | AA21: 45266 | AB21: 32000 | AC21: 45292 | AD21: 32000 | AE21: 45326 | AF21: 32000 | AG21: 45358 | AH21: 32000 | AI21: 45383 | AJ21: 32000 | AK21: 45414 | AO21: 3 | AP21: Vacume Maintenance | AQ21: 44965 | AR21: 400 | AT21: 7 | AU21: Clearing Material - Albert | AV21: 45217 | AW21: 4800 | AY21: 7
C22: Albert - 15000 Additional resource | H22: 15000 | I22: 44989 | J22: 15000 | K22: 45019 | L22: 17000 | M22: 45049 | N22: 17000 | O22: 45083 | P22: 18000 | Q22: 45108 | R22: 18000 | S22: 45142 | T22: 17000 | U22: 45170 | V22: 18000 | W22: 45201 | X22: 17000 | Y22: 45233 | Z22: 18000 | AA22: 45266 | AB22: 23000 | AC22: 45292 | AD22: 23000 | AE22: 45326 | AF22: 23000 | AG22: 45358 | AH22: 23000 | AI22: 45383 | AJ22: 23000 | AK22: 45414 | AO22: 4 | AP22: Intercom - Monthly Maintenance | AQ22: 44965 | AR22: 2500 | AT22: 8 | AU22: Color | AV22: 45217 | AW22: 280 | AY22: 8
D23: =SUM(D15:D22) -> 138000 | F23: =SUM(F15:F22) -> 143000 | H23: =SUM(H15:H22) -> 159000 | J23: =SUM(J15:J22) -> 163000 | L23: =SUM(L15:L22) -> 174000 | N23: =SUM(N15:N22) -> 137000 | P23: =SUM(P15:P22) -> 145000 | R23: =SUM(R15:R22) -> 140000 | T23: =SUM(T15:T22) -> 145000 | V23: =SUM(V15:V22) -> 132500 | X23: =SUM(X15:X22) -> 138500 | Z23: =SUM(Z15:Z22) -> 146000 | AB23: =SUM(AB15:AB22) -> 148500 | AD23: =SUM(AD15:AD22) -> 150000 | AF23: =SUM(AF15:AF22) -> 159000 | AH23: =SUM(AH15:AH22) -> 161000 | AJ23: =SUM(AJ15:AJ22) -> 160000 | AL23: =SUM(AL15:AL22) -> 0 | AO23: 5 | AP23: Vacume bag repair | AQ23: 44971 | AR23: 1000 | AT23: 9 | AU23: Simentex | AV23: 45217 | AW23: 500 | AY23: 45323 | BB23: =SUM(BB15:BB22) -> 15100
B24: Security Guards | C24: Guard 1 | D24: 25000 | E24: 44930 | F24: 25000 | G24: 44964 | H24: 25000 | I24: 44989 | J24: 25000 | K24: 45026 | L24: 25000 | M24: 45049 | N24: 25000 | O24: 45083 | P24: 25000 | Q24: 45113 | R24: 25000 | S24: 45143 | T24: 25000 | U24: 45177 | V24: 25000 | W24: 45203 | X24: 25000 | Y24: 45240 | Z24: 25000 | AA24: 45268 | AB24: 25000 | AC24: 45299 | AD24: 25000 | AE24: 45332 | AF24: 25000 | AG24: 45356 | AH24: 25000 | AI24: 45384 | AJ24: 25000 | AK24: 45430 | AO24: 6 | AP24: Clearing Material - Albert | AQ24: 44976 | AR24: 7500 | AT24: 45200 | AW24: =SUM(AW15:AW23) -> 21640
C25: Guard 2 | D25: 25000 | E25: 44930 | F25: 25000 | G25: 44964 | H25: 25000 | I25: 44989 | J25: 25000 | K25: 45026 | L25: 25000 | M25: 45049 | N25: 25000 | O25: 45083 | P25: 25000 | Q25: 45113 | R25: 25000 | S25: 45143 | T25: 25000 | U25: 45177 | V25: 25000 | W25: 45203 | X25: 25000 | Y25: 45240 | Z25: 25000 | AA25: 45268 | AB25: 25000 | AC25: 45299 | AD25: 25000 | AE25: 45332 | AF25: 25000 | AG25: 45356 | AH25: 25000 | AI25: 45384 | AJ25: 25000 | AK25: 45430 | AO25: 7 | AP25: Key Making | AQ25: 44980 | AR25: 1500 | AY25: 1 | AZ25: Garbage Collection | BA25: 45356 | BB25: 3000
D26: =SUM(D24:D25) -> 50000 | F26: =SUM(F24:F25) -> 50000 | H26: =SUM(H24:H25) -> 50000 | J26: =SUM(J24:J25) -> 50000 | L26: =SUM(L24:L25) -> 50000 | N26: =SUM(N24:N25) -> 50000 | P26: =SUM(P24:P25) -> 50000 | R26: =SUM(R24:R25) -> 50000 | T26: =SUM(T24:T25) -> 50000 | V26: =SUM(V24:V25) -> 50000 | X26: =SUM(X24:X25) -> 50000 | Z26: =SUM(Z24:Z25) -> 50000 | AB26: =SUM(AB24:AB25) -> 50000 | AD26: =SUM(AD24:AD25) -> 50000 | AF26: =SUM(AF24:AF25) -> 50000 | AH26: =SUM(AH24:AH25) -> 50000 | AJ26: =SUM(AJ24:AJ25) -> 50000 | AL26: =SUM(AL24:AL25) -> 0 | AO26: 8 | AP26: Pana - rent | AQ26: 44980 | AR26: 500 | AT26: 1 | AU26: Garbage Collection | AV26: 45240 | AW26: 2500 | AY26: 2 | AZ26: Clearing Material - Albert | BA26: 45362 | BB26: 7000
B27: Lift Work + Monthly Maintenance | C27: Monthly Maintenance | D27: 8500 | E27: 44932 | H27: 8500 | I27: 44989 | J27: 8500 | K27: 45019 | L27: 8500 | M27: 45057 | N27: 8500 | O27: 45087 | P27: 8500 | Q27: 45111 | R27: 8500 | S27: 45140 | T27: 8500 | U27: 45170 | V27: 9800 | W27: 45209 | X27: 8500 | Y27: 45239 | Z27: 9000 | AA27: 45267 | AB27: 9600 | AC27: 45292 | AD27: 9500 | AE27: 45330 | AF27: 9500 | AG27: 45376 | AH27: 9500 | AI27: 45412 | AJ27: 9500 | AK27: 45430 | AO27: 44958 | AR27: =SUM(AR19:AR26) -> 16900 | AT27: 2 | AU27: Clearing Material - Albert | AV27: 45240 | AW27: 1300 | AY27: 3 | AZ27: Intercom - Monthly Maintenance | BA27: 45371 | BB27: 5000 | BD27: Extra paid ?
C28: Oil, Diesel, Rope | D28: 2200 | E28: 44945 | R28: =14300-500-8500 -> 5300 | S28: 45140 | AB28: 14900 | AC28: 45301 | AJ28: =1100+1100 -> 2200 | AK28: 45414 | AT28: 3 | AU28: Intercom - 2 months Aug not paid | AV28: 45242 | AW28: 5000 | AY28: 4 | AZ28: Somework | BA28: 45371 | BB28: 1000
C29: Drive Switch | F29: 35000 | G29: 44975 | L29: 1650 | M29: 45071 | N29: 6000 | O29: 45087 | X29: 1200 | Y29: 45254 | AH29: 6500 | AI29: 45392 | AO29: 1 | AP29: Mosquito - refil with machine | AQ29: 44986 | AR29: 550 | AT29: 4 | AU29: Lock Play Area | AV29: 45242 | AW29: 1200 | AY29: 5 | AZ29: Tap Water Dispenser | BA29: 45376 | BB29: 1500
C30: Button | J30: =1000+600 -> 1600 | K30: 11, 23 Apr | N30: 1940 | O30: 45091 | T30: 1500 | U30: 45187 | AJ30: 1500 | AK30: 45414 | AO30: 2 | AP30: Clearing Material - Albert | AQ30: 44989 | AR30: 1750 | AT30: 5 | AU30: Clearing Material - Albert | AV30: 45249 | AW30: 5000
N31: 1200 | O31: 45093 | T31: 2200 | U31: 45186 | X31: 1300 | Y31: 45240 | AO31: 3 | AP31: Clearing Material - Albert | AQ31: 44992 | AR31: 2000 | AT31: 6 | AU31: Drinking Water - Aqua | AV31: 45250 | AW31: 4070 | AY31: 45352 | BB31: =SUM(BB25:BB30) -> 17500
R32: 4500 | S32: 45143 | AO32: 4 | AP32: Plants - outside | AQ32: 44992 | AR32: 1500 | AT32: 7 | AU32: Bykea for Lights | AV32: 45248 | AW32: 300
X33: 19500 | Y33: 45249 | Z33: 8500 | AA33: 45269 | AO33: 5 | AP33: Garbage Collection | AQ33: 44992 | AR33: 2500 | AT33: 8 | AY33: 1 | AZ33: Water - Aqua for Staff | BA33: 45384 | BB33: 8800
D34: =SUM(D27:D33) -> 10700 | F34: =SUM(F27:F33) -> 35000 | H34: =SUM(H27:H33) -> 8500 | J34: =SUM(J27:J33) -> 10100 | L34: =SUM(L27:L33) -> 10150 | N34: =SUM(N27:N33) -> 17640 | P34: =SUM(P27:P33) -> 8500 | R34: =SUM(R27:R33) -> 18300 | T34: =SUM(T27:T33) -> 12200 | V34: =SUM(V27:V33) -> 9800 | X34: =SUM(X27:X33) -> 30500 | Z34: =SUM(Z27:Z33) -> 17500 | AB34: =SUM(AB27:AB33) -> 24500 | AD34: =SUM(AD27:AD33) -> 9500 | AF34: =SUM(AF27:AF33) -> 9500 | AH34: =SUM(AH27:AH33) -> 16000 | AJ34: =SUM(AJ27:AJ33) -> 13200 | AL34: =SUM(AL27:AL33) -> 0 | AO34: 6 | AP34: Intercom - Monthly Maintenance | AQ34: 44997 | AR34: 2500 | AT34: 9 | AY34: 2 | AZ34: Garbage Collection | BA34: 45387 | BB34: 3000
B35: Others - Petty Expenses | D35: =+AR17 -> 20000 | F35: =+AR27 -> 16900 | H35: =+AR39 -> 23700 | J35: =+AR54 -> 29236 | L35: =+AR62 -> 28880 | N35: =+AR78 -> 23750 | P35: =+AR87 -> 28000 | R35: =+AR93 -> 5050 | T35: =+AW13 -> 16350 | V35: =+AW24 -> 21640 | X35: =+AW35 -> 19370 | Z35: =+AW46 -> 10850 | AB35: =+BB13 -> 14850 | AC35: Various | AD35: =+BB23 -> 15100 | AE35: Various | AF35: =+BB31 -> 17500 | AG35: Various | AH35: =+BB39 -> 19300 | AI35: Various | AJ35: =+BB47 -> 10200 | AK35: Various | AO35: 7 | AP35: Fan winding | AQ35: 44997 | AR35: 2500 | AT35: 45231 | AW35: =SUM(AW26:AW33) -> 19370 | AY35: 3 | AZ35: Clearing Material - Albert | BA35: 45387 | BB35: 5000
AO36: 8 | AP36: Terpal | AQ36: 45000 | AR36: 3400 | AY36: 4 | AZ36: Intercom - Monthly Maintenance
D37: =SUM(D35:D36) -> 20000 | F37: =SUM(F35:F36) -> 16900 | H37: =SUM(H35:H36) -> 23700 | J37: =SUM(J35:J36) -> 29236 | L37: =SUM(L35:L36) -> 28880 | N37: =SUM(N35:N36) -> 23750 | P37: =SUM(P35:P36) -> 28000 | R37: =SUM(R35:R36) -> 5050 | T37: =SUM(T35:T36) -> 16350 | V37: =SUM(V35:V36) -> 21640 | X37: =SUM(X35:X36) -> 19370 | Z37: =SUM(Z35:Z36) -> 10850 | AB37: =SUM(AB35:AB36) -> 14850 | AD37: =+BB23 -> 15100 | AF37: =SUM(AF35:AF36) -> 17500 | AH37: =SUM(AH35:AH36) -> 19300 | AJ37: =SUM(AJ35:AJ36) -> 10200 | AL37: =SUM(AL35:AL36) -> 0 | AO37: 9 | AP37: Clearing Material - Albert | AQ37: 45007 | AR37: 5000 | AT37: 1 | AU37: Garbage Collection | AV37: 45274 | AW37: 2500 | AY37: 5 | AZ37: Rat Catcher | BA37: 45406 | BB37: 2500
B38: Utilities | C38: KESC | D38: 92067 | E38: 44951 | F38: 83294 | G38: 44980 | H38: 141350 | I38: 45012 | J38: 190119 | K38: 45035 | L38: 182570 | M38: 45071 | N38: 178310 | O38: 45103 | P38: 175868 | Q38: 45125 | R38: 245330 | S38: 45163 | T38: 196511 | U38: 45194 | V38: 226152 | W38: 45225 | X38: 220934 | Y38: 45257 | Z38: 256531 | AA38: 45292 | AB38: 199495 | AC38: 45321 | AD38: 182471 | AE38: 45351 | AF38: 182901 | AG38: 45382 | AO38: 10 | AP38: Lock Children play area | AQ38: 45012 | AR38: 2000 | AT38: 2 | AU38: Vacume Cleaner rpair | AV38: 45279 | AW38: 1500
AO39: 44986 | AR39: =SUM(AR29:AR38) -> 23700 | AT39: 3 | AU39: Photo Copy | AV39: 45279 | AW39: 100 | AY39: 45383 | BB39: =SUM(BB33:BB38) -> 19300
D40: =SUM(D38:D39) -> 92067 | F40: =SUM(F38:F39) -> 83294 | H40: =SUM(H38:H39) -> 141350 | J40: =SUM(J38:J39) -> 190119 | L40: =SUM(L38:L39) -> 182570 | N40: =SUM(N38:N39) -> 178310 | P40: =SUM(P38:P39) -> 175868 | R40: =SUM(R38:R39) -> 245330 | T40: =SUM(T38:T39) -> 196511 | V40: =SUM(V38:V39) -> 226152 | X40: =SUM(X38:X39) -> 220934 | Z40: =SUM(Z38:Z39) -> 256531 | AB40: =SUM(AB38:AB39) -> 199495 | AD40: =SUM(AD38:AD39) -> 182471 | AF40: =SUM(AF38:AF39) -> 182901 | AH40: =SUM(AH38:AH39) -> 0 | AJ40: =SUM(AJ38:AJ39) -> 0 | AL40: =SUM(AL38:AL39) -> 0 | AT40: 4 | AU40: Clearing Material - Albert | AV40: 45281 | AW40: 5000
B41: Electrical work Expenses | C41: Electric Breaker | D41: 11400 | E41: 44947 | J41: 20400 | K41: 45045 | X41: 26240 | Y41: 45248 | AF41: 700 | AG41: 45371 | AH41: 1000 | AI41: 45406 | AO41: 1 | AP41: Garbage Collection | AQ41: 45024 | AR41: 2500 | AT41: 5 | AU41: Drinking Water - Aqua | AV41: 45283 | AW41: 1750 | AY41: 1 | AZ41: Water - Aqua for Staff
C42: Lights for building | D42: 16230 | E42: 44954 | F42: 2200 | G42: 44971 | R42: 12900 | S42: 45157 | AF42: 19200 | AG42: 45381 | AO42: 2 | AP42: Dinner Worker | AQ42: 45027 | AR42: 1000 | AT42: 6 | AY42: 2 | AZ42: Garbage Collection | BA42: 45414 | BB42: 3000
C43: Labour Paid to Faraz | F43: 2200 | G43: 44971 | L43: 500 | M43: 45074 | R43: 6000 | S43: 45169 | X43: =4000 -> 4000 | Y43: 45259 | Z43: 3460 | AA43: 45267 | AF43: 2000 | AG43: 45382 | AO43: 3 | AP43: Clearing Material - Albert | AQ43: 45027 | AR43: 1000 | AT43: 7 | AY43: 3 | AZ43: Clearing Material - Albert | BA43: 45414 | BB43: 6500
C44: Fan Repairing | J44: 7900 | K44: 45039 | T44: 3800 | U44: 45187 | AJ44: 2500 | AK44: 45430 | AO44: 4 | AP44: Air freshner + Cells | AQ44: 45029 | AR44: 3346 | AT44: 8 | AY44: 4 | AZ44: Intercom - Monthly Maintenance
C45: Fan Winding | P45: =3600+10530 -> 14130 | Q45: 45112 | AJ45: 5000 | AK45: 45437 | AO45: 5 | AP45: Grren Tea - Taraweah | AQ45: 45029 | AR45: 180 | AT45: 9 | AY45: 5 | AZ45: Better Charger - Terminal | BA45: 45414 | BB45: 700
V46: 2000 | W46: 45201 | AO46: 6 | AP46: H2O Stop | AQ46: 45035 | AR46: 2000 | AT46: 45261 | AW46: =SUM(AW37:AW44) -> 10850 | AY46: 6
D47: =SUM(D41:D46) -> 27630 | F47: =SUM(F41:F46) -> 4400 | H47: =SUM(H41:H46) -> 0 | J47: =SUM(J41:J46) -> 28300 | L47: =SUM(L41:L46) -> 500 | N47: =SUM(N41:N46) -> 0 | P47: =SUM(P41:P46) -> 14130 | R47: =SUM(R41:R46) -> 18900 | T47: =SUM(T41:T46) -> 3800 | V47: =SUM(V41:V46) -> 2000 | X47: =SUM(X41:X46) -> 30240 | Z47: =SUM(Z41:Z46) -> 3460 | AB47: =SUM(AB41:AB46) -> 0 | AD47: =SUM(AD41:AD46) -> 0 | AF47: =SUM(AF41:AF46) -> 21900 | AH47: =SUM(AH41:AH46) -> 1000 | AJ47: =SUM(AJ41:AJ46) -> 7500 | AL47: =SUM(AL41:AL46) -> 0 | AO47: 7 | AP47: Intercom - Monthly Maintenance | AQ47: 45035 | AR47: 2500 | AY47: 45383 | BB47: =SUM(BB41:BB46) -> 10200
B48: Generator & Diesel Exp | C48: Maintenance | F48: 25800 | G48: 44966 | AO48: 8 | AP48: Cleaning complete hall | AQ48: 45035 | AR48: 5330
C49: Diesel + Cartage | D49: 5000 | E49: 44945 | F49: =5000+5000+5000 -> 15000 | G49: 44980 | H49: 5000 | I49: 44998 | J49: 5000 | K49: 45035 | L49: 5000 | M49: 45061 | N49: 5000 | O49: 45083 | P49: 5000 | Q49: 45123 | R49: 5000 | S49: 45140 | T49: 5000 | U49: 45177 | V49: 5000 | W49: 45201 | X49: 5000 | Y49: 45234 | Z49: 5000 | AA49: 45265 | AB49: 5000 | AC49: 45304 | AD49: 5000 | AE49: 45330 | AF49: 5000 | AG49: 45362 | AJ49: 5000 | AK49: 45437 | AO49: 9 | AP49: chip pip | AQ49: 45035 | AR49: 300
C50: Diesel + Cartage | D50: =5000+5000+5000 -> 15000 | E50: 44948 | F50: 5000 | G50: 44981 | J50: 5000 | K50: 45038 | L50: 5000 | M50: 45063 | N50: =5000+5000 -> 10000 | O50: 45087 | P50: 5000 | Q50: 45133 | R50: 5000 | S50: 45148 | T50: 5000 | U50: 45182 | V50: 5000 | W50: 45203 | X50: =5000+5000 -> 10000 | Y50: 45236 | Z50: 5000 | AA50: 45266 | AB50: =5000+5000 -> 10000 | AC50: 45306 | AF50: 5000 | AG50: 45376 | AJ50: 5000 | AK50: 45437 | AO50: 10 | AP50: Clearing Material - Albert | AQ50: 45035 | AR50: 4000
C51: Diesel + Cartage | D51: =5000+5000+5000 -> 15000 | E51: 44951 | F51: 5000 | G51: 44983 | J51: 5000 | K51: 45045 | L51: 5000 | M51: 45066 | N51: 5000 | O51: 45088 | R51: =5000+5000 -> 10000 | S51: 45158 | T51: 5000 | U51: 45184 | V51: =5000+5000+5000 -> 15000 | W51: 45211 | X51: 5000 | Y51: 45240 | Z51: 5000 | AA51: 45266 | AB51: 5000 | AC51: 45318 | AO51: 11 | AP51: Mineral Water - Mosque | AQ51: 45035 | AR51: 580
C52: Diesel + Cartage | D52: =5000+5000 -> 10000 | E52: 44951 | L52: 5000 | M52: 45071 | N52: 5000 | O52: 45091 | T52: =5000+5000 -> 10000 | U52: 45186 | V52: =5000+5000 -> 10000 | W52: 45213 | Z52: 5000 | AA52: 45275 | AB52: 5000 | AC52: 45322 | AO52: 12 | AP52: Lock community hall | AQ52: 45046 | AR52: 1000
C53: Diesel + Cartage | D53: 5000 | E53: 44955 | L53: 10000 | M53: 45075 | N53: 5000 | O53: 45093 | T53: 5500 | U53: 45187 | V53: =15000 -> 15000 | W53: 45215 | Z53: 5000 | AA53: 45276 | AO53: 13 | AP53: Clearing Machine | AQ53: 45045 | AR53: 5500
C54: Maintenance | F54: =5400+3000 -> 8400 | G54: 44981 | V54: 5000 | W54: 45224 | Z54: =5000+5000+2500 -> 12500 | AA54: 45278 | AO54: 45017 | AR54: =SUM(AR41:AR53) -> 29236
C55: Diesel + Cartage | N55: =5000+5000+5000 -> 15000 | O55: 45098
C56: Diesel + Cartage | AO56: 1 | AP56: Garbage Collection | AQ56: 45048 | AR56: 2500
D57: =SUM(D48:D56) -> 50000 | F57: =SUM(F48:F56) -> 59200 | H57: =SUM(H48:H56) -> 5000 | J57: =SUM(J48:J56) -> 15000 | L57: =SUM(L48:L56) -> 30000 | N57: =SUM(N48:N56) -> 45000 | P57: =SUM(P48:P56) -> 10000 | R57: =SUM(R48:R56) -> 20000 | T57: =SUM(T48:T56) -> 30500 | V57: =SUM(V48:V56) -> 55000 | X57: =SUM(X48:X56) -> 20000 | Z57: =SUM(Z48:Z56) -> 37500 | AB57: =SUM(AB48:AB56) -> 25000 | AD57: =SUM(AD48:AD56) -> 5000 | AF57: =SUM(AF48:AF56) -> 10000 | AH57: =SUM(AH48:AH56) -> 0 | AJ57: =SUM(AJ48:AJ56) -> 10000 | AL57: =SUM(AL48:AL56) -> 0 | AO57: 2 | AP57: Intercom - Monthly Maintenance | AQ57: 45061 | AR57: 2500
B58: Building Clolour | C58: Material - All floors & Parking | L58: 236810 | M58: Various | N58: 314940 | O58: Various | R58: 104150 | S58: Various | AO58: 3 | AP58: Clearing Material - Albert | AQ58: 45061 | AR58: 6000
C59: Labour Paid | L59: 175000 | M59: Various | N59: 100000 | O59: Various | R59: 56500 | S59: Various | AO59: 4 | AP59: H2O Stop | AQ59: 45063 | AR59: 2880
N60: 80000 | O60: Various
N61: 33000 | O61: Various | AO61: 5 | AP61: Wood and Carpentor Labour for duct | AQ61: 45071 | AR61: 15000
L62: =SUM(L58:L61) -> 411810 | N62: =SUM(N58:N61) -> 527940 | R62: =SUM(R58:R61) -> 160650 | AB62: =SUM(AB58:AB61) -> 0 | AD62: =SUM(AD58:AD61) -> 0 | AF62: =SUM(AF58:AF61) -> 0 | AH62: =SUM(AH58:AH61) -> 0 | AJ62: =SUM(AJ58:AJ61) -> 0 | AL62: =SUM(AL58:AL61) -> 0 | AO62: 45047 | AR62: =SUM(AR56:AR61) -> 28880
B63: Plants for Building | AD63: 44000 | AE63: 45347 | AF63: 0
B64: Vacume Cleaner | AF64: 15900 | AG64: 45368
AB65: =SUM(AB63:AB64) -> 0 | AD65: =SUM(AD63:AD64) -> 44000 | AF65: =SUM(AF63:AF64) -> 15900 | AH65: =SUM(AH63:AH64) -> 0 | AJ65: =SUM(AJ63:AJ64) -> 0 | AL65: =SUM(AL63:AL64) -> 0
B66: Play Area Expenses | C66: Table Tennis Rackets + Balls | AD66: 0 | AF66: 7000
C67: Snooker Dabbo Polish + Fusball Service + Material | X67: 42000 | Y67: 45245 | Z67: 50000 | AH67: 8500 | AI67: 45388
X68: =SUM(X66:X67) -> 42000 | Z68: =SUM(Z66:Z67) -> 50000 | AB68: =SUM(AB66:AB67) -> 0 | AD68: =SUM(AD66:AD67) -> 0 | AF68: =SUM(AF66:AF67) -> 7000 | AH68: =SUM(AH66:AH67) -> 8500 | AJ68: =SUM(AJ66:AJ67) -> 0 | AL68: =SUM(AL66:AL67) -> 0
B69: Entertaiment Expense | C69: Annual Function - Dinner + Decoration etc | D69: =200000+70000+5000+3000 -> 278000 | E69: 44950 | AO69: 1 | AP69: Garbage Collection | AQ69: 45083 | AR69: 2500
C70: Fireworks and Cakes on New Year | AO70: 2 | AP70: AC Outer Cleaning | AQ70: 45088 | AR70: 1000
C71: Suits for Staff - On Eid | H71: 19300 | I71: 45015 | AF71: 17000 | AG71: 45374 | AO71: 3 | AP71: Intercom - Monthly Maintenance | AQ71: 45088 | AR71: 2500
C72: Cricket for Residence | X72: 19800 | Y72: 45235 | AO72: 4 | AP72: Parking Wash material + Labour | AQ72: 45091 | AR72: =500+2000 -> 2500
D73: =SUM(D69:D71) -> 278000 | F73: =SUM(F69:F71) -> 0 | H73: =SUM(H69:H71) -> 19300 | J73: =SUM(J69:J71) -> 0 | L73: =SUM(L69:L71) -> 0 | N73: =SUM(N69:N71) -> 0 | P73: =SUM(P69:P71) -> 0 | R73: =SUM(R69:R71) -> 0 | T73: =SUM(T69:T71) -> 0 | V73: =SUM(V69:V71) -> 0 | X73: =SUM(X69:X72) -> 19800 | Z73: =SUM(Z69:Z71) -> 0 | AB73: =SUM(AB69:AB71) -> 0 | AD73: =SUM(AD69:AD71) -> 0 | AF73: =SUM(AF69:AF71) -> 17000 | AH73: =SUM(AH69:AH71) -> 0 | AJ73: =SUM(AJ69:AJ71) -> 0 | AL73: =SUM(AL69:AL71) -> 0 | AO73: 5 | AP73: Clearing Material - Albert | AQ73: 45093 | AR73: 5000
B74: Water - Machine and Plumbering Work | C74: Kashif Motor overhead tank | D74: 5480 | E74: 44938 | L74: 23000 | M74: 45047 | N74: 22330 | O74: 45093 | V74: 23000 | W74: 45203 | AB74: 14500 | AC74: 45304 | AH74: 2200 | AI74: 45387 | AO74: 6 | AP74: Air Freshnor | AQ74: 45093 | AR74: 2600
C75: Material | D75: =5950+600 -> 6550 | E75: 44956 | AB75: 15460 | AC75: 45318 | AH75: 2500 | AI75: 45392 | AO75: 7 | AP75: Plant Pots + Fixing + Labour | AQ75: 45095 | AR75: 6500
C76: Boring Machine | D76: 17000 | E76: 44957 | H76: =10000+500 -> 10500 | I76: 44997 | AF76: 16790 | AG76: 45362 | AO76: 8 | AP76: Tap - Wshroom | AQ76: 45098 | AR76: 500
C77: Kashif Labour - Boring | F77: 6000 | G77: 44964 | L77: 22400 | M77: 45057 | X77: 22000 | Y77: 45250 | AF77: 21000 | AG77: 45362 | AH77: 10020 | AI77: 45406 | AO77: 9 | AP77: Wash Room Parts | AQ77: 45107 | AR77: 650
C78: Motor Repairing with Labour | F78: 8000 | G78: 44964 | L78: 34000 | AH78: 7360 | AI78: 45384 | AO78: 45078 | AR78: =SUM(AR69:AR77) -> 23750
F79: 4470 | G79: 44965 | H79: 5000 | I79: 45002 | J79: =9900+2000 -> 11900 | K79: 45026 | X79: =1950+1500 -> 3450 | Y79: 45236
F80: 78000 | G80: 44968 | J80: 32000 | K80: 45024 | AO80: 1 | AP80: Main Whole Cover | AQ80: 45120 | AR80: 1500
F81: 1000 | G81: 44976 | H81: =2000+1000 -> 3000 | I81: 45007 | J81: 3000 | K81: 45024 | L81: 5500 | M81: 45047 | R81: 1000 | S81: 45148 | V81: 1200 | W81: 45224 | Z81: 15000 | AA81: 45274 | AO81: 2 | AP81: Garbage Collection | AQ81: 45120 | AR81: 2500
J82: =31000+31000 -> 62000 | K82: 45045 | L82: 31000 | M82: 45047 | AO82: 3 | AP82: Intercom - Monthly Maintenance | AQ82: 45123 | AR82: 2500
F83: 5500 | G83: 44980 | J83: 3000 | K83: 45045 | L83: =2500+11500 -> 14000 | M83: 45071 | R83: 5840 | S83: 45152 | V83: 7180 | W83: 45201 | Z83: 5000 | AA83: 45275 | AO83: 4 | AP83: Dispensor Repairing | AQ83: 45123 | AR83: 13000
P84: 6000 | Q84: 45112 | R84: 11780 | S84: 45142 | Z84: 13000 | AA84: 45278 | AO84: 5 | AP84: H2O Stop | AQ84: 45133 | AR84: 2000
